Workbook
Name Peso_1: 'Monte Carlo'!$B$9
Name Peso_2: 'Monte Carlo'!$B$10
Name Peso_3: 'Monte Carlo'!$B$11
Name Peso_4: 'Monte Carlo'!$B$12

Sheet Info
A1: Ideias a ser consideradas
A2: 1 | B2: Construção do índice de força da seleção | L2: FC 26 Player Ratings Reveal
B3: • | C3: Força do elenco: média das notas dos jogadores
C4: FC 26 Player Ratings Reveal | I4: World Football Elo Ratings
C5: Jogadores - FC 26 - 18 de mar. de 2026 | SoFIFA
B6: • | C6: Comissão técnica
C7: Avaliar o treinador: se teve alguma conquista e quanto tempo com a seleção
B8: • | C8: Momento da seleção
C9: analisar os últimos jogos e ver se ganhou, perdeu, no de gols, posição
A10: 2 | B10: Análise dos times e possíveis resultados
B11: Quem venceu? Quem perdeu? Empate?
B12: Número de gols
A13: 3 | B13: Probabilidades para os jogos
A14: 4 | B14: Simulação de vários cenários

Sheet Seleções
A1: id | B1: Seleção | C1: Código | D1: Grupo | E1: Média dos jogadores | F1: Comissão Técnica | G1: Fifa Score | H1: Elo Rating | I1: FS_Norm | J1: ER_norm
A2: 1 | B2: Mexico | C2: MEX | D2: A | E2: =AVERAGEIFS(Tabela11[Nota],Tabela11[Seleção],teams[[#This Row],[Seleção]]) -> 74.230769 | F2: =_xlfn.XLOOKUP(teams[[#This Row],[Seleção]],Comissão!$B$2:$B$49,Comissão!$H$2:$H$49,_xleta.N,0,1) -> 76.083333 | G2: 1681.03 | H2: 1858 | I2: =teams[[#This Row],[Fifa Score]]/20 -> 84.0515 | J2: =(teams[[#This Row],[Elo Rating]]/20)*0.9 -> 83.61 | L2: Jogadores | M2: =E54 -> 72.120119 | O2: Desvio padrão Média dos jogadores | S2: =_xlfn.STDEV.S(teams[Média dos jogadores]) -> 4.7664784
A3: 2 | B3: South Africa | C3: RSA | D3: A | E3: =AVERAGEIFS(Tabela11[Nota],Tabela11[Seleção],teams[[#This Row],[Seleção]]) -> 69.695652 | F3: =_xlfn.XLOOKUP(teams[[#This Row],[Seleção]],Comissão!$B$2:$B$49,Comissão!$H$2:$H$49,_xleta.N,0,1) -> 48.366667 | G3: 1429.73 | H3: 1524 | I3: =teams[[#This Row],[Fifa Score]]/20 -> 71.4865 | J3: =(teams[[#This Row],[Elo Rating]]/20)*0.9 -> 68.58 | L3: Comissão | M3: =F54 -> 62.554514 | O3: Desvio padrão Comissão Técnica | S3: =_xlfn.STDEV.S(teams[Comissão Técnica]) -> 19.486551
A4: 3 | B4: South Korea | C4: KOR | D4: A | E4: =AVERAGEIFS(Tabela11[Nota],Tabela11[Seleção],teams[[#This Row],[Seleção]]) -> 69.384615 | F4: =_xlfn.XLOOKUP(teams[[#This Row],[Seleção]],Comissão!$B$2:$B$49,Comissão!$H$2:$H$49,_xleta.N,0,1) -> 67.9875 | G4: 1588.66 | H4: 1752 | I4: =teams[[#This Row],[Fifa Score]]/20 -> 79.433 | J4: =(teams[[#This Row],[Elo Rating]]/20)*0.9 -> 78.84 | L4: FifaScore | M4: =I54 -> 78.990229 | O4: Desvio padrão FS_Norm | S4: =_xlfn.STDEV.S(teams[FS_Norm]) -> 7.8329911
A5: 4 | B5: Czechia | C5: CZE | D5: A | E5: =AVERAGEIFS(Tabela11[Nota],Tabela11[Seleção],teams[[#This Row],[Seleção]]) -> 70.695652 | F5: =_xlfn.XLOOKUP(teams[[#This Row],[Seleção]],Comissão!$B$2:$B$49,Comissão!$H$2:$H$49,_xleta.N,0,1) -> 28.283333 | G5: 1501.38 | H5: 1726 | I5: =teams[[#This Row],[Fifa Score]]/20 -> 75.069 | J5: =(teams[[#This Row],[Elo Rating]]/20)*0.9 -> 77.67 | L5: EloRating | M5: =J54 -> 80.196563 | O5: Desvio padrão ER_Norm | S5: =_xlfn.STDEV.S(teams[ER_norm]) -> 7.9288405
A6: 5 | B6: Canada | C6: CAN | D6: B | E6: =AVERAGEIFS(Tabela11[Nota],Tabela11[Seleção],teams[[#This Row],[Seleção]]) -> 68.769231 | F6: =_xlfn.XLOOKUP(teams[[#This Row],[Seleção]],Comissão!$B$2:$B$49,Comissão!$H$2:$H$49,_xleta.N,0,1) -> 69.225 | G6: 1556.48 | H6: 1784 | I6: =teams[[#This Row],[Fifa Score]]/20 -> 77.824 | J6: =(teams[[#This Row],[Elo Rating]]/20)*0.9 -> 80.28 | L6: Média Geral | M6: =AVERAGE(M2:M5) -> 73.465356
A7: 6 | B7: Bosnia-Herzegovina | C7: BIH | D7: B | E7: =AVERAGEIFS(Tabela11[Nota],Tabela11[Seleção],teams[[#This Row],[Seleção]]) -> 68 | F7: =_xlfn.XLOOKUP(teams[[#This Row],[Seleção]],Comissão!$B$2:$B$49,Comissão!$H$2:$H$49,_xleta.N,0,1) -> 71.7 | G7: 1385.84 | H7: 1594 | I7: =teams[[#This Row],[Fifa Score]]/20 -> 69.292 | J7: =(teams[[#This Row],[Elo Rating]]/20)*0.9 -> 71.73
A8: 7 | B8: Qatar | C8: QAT | D8: B | E8: =AVERAGEIFS(Tabela11[Nota],Tabela11[Seleção],teams[[#This Row],[Seleção]]) -> 66.4375 | F8: =_xlfn.XLOOKUP(teams[[#This Row],[Seleção]],Comissão!$B$2:$B$49,Comissão!$H$2:$H$49,_xleta.N,0,1) -> 33.516667 | G8: 1454.96 | H8: 1425 | I8: =teams[[#This Row],[Fifa Score]]/20 -> 72.748 | J8: =(teams[[#This Row],[Elo Rating]]/20)*0.9 -> 64.125
A9: 8 | B9: Switzerland | C9: SUI | D9: B | E9: =AVERAGEIFS(Tabela11[Nota],Tabela11[Seleção],teams[[#This Row],[Seleção]]) -> 65.846154 | F9: =_xlfn.XLOOKUP(teams[[#This Row],[Seleção]],Comissão!$B$2:$B$49,Comissão!$H$2:$H$49,_xleta.N,0,1) -> 57.7 | G9: 1649.4 | H9: 1889 | I9: =teams[[#This Row],[Fifa Score]]/20 -> 82.47 | J9: =(teams[[#This Row],[Elo Rating]]/20)*0.9 -> 85.005
A10: 9 | B10: Brazil | C10: BRA | D10: C | E10: =AVERAGEIFS(Tabela11[Nota],Tabela11[Seleção],teams[[#This Row],[Seleção]]) -> 71.083333 | F10: =_xlfn.XLOOKUP(teams[[#This Row],[Seleção]],Comissão!$B$2:$B$49,Comissão!$H$2:$H$49,_xleta.N,0,1) -> 46.279167 | G10: 1761.16 | H10: 1984 | I10: =teams[[#This Row],[Fifa Score]]/20 -> 88.058 | J10: =(teams[[#This Row],[Elo Rating]]/20)*0.9 -> 89.28
A11: 10 | B11: Morocco | C11: MAR | D11: C | E11: =AVERAGEIFS(Tabela11[Nota],Tabela11[Seleção],teams[[#This Row],[Seleção]]) -> 74.62069 | F11: =_xlfn.XLOOKUP(teams[[#This Row],[Seleção]],Comissão!$B$2:$B$49,Comissão!$H$2:$H$49,_xleta.N,0,1) -> 38.570833 | G11: 1755.87 | H11: 1821 | I11: =teams[[#This Row],[Fifa Score]]/20 -> 87.7935 | J11: =(teams[[#This Row],[Elo Rating]]/20)*0.9 -> 81.945
A12: 11 | B12: Haiti | C12: HAI | D12: C | E12: =AVERAGEIFS(Tabela11[Nota],Tabela11[Seleção],teams[[#This Row],[Seleção]]) -> 67.36 | F12: =_xlfn.XLOOKUP(teams[[#This Row],[Seleção]],Comissão!$B$2:$B$49,Comissão!$H$2:$H$49,_xleta.N,0,1) -> 62.366667 | G12: 1291.71 | H12: 1532 | I12: =teams[[#This Row],[Fifa Score]]/20 -> 64.5855 | J12: =(teams[[#This Row],[Elo Rating]]/20)*0.9 -> 68.94
A13: 12 | B13: Scotland | C13: SCO | D13: C | E13: =AVERAGEIFS(Tabela11[Nota],Tabela11[Seleção],teams[[#This Row],[Seleção]]) -> 73.269231 | F13: =_xlfn.XLOOKUP(teams[[#This Row],[Seleção]],Comissão!$B$2:$B$49,Comissão!$H$2:$H$49,_xleta.N,0,1) -> 57.7 | G13: 1498.35 | H13: 1767 | I13: =teams[[#This Row],[Fifa Score]]/20 -> 74.9175 | J13: =(teams[[#This Row],[Elo Rating]]/20)*0.9 -> 79.515
A14: 13 | B14: USA | C14: USA | D14: D | E14: =AVERAGEIFS(Tabela11[Nota],Tabela11[Seleção],teams[[#This Row],[Seleção]]) -> 74.153846 | F14: =_xlfn.XLOOKUP(teams[[#This Row],[Seleção]],Comissão!$B$2:$B$49,Comissão!$H$2:$H$49,_xleta.N,0,1) -> 65.5125 | G14: 1673.13 | H14: 1721 | I14: =teams[[#This Row],[Fifa Score]]/20 -> 83.6565 | J14: =(teams[[#This Row],[Elo Rating]]/20)*0.9 -> 77.445
A15: 14 | B15: Paraguay | C15: PAR | D15: D | E15: =AVERAGEIFS(Tabela11[Nota],Tabela11[Seleção],teams[[#This Row],[Seleção]]) -> 71.269231 | F15: =_xlfn.XLOOKUP(teams[[#This Row],[Seleção]],Comissão!$B$2:$B$49,Comissão!$H$2:$H$49,_xleta.N,0,1) -> 52.75 | G15: 1503.5 | H15: 1833 | I15: =teams[[#This Row],[Fifa Score]]/20 -> 75.175 | J15: =(teams[[#This Row],[Elo Rating]]/20)*0.9 -> 82.485
A16: 15 | B16: Australia | C16: AUS | D16: D | E16: =AVERAGEIFS(Tabela11[Nota],Tabela11[Seleção],teams[[#This Row],[Seleção]]) -> 67.777778 | F16: =_xlfn.XLOOKUP(teams[[#This Row],[Seleção]],Comissão!$B$2:$B$49,Comissão!$H$2:$H$49,_xleta.N,0,1) -> 51.5125 | G16: 1580.67 | H16: 1783 | I16: =teams[[#This Row],[Fifa Score]]/20 -> 79.0335 | J16: =(teams[[#This Row],[Elo Rating]]/20)*0.9 -> 80.235
A17: 16 | B17: Turkiye | C17: TUR | D17: D | E17: =AVERAGEIFS(Tabela11[Nota],Tabela11[Seleção],teams[[#This Row],[Seleção]]) -> 76.344828 | F17: =_xlfn.XLOOKUP(teams[[#This Row],[Seleção]],Comissão!$B$2:$B$49,Comissão!$H$2:$H$49,_xleta.N,0,1) -> 90.366667 | G17: 1599.04 | H17: 1902 | I17: =teams[[#This Row],[Fifa Score]]/20 -> 79.952 | J17: =(teams[[#This Row],[Elo Rating]]/20)*0.9 -> 85.59
A18: 17 | B18: Germany | C18: GER | D18: E | E18: =AVERAGEIFS(Tabela11[Nota],Tabela11[Seleção],teams[[#This Row],[Seleção]]) -> 80.423077 | F18: =_xlfn.XLOOKUP(teams[[#This Row],[Seleção]],Comissão!$B$2:$B$49,Comissão!$H$2:$H$49,_xleta.N,0,1) -> 99.7 | G18: 1730.37 | H18: 1923 | I18: =teams[[#This Row],[Fifa Score]]/20 -> 86.5185 | J18: =(teams[[#This Row],[Elo Rating]]/20)*0.9 -> 86.535
... A31: 30 | B31: Cabo Verde | C31: CPV | D31: H | E31: =AVERAGEIFS(Tabela11[Nota],Tabela11[Seleção],teams[[#This Row],[Seleção]]) -> 69.653846 | F31: =_xlfn.XLOOKUP(teams[[#This Row],[Seleção]],Comissão!$B$2:$B$49,Comissão!$H$2:$H$49,_xleta.N,0,1) -> 57.7 | G31: 1366.13 | H31: 1549 | I31: =teams[[#This Row],[Fifa Score]]/20 -> 68.3065 | J31: =(teams[[#This Row],[Elo Rating]]/20)*0.9 -> 69.705
A32: 31 | B32: Saudi Arabia | C32: KSA | D32: H | E32: =AVERAGEIFS(Tabela11[Nota],Tabela11[Seleção],teams[[#This Row],[Seleção]]) -> 64.225806 | F32: =_xlfn.XLOOKUP(teams[[#This Row],[Seleção]],Comissão!$B$2:$B$49,Comissão!$H$2:$H$49,_xleta.N,0,1) -> 39.704167 | G32: 1421.43 | H32: 1568 | I32: =teams[[#This Row],[Fifa Score]]/20 -> 71.0715 | J32: =(teams[[#This Row],[Elo Rating]]/20)*0.9 -> 70.56 | L32: Desvio padrão Média dos jogadores
A33: 32 | B33: Uruguay | C33: URU | D33: H | E33: =AVERAGEIFS(Tabela11[Nota],Tabela11[Seleção],teams[[#This Row],[Seleção]]) -> 74.848485 | F33: =_xlfn.XLOOKUP(teams[[#This Row],[Seleção]],Comissão!$B$2:$B$49,Comissão!$H$2:$H$49,_xleta.N,0,1) -> 56.4625 | G33: 1673.07 | H33: 1892 | I33: =teams[[#This Row],[Fifa Score]]/20 -> 83.6535 | J33: =(teams[[#This Row],[Elo Rating]]/20)*0.9 -> 85.14 | L33: Desvio padrão Comissão Técnica
A34: 33 | B34: France | C34: FRA | D34: I | E34: =AVERAGEIFS(Tabela11[Nota],Tabela11[Seleção],teams[[#This Row],[Seleção]]) -> 81.8 | F34: =_xlfn.XLOOKUP(teams[[#This Row],[Seleção]],Comissão!$B$2:$B$49,Comissão!$H$2:$H$49,_xleta.N,0,1) -> 90.366667 | G34: 1877.32 | H34: 2082 | I34: =teams[[#This Row],[Fifa Score]]/20 -> 93.866 | J34: =(teams[[#This Row],[Elo Rating]]/20)*0.9 -> 93.69 | L34: Desvio padrão FifaScore
A35: 34 | B35: Senegal | C35: SEN | D35: I | E35: =AVERAGEIFS(Tabela11[Nota],Tabela11[Seleção],teams[[#This Row],[Seleção]]) -> 73.607143 | F35: =_xlfn.XLOOKUP(teams[[#This Row],[Seleção]],Comissão!$B$2:$B$49,Comissão!$H$2:$H$49,_xleta.N,0,1) -> 89.8 | G35: 1688.99 | H35: 1879 | I35: =teams[[#This Row],[Fifa Score]]/20 -> 84.4495 | J35: =(teams[[#This Row],[Elo Rating]]/20)*0.9 -> 84.555 | L35: Desvio padrão EloRating
A36: 35 | B36: Iraq | C36: IRQ | D36: I | E36: =AVERAGEIFS(Tabela11[Nota],Tabela11[Seleção],teams[[#This Row],[Seleção]]) -> 65.071429 | F36: =_xlfn.XLOOKUP(teams[[#This Row],[Seleção]],Comissão!$B$2:$B$49,Comissão!$H$2:$H$49,_xleta.N,0,1) -> 55.6125 | G36: 1447.14 | H36: 1607 | I36: =teams[[#This Row],[Fifa Score]]/20 -> 72.357 | J36: =(teams[[#This Row],[Elo Rating]]/20)*0.9 -> 72.315
A37: 36 | B37: Norway | C37: NOR | D37: I | E37: =AVERAGEIFS(Tabela11[Nota],Tabela11[Seleção],teams[[#This Row],[Seleção]]) -> 73.041667 | F37: =_xlfn.XLOOKUP(teams[[#This Row],[Seleção]],Comissão!$B$2:$B$49,Comissão!$H$2:$H$49,_xleta.N,0,1) -> 67.033333 | G37: 1550.94 | H37: 1912 | I37: =teams[[#This Row],[Fifa Score]]/20 -> 77.547 | J37: =(teams[[#This Row],[Elo Rating]]/20)*0.9 -> 86.04
A38: 37 | B38: Argentina | C38: ARG | D38: J | E38: =AVERAGEIFS(Tabela11[Nota],Tabela11[Seleção],teams[[#This Row],[Seleção]]) -> 77.965517 | F38: =_xlfn.XLOOKUP(teams[[#This Row],[Seleção]],Comissão!$B$2:$B$49,Comissão!$H$2:$H$49,_xleta.N,0,1) -> 99.7 | G38: 1874.81 | H38: 2113 | I38: =teams[[#This Row],[Fifa Score]]/20 -> 93.7405 | J38: =(teams[[#This Row],[Elo Rating]]/20)*0.9 -> 95.085
A39: 38 | B39: Algeria | C39: ALG | D39: J | E39: =AVERAGEIFS(Tabela11[Nota],Tabela11[Seleção],teams[[#This Row],[Seleção]]) -> 71.481481 | F39: =_xlfn.XLOOKUP(teams[[#This Row],[Seleção]],Comissão!$B$2:$B$49,Comissão!$H$2:$H$49,_xleta.N,0,1) -> 76.366667 | G39: 1564.26 | H39: 1743 | I39: =teams[[#This Row],[Fifa Score]]/20 -> 78.213 | J39: =(teams[[#This Row],[Elo Rating]]/20)*0.9 -> 78.435
A40: 39 | B40: Austria | C40: AUT | D40: J | E40: =AVERAGEIFS(Tabela11[Nota],Tabela11[Seleção],teams[[#This Row],[Seleção]]) -> 76.285714 | F40: =_xlfn.XLOOKUP(teams[[#This Row],[Seleção]],Comissão!$B$2:$B$49,Comissão!$H$2:$H$49,_xleta.N,0,1) -> 76.366667 | G40: 1593.45 | H40: 1827 | I40: =teams[[#This Row],[Fifa Score]]/20 -> 79.6725 | J40: =(teams[[#This Row],[Elo Rating]]/20)*0.9 -> 82.215
A41: 40 | B41: Jordan | C41: JOR | D41: J | E41: =AVERAGEIFS(Tabela11[Nota],Tabela11[Seleção],teams[[#This Row],[Seleção]]) -> 65.407407 | F41: =_xlfn.XLOOKUP(teams[[#This Row],[Seleção]],Comissão!$B$2:$B$49,Comissão!$H$2:$H$49,_xleta.N,0,1) -> 64.558333 | G41: 1391.45 | H41: 1690 | I41: =teams[[#This Row],[Fifa Score]]/20 -> 69.5725 | J41: =(teams[[#This Row],[Elo Rating]]/20)*0.9 -> 76.05
A42: 41 | B42: Portugal | C42: POR | D42: K | E42: =AVERAGEIFS(Tabela11[Nota],Tabela11[Seleção],teams[[#This Row],[Seleção]]) -> 80.2 | F42: =_xlfn.XLOOKUP(teams[[#This Row],[Seleção]],Comissão!$B$2:$B$49,Comissão!$H$2:$H$49,_xleta.N,0,1) -> 67.033333 | G42: 1763.83 | H42: 1984 | I42: =teams[[#This Row],[Fifa Score]]/20 -> 88.1915 | J42: =(teams[[#This Row],[Elo Rating]]/20)*0.9 -> 89.28
A43: 42 | B43: Congo | C43: COD | D43: K | E43: =AVERAGEIFS(Tabela11[Nota],Tabela11[Seleção],teams[[#This Row],[Seleção]]) -> 72.52381 | F43: =_xlfn.XLOOKUP(teams[[#This Row],[Seleção]],Comissão!$B$2:$B$49,Comissão!$H$2:$H$49,_xleta.N,0,1) -> 76.366667 | G43: 1478.35 | H43: 1655 | I43: =teams[[#This Row],[Fifa Score]]/20 -> 73.9175 | J43: =(teams[[#This Row],[Elo Rating]]/20)*0.9 -> 74.475
A44: 43 | B44: Uzbekistan | C44: UZB | D44: K | E44: =AVERAGEIFS(Tabela11[Nota],Tabela11[Seleção],teams[[#This Row],[Seleção]]) -> 68.576923 | F44: =_xlfn.XLOOKUP(teams[[#This Row],[Seleção]],Comissão!$B$2:$B$49,Comissão!$H$2:$H$49,_xleta.N,0,1) -> 49.425 | G44: 1465.34 | H44: 1727 | I44: =teams[[#This Row],[Fifa Score]]/20 -> 73.267 | J44: =(teams[[#This Row],[Elo Rating]]/20)*0.9 -> 77.715
A45: 44 | B45: Colombia | C45: COL | D45: K | E45: =AVERAGEIFS(Tabela11[Nota],Tabela11[Seleção],teams[[#This Row],[Seleção]]) -> 76.230769 | F45: =_xlfn.XLOOKUP(teams[[#This Row],[Seleção]],Comissão!$B$2:$B$49,Comissão!$H$2:$H$49,_xleta.N,0,1) -> 62.366667 | G45: 1693.09 | H45: 1975 | I45: =teams[[#This Row],[Fifa Score]]/20 -> 84.6545 | J45: =(teams[[#This Row],[Elo Rating]]/20)*0.9 -> 88.875
A46: 45 | B46: England | C46: ENG | D46: L | E46: =AVERAGEIFS(Tabela11[Nota],Tabela11[Seleção],teams[[#This Row],[Seleção]]) -> 80.342857 | F46: =_xlfn.XLOOKUP(teams[[#This Row],[Seleção]],Comissão!$B$2:$B$49,Comissão!$H$2:$H$49,_xleta.N,0,1) -> 65.229167 | G46: 1825.97 | H46: 2020 | I46: =teams[[#This Row],[Fifa Score]]/20 -> 91.2985 | J46: =(teams[[#This Row],[Elo Rating]]/20)*0.9 -> 90.9
A47: 46 | B47: Croatia | C47: CRO | D47: L | E47: =AVERAGEIFS(Tabela11[Nota],Tabela11[Seleção],teams[[#This Row],[Seleção]]) -> 75.346154 | F47: =_xlfn.XLOOKUP(teams[[#This Row],[Seleção]],Comissão!$B$2:$B$49,Comissão!$H$2:$H$49,_xleta.N,0,1) -> 71.7 | G47: 1717.07 | H47: 1930 | I47: =teams[[#This Row],[Fifa Score]]/20 -> 85.8535 | J47: =(teams[[#This Row],[Elo Rating]]/20)*0.9 -> 86.85
... A49: 48 | B49: Panama | C49: PAN | D49: L | E49: =AVERAGEIFS(Tabela11[Nota],Tabela11[Seleção],teams[[#This Row],[Seleção]]) -> 68.304348 | F49: =_xlfn.XLOOKUP(teams[[#This Row],[Seleção]],Comissão!$B$2:$B$49,Comissão!$H$2:$H$49,_xleta.N,0,1) -> 67.033333 | G49: 1540.64 | H49: 1737 | I49: =teams[[#This Row],[Fifa Score]]/20 -> 77.032 | J49: =(teams[[#This Row],[Elo Rating]]/20)*0.9 -> 78.165
G51: link | H51: link
B54: Média | E54: =AVERAGE(teams[Média dos jogadores]) -> 72.120119 | F54: =AVERAGE(teams[Comissão Técnica]) -> 62.554514 | G54: =AVERAGE(teams[Fifa Score]) -> 1579.8046 | H54: =AVERAGE(teams[Elo Rating]) -> 1782.1458 | I54: =AVERAGE(teams[FS_Norm]) -> 78.990229 | J54: =AVERAGE(teams[ER_norm]) -> 80.196563

Sheet Comissão
A1: id | B1: Seleção | C1: Treinador | D1: Longevidade (meses) - 04/26 | E1: % Vitórias | F1: % Empates | G1: % Derrotas | H1: Nota Técnica
A2: =Seleções!A2 -> 1 | B2: =Seleções!B2 -> Mexico | C2: =Treinadores!A18 -> Javier Aguirre | D2: 20 | E2: 0.6 | F2: 0.4 | G2: 0 | H2: =(((E2)*3+(F2)*1)/3)*70+(MIN(D2/24,1)*30)*0.99 -> 76.083333
A3: =Seleções!A3 -> 2 | B3: =Seleções!B3 -> South Africa | C3: =Treinadores!A16 -> Hugo Broos | D3: 60 | E3: 0.2 | F3: 0.2 | G3: 0.6 | H3: =(((E3)*3+(F3)*1)/3)*70+(MIN(D3/24,1)*30)*0.99 -> 48.366667
A4: =Seleções!A4 -> 3 | B4: =Seleções!B4 -> South Korea | C4: =Treinadores!A29 -> Myung-bo Hong | D4: 21 | E4: 0.6 | F4: 0 | G4: 0.4 | H4: =(((E4)*3+(F4)*1)/3)*70+(MIN(D4/24,1)*30)*0.99 -> 67.9875
A5: =Seleções!A5 -> 4 | B5: =Seleções!B5 -> Czechia | C5: =Treinadores!A26 -> Miroslav Koubek | D5: 4 | E5: 0.2 | F5: 0.4 | G5: 0.4 | H5: =(((E5)*3+(F5)*1)/3)*70+(MIN(D5/24,1)*30)*0.99 -> 28.283333
A6: =Seleções!A6 -> 5 | B6: =Seleções!B6 -> Canada | C6: =Treinadores!A19 -> Jesse Marsch | D6: 22 | E6: 0.4 | F6: 0.6 | G6: 0 | H6: =(((E6)*3+(F6)*1)/3)*70+(MIN(D6/24,1)*30)*0.99 -> 69.225
A7: =Seleções!A7 -> 6 | B7: =Seleções!B7 -> Bosnia-Herzegovina | C7: =Treinadores!A38 -> Sergej Barbarez | D7: 24 | E7: 0.4 | F7: 0.6 | G7: 0 | H7: =(((E7)*3+(F7)*1)/3)*70+(MIN(D7/24,1)*30)*0.99 -> 71.7
A8: =Seleções!A8 -> 7 | B8: =Seleções!B8 -> Qatar | C8: =Treinadores!A20 -> Julen Lopetegui | D8: 12 | E8: 0.2 | F8: 0.2 | G8: 0.6 | H8: =(((E8)*3+(F8)*1)/3)*70+(MIN(D8/24,1)*30)*0.99 -> 33.516667
A9: =Seleções!A9 -> 8 | B9: =Seleções!B9 -> Switzerland | C9: =Treinadores!A28 -> Murat Yakin | D9: 56 | E9: 0.2 | F9: 0.6 | G9: 0.2 | H9: =(((E9)*3+(F9)*1)/3)*70+(MIN(D9/24,1)*30)*0.99 -> 57.7
A10: =Seleções!A10 -> 9 | B10: =Seleções!B10 -> Brazil | C10: =Treinadores!A4 -> Carlo Ancelotti | D10: 11 | E10: 0.4 | F10: 0.2 | G10: 0.4 | H10: =(((E10)*3+(F10)*1)/3)*70+(MIN(D10/24,1)*30)*0.99 -> 46.279167 | O10: adicionar um bônus para o historico de titulos do treinador
A11: =Seleções!A11 -> 10 | B11: =Seleções!B11 -> Morocco | C11: =Treinadores!A27 -> Mohamed Ouahbi | D11: 1 | E11: 0.4 | F11: 0.4 | G11: 0.2 | H11: =(((E11)*3+(F11)*1)/3)*70+(MIN(D11/24,1)*30)*0.99 -> 38.570833 | O11: por exemplo o ancelotti ganhou um titulo importante ent ele tem um peso maior
A12: =Seleções!A12 -> 11 | B12: =Seleções!B12 -> Haiti | C12: =Treinadores!A42 -> Sébastien Migné | D12: 25 | E12: 0.4 | F12: 0.2 | G12: 0.4 | H12: =(((E12)*3+(F12)*1)/3)*70+(MIN(D12/24,1)*30)*0.99 -> 62.366667 | O12: rodar mais que uma simulação mudando o peso
A13: =Seleções!A13 -> 12 | B13: =Seleções!B13 -> Scotland | C13: =Treinadores!A39 -> Steve Clarke | D13: 82 | E13: 0.4 | F13: 0 | G13: 0.6 | H13: =(((E13)*3+(F13)*1)/3)*70+(MIN(D13/24,1)*30)*0.99 -> 57.7
A14: =Seleções!A14 -> 13 | B14: =Seleções!B14 -> USA | C14: =Treinadores!A25 -> Mauricio Pochettino | D14: 19 | E14: 0.6 | F14: 0 | G14: 0.4 | H14: =(((E14)*3+(F14)*1)/3)*70+(MIN(D14/24,1)*30)*0.99 -> 65.5125
A15: =Seleções!A15 -> 14 | B15: =Seleções!B15 -> Paraguay | C15: =Treinadores!A12 -> Gustavo Alfaro | D15: 20 | E15: 0.4 | F15: 0 | G15: 0.6 | H15: =(((E15)*3+(F15)*1)/3)*70+(MIN(D15/24,1)*30)*0.99 -> 52.75
A16: =Seleções!A16 -> 15 | B16: =Seleções!B16 -> Australia | C16: =Treinadores!A45 -> Tony Popovic | D16: 19 | E16: 0.4 | F16: 0 | G16: 0.6 | H16: =(((E16)*3+(F16)*1)/3)*70+(MIN(D16/24,1)*30)*0.99 -> 51.5125
A17: =Seleções!A17 -> 16 | B17: =Seleções!B17 -> Turkiye | C17: =Treinadores!A46 -> Vincenzo Montella | D17: 31 | E17: 0.8 | F17: 0.2 | G17: 0 | H17: =(((E17)*3+(F17)*1)/3)*70+(MIN(D17/24,1)*30)*0.99 -> 90.366667
A18: =Seleções!A18 -> 17 | B18: =Seleções!B18 -> Germany | C18: =Treinadores!A21 -> Julian Nagelsmann | D18: 31 | E18: 1 | F18: 0 | G18: 0 | H18: =(((E18)*3+(F18)*1)/3)*70+(MIN(D18/24,1)*30)*0.99 -> 99.7
A19: =Seleções!A19 -> 18 | B19: =Seleções!B19 -> Curaçao | C19: =Treinadores!A9 -> Fred Rutten | D19: 1 | E19: 0.2 | F19: 0.4 | G19: 0.4 | H19: =(((E19)*3+(F19)*1)/3)*70+(MIN(D19/24,1)*30)*0.99 -> 24.570833
A20: =Seleções!A20 -> 19 | B20: =Seleções!B20 -> Côte d'Ivoire | C20: =Treinadores!A7 -> Emerse Faé | D20: 2 | E20: 0.8 | F20: 0 | G20: 0.2 | H20: =(((E20)*3+(F20)*1)/3)*70+(MIN(D20/24,1)*30)*0.99 -> 58.475
A21: =Seleções!A21 -> 20 | B21: =Seleções!B21 -> Ecuador | C21: =Treinadores!A37 -> Sebastián Beccacece | D21: 20 | E21: 0.2 | F21: 0.8 | G21: 0 | H21: =(((E21)*3+(F21)*1)/3)*70+(MIN(D21/24,1)*30)*0.99 -> 57.416667
A22: =Seleções!A22 -> 21 | B22: =Seleções!B22 -> Netherlands | C22: =Treinadores!A34 -> Ronald Koeman | D22: 36 | E22: 0.6 | F22: 0.4 | G22: 0 | H22: =(((E22)*3+(F22)*1)/3)*70+(MIN(D22/24,1)*30)*0.99 -> 81.033333
A23: =Seleções!A23 -> 22 | B23: =Seleções!B23 -> Japan | C23: =Treinadores!A13 -> Hajime Moriyasu | D23: 92 | E23: 1 | F23: 0 | G23: 0 | H23: =(((E23)*3+(F23)*1)/3)*70+(MIN(D23/24,1)*30)*0.99 -> 99.7
A24: =Seleções!A24 -> 23 | B24: =Seleções!B24 -> Sweden | C24: =Treinadores!A11 -> Graham Potter | D24: 6 | E24: 0.4 | F24: 0.2 | G24: 0.4 | H24: =(((E24)*3+(F24)*1)/3)*70+(MIN(D24/24,1)*30)*0.99 -> 40.091667
A25: =Seleções!A25 -> 24 | B25: =Seleções!B25 -> Tunisia | C25: =Treinadores!A36 -> Sabri Lamouchi | D25: 3 | E25: 0.2 | F25: 0.6 | G25: 0.2 | H25: =(((E25)*3+(F25)*1)/3)*70+(MIN(D25/24,1)*30)*0.99 -> 31.7125
A26: =Seleções!A26 -> 25 | B26: =Seleções!B26 -> Belgium | C26: =Treinadores!A35 -> Rudi Garcia | D26: 15 | E26: 0.6 | F26: 0.4 | G26: 0 | H26: =(((E26)*3+(F26)*1)/3)*70+(MIN(D26/24,1)*30)*0.99 -> 69.895833
A27: =Seleções!A27 -> 26 | B27: =Seleções!B27 -> Egypt | C27: =Treinadores!A15 -> Hossam Hassan | D27: 26 | E27: 0.6 | F27: 0.2 | G27: 0.2 | H27: =(((E27)*3+(F27)*1)/3)*70+(MIN(D27/24,1)*30)*0.99 -> 76.366667
A28: =Seleções!A28 -> 27 | B28: =Seleções!B28 -> IR Iran | C28: =Treinadores!A2 -> Amir Ghalenoei | D28: 36 | E28: 0.4 | F28: 0.4 | G28: 0.2 | H28: =(((E28)*3+(F28)*1)/3)*70+(MIN(D28/24,1)*30)*0.99 -> 67.033333
A29: =Seleções!A29 -> 28 | B29: =Seleções!B29 -> New Zealand | C29: =Treinadores!A5 -> Darren Bazeley | D29: 33 | E29: 0.2 | F29: 0.2 | G29: 0.6 | H29: =(((E29)*3+(F29)*1)/3)*70+(MIN(D29/24,1)*30)*0.99 -> 48.366667
A30: =Seleções!A30 -> 29 | B30: =Seleções!B30 -> Spain | C30: =Treinadores!A23 -> Luis de la Fuente | D30: 36 | E30: 0.6 | F30: 0.4 | G30: 0 | H30: =(((E30)*3+(F30)*1)/3)*70+(MIN(D30/24,1)*30)*0.99 -> 81.033333
A31: =Seleções!A31 -> 30 | B31: =Seleções!B31 -> Cabo Verde | C31: =Treinadores!A3 -> Bubista | D31: 74 | E31: 0.2 | F31: 0.6 | G31: 0.2 | H31: =(((E31)*3+(F31)*1)/3)*70+(MIN(D31/24,1)*30)*0.99 -> 57.7
A32: =Seleções!A32 -> 31 | B32: =Seleções!B32 -> Saudi Arabia | C32: =Treinadores!A14 -> Hervé Renard | D32: 17 | E32: 0.2 | F32: 0.2 | G32: 0.6 | H32: =(((E32)*3+(F32)*1)/3)*70+(MIN(D32/24,1)*30)*0.99 -> 39.704167
A33: =Seleções!A33 -> 32 | B33: =Seleções!B33 -> Uruguay | C33: =Treinadores!A24 -> Marcelo Bielsa | D33: 23 | E33: 0.2 | F33: 0.6 | G33: 0.2 | H33: =(((E33)*3+(F33)*1)/3)*70+(MIN(D33/24,1)*30)*0.99 -> 56.4625
A34: =Seleções!A34 -> 33 | B34: =Seleções!B34 -> France | C34: =Treinadores!A6 -> Didier Deschamps | D34: 165 | E34: 0.8 | F34: 0.2 | G34: 0 | H34: =(((E34)*3+(F34)*1)/3)*70+(MIN(D34/24,1)*30)*0.99 -> 90.366667
A35: =Seleções!A35 -> 34 | B35: =Seleções!B35 -> Senegal | C35: =Treinadores!A31 -> Pape Thiaw | D35: 16 | E35: 1 | F35: 0 | G35: 0 | H35: =(((E35)*3+(F35)*1)/3)*70+(MIN(D35/24,1)*30)*0.99 -> 89.8
A36: =Seleções!A36 -> 35 | B36: =Seleções!B36 -> Iraq | C36: =Treinadores!A10 -> Graham Arnold | D36: 11 | E36: 0.6 | F36: 0 | G36: 0.4 | H36: =(((E36)*3+(F36)*1)/3)*70+(MIN(D36/24,1)*30)*0.99 -> 55.6125
A37: =Seleções!A37 -> 36 | B37: =Seleções!B37 -> Norway | C37: =Treinadores!A40 -> Ståle Solbakken | D37: 64 | E37: 0.4 | F37: 0.4 | G37: 0.2 | H37: =(((E37)*3+(F37)*1)/3)*70+(MIN(D37/24,1)*30)*0.99 -> 67.033333
A38: =Seleções!A38 -> 37 | B38: =Seleções!B38 -> Argentina | C38: =Treinadores!A22 -> Lionel Scaloni | D38: 92 | E38: 1 | F38: 0 | G38: 0 | H38: =(((E38)*3+(F38)*1)/3)*70+(MIN(D38/24,1)*30)*0.99 -> 99.7
A39: =Seleções!A39 -> 38 | B39: =Seleções!B39 -> Algeria | C39: =Treinadores!A47 -> Vladimir Petkovic | D39: 25 | E39: 0.6 | F39: 0.2 | G39: 0.2 | H39: =(((E39)*3+(F39)*1)/3)*70+(MIN(D39/24,1)*30)*0.99 -> 76.366667
A40: =Seleções!A40 -> 39 | B40: =Seleções!B40 -> Austria | C40: =Treinadores!A32 -> Ralf Rangnick | D40: 46 | E40: 0.6 | F40: 0.2 | G40: 0.2 | H40: =(((E40)*3+(F40)*1)/3)*70+(MIN(D40/24,1)*30)*0.99 -> 76.366667
A41: =Seleções!A41 -> 40 | B41: =Seleções!B41 -> Jordan | C41: =Treinadores!A17 -> Jamal Sellami | D41: 22 | E41: 0.4 | F41: 0.4 | G41: 0.2 | H41: =(((E41)*3+(F41)*1)/3)*70+(MIN(D41/24,1)*30)*0.99 -> 64.558333
A42: =Seleções!A42 -> 41 | B42: =Seleções!B42 -> Portugal | C42: =Treinadores!A33 -> Roberto Martínez | D42: 39 | E42: 0.4 | F42: 0.4 | G42: 0.2 | H42: =(((E42)*3+(F42)*1)/3)*70+(MIN(D42/24,1)*30)*0.99 -> 67.033333
A43: =Seleções!A43 -> 42 | B43: =Seleções!B43 -> Congo | C43: =Treinadores!A41 -> Sébastien Desabre | D43: 44 | E43: 0.6 | F43: 0.2 | G43: 0.2 | H43: =(((E43)*3+(F43)*1)/3)*70+(MIN(D43/24,1)*30)*0.99 -> 76.366667
A44: =Seleções!A44 -> 43 | B44: =Seleções!B44 -> Uzbekistan | C44: =Treinadores!A8 -> Fabio Cannavaro | D44: 6 | E44: 0.4 | F44: 0.6 | G44: 0 | H44: =(((E44)*3+(F44)*1)/3)*70+(MIN(D44/24,1)*30)*0.99 -> 49.425
A45: =Seleções!A45 -> 44 | B45: =Seleções!B45 -> Colombia | C45: =Treinadores!A30 -> Néstor Lorenzo | D45: 45 | E45: 0.4 | F45: 0.2 | G45: 0.4 | H45: =(((E45)*3+(F45)*1)/3)*70+(MIN(D45/24,1)*30)*0.99 -> 62.366667
A46: =Seleções!A46 -> 45 | B46: =Seleções!B46 -> England | C46: =Treinadores!A44 -> Thomas Tuchel | D46: 15 | E46: 0.6 | F46: 0.2 | G46: 0.2 | H46: =(((E46)*3+(F46)*1)/3)*70+(MIN(D46/24,1)*30)*0.99 -> 65.229167
A47: =Seleções!A47 -> 46 | B47: =Seleções!B47 -> Croatia | C47: =Tabela_2[[#This Row],[Treinador]] -> Vladimir Petkovic | D47: 102 | E47: 0.6 | F47: 0 | G47: 0.4 | H47: =(((E47)*3+(F47)*1)/3)*70+(MIN(D47/24,1)*30)*0.99 -> 71.7
A48: =Seleções!A48 -> 47 | B48: =Seleções!B48 -> Ghana | D48: 2 | E48: 0.2 | F48: 0 | G48: 0.8 | H48: =(((E48)*3+(F48)*1)/3)*70+(MIN(D48/24,1)*30)*0.99 -> 16.475
A49: =Seleções!A49 -> 48 | B49: =Seleções!B49 -> Panama | C49: =Treinadores!A43 -> Thomas Christiansen | D49: 68 | E49: 0.4 | F49: 0.4 | G49: 0.2 | H49: =(((E49)*3+(F49)*1)/3)*70+(MIN(D49/24,1)*30)*0.99 -> 67.033333
B52: *Vitorias, empates e derrotas feita verificando o elorating | E52: eloratings.net

Sheet Saldo
A1: id | B1: Seleção | C1: % Vitórias (Últimos 20) | D1: Gols Marcados (GP) | E1: Gols Sofridos (GC) | F1: Saldo de Gols (SG) | G1: Média de gols feitos | H1: Média de gols sofridos
A2: 1 | B2: Mexico | C2: 0.6 | D2: 38 | E2: 21 | F2: =D2-E2 -> 17 | G2: =D2/20 -> 1.9 | H2: =E2/20 -> 1.05
A3: 2 | B3: South Africa | C3: 0.45 | D3: 24 | E3: 22 | F3: =D3-E3 -> 2 | G3: =D3/20 -> 1.2 | H3: =E3/20 -> 1.1
A4: 3 | B4: South Korea | C4: 0.65 | D4: 45 | E4: 18 | F4: =D4-E4 -> 27 | G4: =D4/20 -> 2.25 | H4: =E4/20 -> 0.9
A5: 4 | B5: Czechia | C5: 0.5 | D5: 31 | E5: 26 | F5: =D5-E5 -> 5 | G5: =D5/20 -> 1.55 | H5: =E5/20 -> 1.3
A6: 5 | B6: Canada | C6: 0.5 | D6: 34 | E6: 28 | F6: =D6-E6 -> 6 | G6: =D6/20 -> 1.7 | H6: =E6/20 -> 1.4
A7: 6 | B7: Bosnia-Herzegovina | C7: 0.35 | D7: 22 | E7: 33 | F7: =D7-E7 -> -11 | G7: =D7/20 -> 1.1 | H7: =E7/20 -> 1.65
A8: 7 | B8: Qatar | C8: 0.55 | D8: 36 | E8: 27 | F8: =D8-E8 -> 9 | G8: =D8/20 -> 1.8 | H8: =E8/20 -> 1.35
A9: 8 | B9: Switzerland | C9: 0.45 | D9: 29 | E9: 25 | F9: =D9-E9 -> 4 | G9: =D9/20 -> 1.45 | H9: =E9/20 -> 1.25
A10: 9 | B10: Brazil | C10: 0.7 | D10: 48 | E10: 15 | F10: =D10-E10 -> 33 | G10: =D10/20 -> 2.4 | H10: =E10/20 -> 0.75
A11: 10 | B11: Morocco | C11: 0.65 | D11: 35 | E11: 14 | F11: =D11-E11 -> 21 | G11: =D11/20 -> 1.75 | H11: =E11/20 -> 0.7
A12: 11 | B12: Haiti | C12: 0.3 | D12: 19 | E12: 38 | F12: =D12-E12 -> -19 | G12: =D12/20 -> 0.95 | H12: =E12/20 -> 1.9
A13: 12 | B13: Scotland | C13: 0.4 | D13: 24 | E13: 31 | F13: =D13-E13 -> -7 | G13: =D13/20 -> 1.2 | H13: =E13/20 -> 1.55
... A49: 48 | B49: Panama | C49: 0.45 | D49: 28 | E49: 30 | F49: =D49-E49 -> -2 | G49: =D49/20 -> 1.4 | H49: =E49/20 -> 1.5

Sheet Jogos
A1: date | B1: match_number | C1: group | D1: stadium | E1: date_dt
A2: 46184 | B2: Match 1 | C2: Group A | D2: Mexico City Stadium | E2: 46184
A3: 46184 | B3: Match 2 | C3: Group A | D3: Estadio Guadalajara | E3: 46184
A4: 46185 | B4: Match 3 | C4: Group B | D4: Toronto Stadium | E4: 46185
A5: 46185 | B5: Match 4 | C5: Group D | D5: Los Angeles Stadium | E5: 46185
A6: 46186 | B6: Match 5 | C6: Group C | D6: Boston Stadium | E6: 46186
A7: 46186 | B7: Match 6 | C7: Group D | D7: BC Place Vancouver | E7: 46186
A8: 46186 | B8: Match 7 | C8: Group C | D8: New York New Jersey Stadium | E8: 46186
A9: 46186 | B9: Match 8 | C9: Group B | D9: San Francisco Bay Area Stadium | E9: 46186
A10: 46187 | B10: Match 9 | C10: Group E | D10: Philadelphia Stadium | E10: 46187
A11: 46187 | B11: Match 10 | C11: Group E | D11: Houston Stadium | E11: 46187
A12: 46187 | B12: Match 11 | C12: Group F | D12: Dallas Stadium | E12: 46187
A13: 46187 | B13: Match 12 | C13: Group F | D13: Estadio Monterrey | E13: 46187
... A105: 46222 | B105: Match 104 | C105: Winner match 101 v Winner match 102 | D105: New York New Jersey Stadium | E105: 46222

Sheet Jogadores
A1: Grupo | B1: Seleção | C1: Jogador | D1: Nota | F1: Grupo | G1: Seleção | H1: Média dos jogadores
A2: A | B2: Mexico | C2: Guillermo Ochoa | D2: 74 | F2: A | G2: Mexico | H2: =AVERAGEIFS(Tabela11[Nota],Tabela11[Seleção],G2) -> 74.230769
A3: A | B3: Mexico | C3: Carlos Acevedo | D3: 74 | F3: A | G3: South Africa | H3: =AVERAGEIFS(Tabela11[Nota],Tabela11[Seleção],G3) -> 69.695652
A4: A | B4: Mexico | C4: Raúl Rangel | D4: 76 | F4: A | G4: South Korea | H4: =AVERAGEIFS(Tabela11[Nota],Tabela11[Seleção],G4) -> 69.384615
A5: A | B5: Mexico | C5: Jesús Gallardo | D5: 77 | F5: A | G5: Czechia | H5: =AVERAGEIFS(Tabela11[Nota],Tabela11[Seleção],G5) -> 70.695652
A6: A | B6: Mexico | C6: Jorge Sánchez | D6: 73 | F6: B | G6: Canada | H6: =AVERAGEIFS(Tabela11[Nota],Tabela11[Seleção],G6) -> 68.769231
A7: A | B7: Mexico | C7: César Montes | D7: 75 | F7: B | G7: Bosnia-Herzegovina | H7: =AVERAGEIFS(Tabela11[Nota],Tabela11[Seleção],G7) -> 68
A8: A | B8: Mexico | C8: Jesús Ângulo | D8: 74 | F8: B | G8: Qatar | H8: =AVERAGEIFS(Tabela11[Nota],Tabela11[Seleção],G8) -> 66.4375
A9: A | B9: Mexico | C9: Johan Vásquez | D9: 75 | F9: B | G9: Switzerland | H9: =AVERAGEIFS(Tabela11[Nota],Tabela11[Seleção],G9) -> 65.846154
A10: A | B10: Mexico | C10: Richard Ledezma | D10: 73 | F10: C | G10: Brazil | H10: =AVERAGEIFS(Tabela11[Nota],Tabela11[Seleção],G10) -> 71.083333
A11: A | B11: Mexico | C11: Israel Reyes | D11: 75 | F11: C | G11: Morocco | H11: =AVERAGEIFS(Tabela11[Nota],Tabela11[Seleção],G11) -> 74.62069
A12: A | B12: Mexico | C12: Everardo López | D12: 72 | F12: C | G12: Haiti | H12: =AVERAGEIFS(Tabela11[Nota],Tabela11[Seleção],G12) -> 67.36
A13: A | B13: Mexico | C13: Brian Gutiérrez | D13: 68 | F13: C | G13: Scotland | H13: =AVERAGEIFS(Tabela11[Nota],Tabela11[Seleção],G13) -> 73.269231
... A49: A | B49: South Africa | C49: Thapelo Maseko | D49: 70 | F49: L | G49: Panama | H49: =AVERAGEIFS(Tabela11[Nota],Tabela11[Seleção],G49) -> 68.304348
A50: A | B50: South Africa | C50: Relebohile Ratomo | D50: 70
A51: A | B51: South Korea | C51: Kim Seung-Gyu | D51: 72
A52: A | B52: South Korea | C52: Jo Hyeon-Woo | D52: 66
A53: A | B53: South Korea | C53: Song Bum-Keun | D53: 77
A54: A | B54: South Korea | C54: Kim Min-Jae | D54: 59
A55: A | B55: South Korea | C55: Kim Ju-Sung | D55: 58
A56: A | B56: South Korea | C56: Kim Moon-Hwan | D56: 58
A57: A | B57: South Korea | C57: Kim Tae-Hyeon | D57: 50
A58: A | B58: South Korea | C58: Lee Tae-Seok | D58: 69
A59: A | B59: South Korea | C59: Han-Beom Lee | D59: 69
A60: A | B60: South Korea | C60: Seol Young-Woo | D60: 65
A61: A | B61: South Korea | C61: Cho Yu-Min | D61: 69
... A1285: L | B1285: Panama | C1285: José Kadir | D1285: 68

Sheet Jogos (times)
A1: date | B1: match_number | C1: teams | D1: group | E1: stadium | F1: date_dt
A2: 46184 | B2: Match 1 | C2: Mexico v South Africa | D2: Group A | E2: Mexico City Stadium | F2: 46184
A3: 46184 | B3: Match 2 | C3: Korea Republic v Czechia | D3: Group A | E3: Estadio Guadalajara | F3: 46184
A4: 46185 | B4: Match 3 | C4: Canada v Bosnia and Herzegovina | D4: Group B | E4: Toronto Stadium | F4: 46185
A5: 46185 | B5: Match 4 | C5: USA v Paraguay | D5: Group D | E5: Los Angeles Stadium | F5: 46185
A6: 46186 | B6: Match 5 | C6: Haiti v Scotland | D6: Group C | E6: Boston Stadium | F6: 46186
A7: 46186 | B7: Match 6 | C7: Australia v Türkiye | D7: Group D | E7: BC Place Vancouver | F7: 46186
A8: 46186 | B8: Match 7 | C8: Brazil v Morocco | D8: Group C | E8: New York New Jersey Stadium | F8: 46186
A9: 46186 | B9: Match 8 | C9: Qatar v Switzerland | D9: Group B | E9: San Francisco Bay Area Stadium | F9: 46186
A10: 46187 | B10: Match 9 | C10: Côte d'Ivoire v Ecuador | D10: Group E | E10: Philadelphia Stadium | F10: 46187
A11: 46187 | B11: Match 10 | C11: Germany v Curaçao | D11: Group E | E11: Houston Stadium | F11: 46187
A12: 46187 | B12: Match 11 | C12: Netherlands v Japan | D12: Group F | E12: Dallas Stadium | F12: 46187
A13: 46187 | B13: Match 12 | C13: Sweden v Tunisia | D13: Group F | E13: Estadio Monterrey | F13: 46187
... A73: 46200 | B73: Match 72 | C73: Congo DR v Uzbekistan | D73: Group K | E73: Atlanta Stadium | F73: 46200
A74: 46201 | B74: Match 73 | C74: Group A runners-up v Group B runners-up | E74: Los Angeles Stadium | F74: 46201
A75: 46202 | B75: Match 74 | C75: Group E winners v Group A/B/C/D/F third place | E75: Boston Stadium | F75: 46202
A76: 46202 | B76: Match 75 | C76: Group F winners v Group C runners-up | E76: Estadio Monterrey | F76: 46202
A77: 46202 | B77: Match 76 | C77: Group C winners v Group F runners-up | E77: Houston Stadium | F77: 46202
A78: 46203 | B78: Match 77 | C78: Group I winners v Group C/D/F/G/H third place | E78: New York New Jersey Stadium | F78: 46203
A79: 46203 | B79: Match 78 | C79: Group E runners up v Group I runners-up | E79: Dallas Stadium | F79: 46203
A80: 46203 | B80: Match 79 | C80: Group A winners v Group C/E/F/H/I third place | E80: Mexico City Stadium | F80: 46203
A81: 46204 | B81: Match 80 | C81: Group L winners v Group E/H/I/J/K third place | E81: Atlanta Stadium | F81: 46204
A82: 46204 | B82: Match 81 | C82: Group D winners v Group B/E/F/I/J third place | E82: San Francisco Bay Area Stadium | F82: 46204
A83: 46204 | B83: Match 82 | C83: Group G winners v Group A/E/H/I/J third place | E83: Seattle Stadium | F83: 46204
A84: 46205 | B84: Match 83 | C84: Group K runners-up v Group L runners-up | E84: Toronto Stadium | F84: 46205
A85: 46205 | B85: Match 84 | C85: Group H winners v Group J runners-up | E85: Los Angeles Stadium | F85: 46205
... A105: 46222 | B105: Match 104 | C105: Winner match 101 v Winner match 102 | E105: New York New Jersey Stadium | F105: 46222

Sheet Monte Carlo
A1: Time A | B1: =Seleções!B2 -> Mexico | D1: Iteração | E1: Time A | F1: Time B | G1: Gols A (0) | H1: Gols A (1) | I1: Gols A (2) | J1: Gols A (3) | K1: Gols B (0) | L1: Gols B (1) | M1: Gols B (2) | N1: Gols B (3) | Q1: Prob_A | R1: Prob_B | S1: Prob_E | T1: Vencedor | U1: Gols A | V1: Outro | W1: Gols B
A2: x | D2: 1 | E2: =MAX(0,MIN(100,ROUNDDOWN(_xlfn.NORM.INV(RAND(),((_xlfn.XLOOKUP($B$1,teams[Seleção],teams[Média dos jogadores],"",0,1)*'Monte Carlo'!$B$9)+(_xlfn.XLOOKUP($B$1,teams[Seleção],teams[Comissão Técnica],"",0,1)*'Monte Carlo'!$B$10)+(_xlfn.XLOOKUP($B$1,teams[Seleção],teams[FS_Norm],"",0,1)*'Monte Carlo'!$B$11)+(_xlfn.XLOOKUP($B$1,teams[Seleção],teams[ER_norm],"",0,1)*'Monte Carlo'!$B$12)),$B$14),0))) -> 88 | F2: =MAX(0,MIN(100,ROUNDDOWN(_xlfn.NORM.INV(RAND(),((_xlfn.XLOOKUP($B$3,teams[Seleção],teams[Média dos jogadores],"",0,1)*'Monte Carlo'!$B$9)+(_xlfn.XLOOKUP($B$3,teams[Seleção],teams[Comissão Técnica],"",0,1)*'Monte Carlo'!$B$10)+(_xlfn.XLOOKUP($B$3,teams[Seleção],teams[FS_Norm],"",0,1)*'Monte Carlo'!$B$11)+(_xlfn.XLOOKUP($B$3,teams[Seleção],teams[ER_norm],"",0,1)*'Monte Carlo'!$B$12)),$B$14),0))) -> 76 | G2: =_xlfn.POISSON.DIST(0,($B$18*E2/'Monte Carlo'!$B$21),FALSE) -> 0.091110063 | H2: =_xlfn.POISSON.DIST(1,($B$18*E2/'Monte Carlo'!$B$21),0) -> 0.2182712 | I2: =_xlfn.POISSON.DIST(2,($B$18*E2/'Monte Carlo'!$B$21),0) -> 0.26145473 | J2: =_xlfn.POISSON.DIST(3,($B$18*E2/'Monte Carlo'!$B$21),0) -> 0.2087879 | K2: =_xlfn.POISSON.DIST(0,($B$19*F2/'Monte Carlo'!$B$21),0) -> 0.35540361 | L2: =_xlfn.POISSON.DIST(1,($B$19*F2/'Monte Carlo'!$B$21),0) -> 0.36766546 | M2: =_xlfn.POISSON.DIST(2,($B$19*F2/'Monte Carlo'!$B$21),0) -> 0.19017518 | N2: =_xlfn.POISSON.DIST(3,($B$19*F2/'Monte Carlo'!$B$21),0) -> 0.06557882 | Q2: {=SUMPRODUCT(N(E2:E1001>F2:F1001))/1000} -> 0.82 | R2: {=SUMPRODUCT(N(E2:E1001<F2:F1001))/1000} -> 0.158 | S2: {=SUMPRODUCT(N(E2:E1001=F2:F1001))/1000} -> 0.022 | T2: =IF(Q2>R2,$B$1,IF(Q2<R2,$B$3,"Empate")) -> Mexico | U2: =ROUNDDOWN(_xlfn.XLOOKUP(MAX(S12:S27),S12:S27,Q12:Q27,"",0,1),0) & " x " & _xlfn.XLOOKUP(MAX(S12:S27),S12:S27,R12:R27,"",0,1) -> 2 x 0 | V2: =IF(T2=B1,B3) -> South Africa | W2: {=_xlfn.XLOOKUP(MAX(_xlfn._xlws.FILTER(S12:S27,R12:R27>Q12:Q27)),S12:S27,R12:R27,"",0,1) & " x " & _xlfn.XLOOKUP(MAX(_xlfn._xlws.FILTER(S12:S27,R12:R27>Q12:Q27)),S12:S27,Q12:Q27,"",0,1)} -> 1 x 0
A3: Time B | B3: =teams[[#This Row],[Seleção]] -> South Africa | D3: 2 | E3: =MAX(0,MIN(100,ROUNDDOWN(_xlfn.NORM.INV(RAND(),((_xlfn.XLOOKUP($B$1,teams[Seleção],teams[Média dos jogadores],"",0,1)*'Monte Carlo'!$B$9)+(_xlfn.XLOOKUP($B$1,teams[Seleção],teams[Comissão Técnica],"",0,1)*'Monte Carlo'!$B$10)+(_xlfn.XLOOKUP($B$1,teams[Seleção],teams[FS_Norm],"",0,1)*'Monte Carlo'!$B$11)+(_xlfn.XLOOKUP($B$1,teams[Seleção],teams[ER_norm],"",0,1)*'Monte Carlo'!$B$12)),$B$14),0))) -> 95 | F3: =MAX(0,MIN(100,ROUNDDOWN(_xlfn.NORM.INV(RAND(),((_xlfn.XLOOKUP($B$3,teams[Seleção],teams[Média dos jogadores],"",0,1)*'Monte Carlo'!$B$9)+(_xlfn.XLOOKUP($B$3,teams[Seleção],teams[Comissão Técnica],"",0,1)*'Monte Carlo'!$B$10)+(_xlfn.XLOOKUP($B$3,teams[Seleção],teams[FS_Norm],"",0,1)*'Monte Carlo'!$B$11)+(_xlfn.XLOOKUP($B$3,teams[Seleção],teams[ER_norm],"",0,1)*'Monte Carlo'!$B$12)),$B$14),0))) -> 70 | G3: =_xlfn.POISSON.DIST(0,($B$18*E3/'Monte Carlo'!$B$21),FALSE) -> 0.075301665 | H3: =_xlfn.POISSON.DIST(1,($B$18*E3/'Monte Carlo'!$B$21),0) -> 0.19474916 | I3: =_xlfn.POISSON.DIST(2,($B$18*E3/'Monte Carlo'!$B$21),0) -> 0.2518353 | J3: =_xlfn.POISSON.DIST(3,($B$18*E3/'Monte Carlo'!$B$21),0) -> 0.21710327 | K3: =_xlfn.POISSON.DIST(0,($B$19*F3/'Monte Carlo'!$B$21),0) -> 0.38564807 | L3: =_xlfn.POISSON.DIST(1,($B$19*F3/'Monte Carlo'!$B$21),0) -> 0.36745707 | M3: =_xlfn.POISSON.DIST(2,($B$19*F3/'Monte Carlo'!$B$21),0) -> 0.17506207 | N3: =_xlfn.POISSON.DIST(3,($B$19*F3/'Monte Carlo'!$B$21),0) -> 0.055601469
D4: 3 | E4: =MAX(0,MIN(100,ROUNDDOWN(_xlfn.NORM.INV(RAND(),((_xlfn.XLOOKUP($B$1,teams[Seleção],teams[Média dos jogadores],"",0,1)*'Monte Carlo'!$B$9)+(_xlfn.XLOOKUP($B$1,teams[Seleção],teams[Comissão Técnica],"",0,1)*'Monte Carlo'!$B$10)+(_xlfn.XLOOKUP($B$1,teams[Seleção],teams[FS_Norm],"",0,1)*'Monte Carlo'!$B$11)+(_xlfn.XLOOKUP($B$1,teams[Seleção],teams[ER_norm],"",0,1)*'Monte Carlo'!$B$12)),$B$14),0))) -> 72 | F4: =MAX(0,MIN(100,ROUNDDOWN(_xlfn.NORM.INV(RAND(),((_xlfn.XLOOKUP($B$3,teams[Seleção],teams[Média dos jogadores],"",0,1)*'Monte Carlo'!$B$9)+(_xlfn.XLOOKUP($B$3,teams[Seleção],teams[Comissão Técnica],"",0,1)*'Monte Carlo'!$B$10)+(_xlfn.XLOOKUP($B$3,teams[Seleção],teams[FS_Norm],"",0,1)*'Monte Carlo'!$B$11)+(_xlfn.XLOOKUP($B$3,teams[Seleção],teams[ER_norm],"",0,1)*'Monte Carlo'!$B$12)),$B$14),0))) -> 74 | G4: =_xlfn.POISSON.DIST(0,($B$18*E4/'Monte Carlo'!$B$21),FALSE) -> 0.14084327 | H4: =_xlfn.POISSON.DIST(1,($B$18*E4/'Monte Carlo'!$B$21),0) -> 0.27606796 | I4: =_xlfn.POISSON.DIST(2,($B$18*E4/'Monte Carlo'!$B$21),0) -> 0.27056145 | J4: =_xlfn.POISSON.DIST(3,($B$18*E4/'Monte Carlo'!$B$21),0) -> 0.17677651 | K4: =_xlfn.POISSON.DIST(0,($B$19*F4/'Monte Carlo'!$B$21),0) -> 0.36521192 | L4: =_xlfn.POISSON.DIST(1,($B$19*F4/'Monte Carlo'!$B$21),0) -> 0.36786975 | M4: =_xlfn.POISSON.DIST(2,($B$19*F4/'Monte Carlo'!$B$21),0) -> 0.18527346 | N4: =_xlfn.POISSON.DIST(3,($B$19*F4/'Monte Carlo'!$B$21),0) -> 0.062207262
D5: 4 | E5: =MAX(0,MIN(100,ROUNDDOWN(_xlfn.NORM.INV(RAND(),((_xlfn.XLOOKUP($B$1,teams[Seleção],teams[Média dos jogadores],"",0,1)*'Monte Carlo'!$B$9)+(_xlfn.XLOOKUP($B$1,teams[Seleção],teams[Comissão Técnica],"",0,1)*'Monte Carlo'!$B$10)+(_xlfn.XLOOKUP($B$1,teams[Seleção],teams[FS_Norm],"",0,1)*'Monte Carlo'!$B$11)+(_xlfn.XLOOKUP($B$1,teams[Seleção],teams[ER_norm],"",0,1)*'Monte Carlo'!$B$12)),$B$14),0))) -> 57 | F5: =MAX(0,MIN(100,ROUNDDOWN(_xlfn.NORM.INV(RAND(),((_xlfn.XLOOKUP($B$3,teams[Seleção],teams[Média dos jogadores],"",0,1)*'Monte Carlo'!$B$9)+(_xlfn.XLOOKUP($B$3,teams[Seleção],teams[Comissão Técnica],"",0,1)*'Monte Carlo'!$B$10)+(_xlfn.XLOOKUP($B$3,teams[Seleção],teams[FS_Norm],"",0,1)*'Monte Carlo'!$B$11)+(_xlfn.XLOOKUP($B$3,teams[Seleção],teams[ER_norm],"",0,1)*'Monte Carlo'!$B$12)),$B$14),0))) -> 64 | G5: =_xlfn.POISSON.DIST(0,($B$18*E5/'Monte Carlo'!$B$21),FALSE) -> 0.21187648 | H5: =_xlfn.POISSON.DIST(1,($B$18*E5/'Monte Carlo'!$B$21),0) -> 0.32877971 | I5: =_xlfn.POISSON.DIST(2,($B$18*E5/'Monte Carlo'!$B$21),0) -> 0.25509226 | J5: =_xlfn.POISSON.DIST(3,($B$18*E5/'Monte Carlo'!$B$21),0) -> 0.13194663 | K5: =_xlfn.POISSON.DIST(0,($B$19*F5/'Monte Carlo'!$B$21),0) -> 0.4184663 | L5: =_xlfn.POISSON.DIST(1,($B$19*F5/'Monte Carlo'!$B$21),0) -> 0.36455065 | M5: =_xlfn.POISSON.DIST(2,($B$19*F5/'Monte Carlo'!$B$21),0) -> 0.15879077 | N5: =_xlfn.POISSON.DIST(3,($B$19*F5/'Monte Carlo'!$B$21),0) -> 0.046110666
D6: 5 | E6: =MAX(0,MIN(100,ROUNDDOWN(_xlfn.NORM.INV(RAND(),((_xlfn.XLOOKUP($B$1,teams[Seleção],teams[Média dos jogadores],"",0,1)*'Monte Carlo'!$B$9)+(_xlfn.XLOOKUP($B$1,teams[Seleção],teams[Comissão Técnica],"",0,1)*'Monte Carlo'!$B$10)+(_xlfn.XLOOKUP($B$1,teams[Seleção],teams[FS_Norm],"",0,1)*'Monte Carlo'!$B$11)+(_xlfn.XLOOKUP($B$1,teams[Seleção],teams[ER_norm],"",0,1)*'Monte Carlo'!$B$12)),$B$14),0))) -> 69 | F6: =MAX(0,MIN(100,ROUNDDOWN(_xlfn.NORM.INV(RAND(),((_xlfn.XLOOKUP($B$3,teams[Seleção],teams[Média dos jogadores],"",0,1)*'Monte Carlo'!$B$9)+(_xlfn.XLOOKUP($B$3,teams[Seleção],teams[Comissão Técnica],"",0,1)*'Monte Carlo'!$B$10)+(_xlfn.XLOOKUP($B$3,teams[Seleção],teams[FS_Norm],"",0,1)*'Monte Carlo'!$B$11)+(_xlfn.XLOOKUP($B$3,teams[Seleção],teams[ER_norm],"",0,1)*'Monte Carlo'!$B$12)),$B$14),0))) -> 66 | G6: =_xlfn.POISSON.DIST(0,($B$18*E6/'Monte Carlo'!$B$21),FALSE) -> 0.15282888 | H6: =_xlfn.POISSON.DIST(1,($B$18*E6/'Monte Carlo'!$B$21),0) -> 0.28707933 | I6: =_xlfn.POISSON.DIST(2,($B$18*E6/'Monte Carlo'!$B$21),0) -> 0.26963014 | J6: =_xlfn.POISSON.DIST(3,($B$18*E6/'Monte Carlo'!$B$21),0) -> 0.16882769 | K6: =_xlfn.POISSON.DIST(0,($B$19*F6/'Monte Carlo'!$B$21),0) -> 0.40722776 | L6: =_xlfn.POISSON.DIST(1,($B$19*F6/'Monte Carlo'!$B$21),0) -> 0.36584635 | M6: =_xlfn.POISSON.DIST(2,($B$19*F6/'Monte Carlo'!$B$21),0) -> 0.164335 | N6: =_xlfn.POISSON.DIST(3,($B$19*F6/'Monte Carlo'!$B$21),0) -> 0.049211905
D7: 6 | E7: =MAX(0,MIN(100,ROUNDDOWN(_xlfn.NORM.INV(RAND(),((_xlfn.XLOOKUP($B$1,teams[Seleção],teams[Média dos jogadores],"",0,1)*'Monte Carlo'!$B$9)+(_xlfn.XLOOKUP($B$1,teams[Seleção],teams[Comissão Técnica],"",0,1)*'Monte Carlo'!$B$10)+(_xlfn.XLOOKUP($B$1,teams[Seleção],teams[FS_Norm],"",0,1)*'Monte Carlo'!$B$11)+(_xlfn.XLOOKUP($B$1,teams[Seleção],teams[ER_norm],"",0,1)*'Monte Carlo'!$B$12)),$B$14),0))) -> 79 | F7: =MAX(0,MIN(100,ROUNDDOWN(_xlfn.NORM.INV(RAND(),((_xlfn.XLOOKUP($B$3,teams[Seleção],teams[Média dos jogadores],"",0,1)*'Monte Carlo'!$B$9)+(_xlfn.XLOOKUP($B$3,teams[Seleção],teams[Comissão Técnica],"",0,1)*'Monte Carlo'!$B$10)+(_xlfn.XLOOKUP($B$3,teams[Seleção],teams[FS_Norm],"",0,1)*'Monte Carlo'!$B$11)+(_xlfn.XLOOKUP($B$3,teams[Seleção],teams[ER_norm],"",0,1)*'Monte Carlo'!$B$12)),$B$14),0))) -> 53 | G7: =_xlfn.POISSON.DIST(0,($B$18*E7/'Monte Carlo'!$B$21),FALSE) -> 0.11640572 | H7: =_xlfn.POISSON.DIST(1,($B$18*E7/'Monte Carlo'!$B$21),0) -> 0.25035071 | I7: =_xlfn.POISSON.DIST(2,($B$18*E7/'Monte Carlo'!$B$21),0) -> 0.26921133 | J7: =_xlfn.POISSON.DIST(3,($B$18*E7/'Monte Carlo'!$B$21),0) -> 0.19299523 | K7: =_xlfn.POISSON.DIST(0,($B$19*F7/'Monte Carlo'!$B$21),0) -> 0.48605744 | L7: =_xlfn.POISSON.DIST(1,($B$19*F7/'Monte Carlo'!$B$21),0) -> 0.35065568 | M7: =_xlfn.POISSON.DIST(2,($B$19*F7/'Monte Carlo'!$B$21),0) -> 0.1264865 | N7: =_xlfn.POISSON.DIST(3,($B$19*F7/'Monte Carlo'!$B$21),0) -> 0.030416987
A8: Peso | B8: Peso_Norm | D8: 7 | E8: =MAX(0,MIN(100,ROUNDDOWN(_xlfn.NORM.INV(RAND(),((_xlfn.XLOOKUP($B$1,teams[Seleção],teams[Média dos jogadores],"",0,1)*'Monte Carlo'!$B$9)+(_xlfn.XLOOKUP($B$1,teams[Seleção],teams[Comissão Técnica],"",0,1)*'Monte Carlo'!$B$10)+(_xlfn.XLOOKUP($B$1,teams[Seleção],teams[FS_Norm],"",0,1)*'Monte Carlo'!$B$11)+(_xlfn.XLOOKUP($B$1,teams[Seleção],teams[ER_norm],"",0,1)*'Monte Carlo'!$B$12)),$B$14),0))) -> 78 | F8: =MAX(0,MIN(100,ROUNDDOWN(_xlfn.NORM.INV(RAND(),((_xlfn.XLOOKUP($B$3,teams[Seleção],teams[Média dos jogadores],"",0,1)*'Monte Carlo'!$B$9)+(_xlfn.XLOOKUP($B$3,teams[Seleção],teams[Comissão Técnica],"",0,1)*'Monte Carlo'!$B$10)+(_xlfn.XLOOKUP($B$3,teams[Seleção],teams[FS_Norm],"",0,1)*'Monte Carlo'!$B$11)+(_xlfn.XLOOKUP($B$3,teams[Seleção],teams[ER_norm],"",0,1)*'Monte Carlo'!$B$12)),$B$14),0))) -> 56 | G8: =_xlfn.POISSON.DIST(0,($B$18*E8/'Monte Carlo'!$B$21),FALSE) -> 0.11961825 | H8: =_xlfn.POISSON.DIST(1,($B$18*E8/'Monte Carlo'!$B$21),0) -> 0.25400336 | I8: =_xlfn.POISSON.DIST(2,($B$18*E8/'Monte Carlo'!$B$21),0) -> 0.26968169 | J8: =_xlfn.POISSON.DIST(3,($B$18*E8/'Monte Carlo'!$B$21),0) -> 0.19088519 | K8: =_xlfn.POISSON.DIST(0,($B$19*F8/'Monte Carlo'!$B$21),0) -> 0.4666088 | L8: =_xlfn.POISSON.DIST(1,($B$19*F8/'Monte Carlo'!$B$21),0) -> 0.35567912 | M8: =_xlfn.POISSON.DIST(2,($B$19*F8/'Monte Carlo'!$B$21),0) -> 0.1355607 | N8: =_xlfn.POISSON.DIST(3,($B$19*F8/'Monte Carlo'!$B$21),0) -> 0.03444435
A9: =RANDBETWEEN(10,40) -> 19 | B9: =A9/SUM($A$9:$A$12) -> 0.22093023 | D9: 8 | E9: =MAX(0,MIN(100,ROUNDDOWN(_xlfn.NORM.INV(RAND(),((_xlfn.XLOOKUP($B$1,teams[Seleção],teams[Média dos jogadores],"",0,1)*'Monte Carlo'!$B$9)+(_xlfn.XLOOKUP($B$1,teams[Seleção],teams[Comissão Técnica],"",0,1)*'Monte Carlo'!$B$10)+(_xlfn.XLOOKUP($B$1,teams[Seleção],teams[FS_Norm],"",0,1)*'Monte Carlo'!$B$11)+(_xlfn.XLOOKUP($B$1,teams[Seleção],teams[ER_norm],"",0,1)*'Monte Carlo'!$B$12)),$B$14),0))) -> 76 | F9: =MAX(0,MIN(100,ROUNDDOWN(_xlfn.NORM.INV(RAND(),((_xlfn.XLOOKUP($B$3,teams[Seleção],teams[Média dos jogadores],"",0,1)*'Monte Carlo'!$B$9)+(_xlfn.XLOOKUP($B$3,teams[Seleção],teams[Comissão Técnica],"",0,1)*'Monte Carlo'!$B$10)+(_xlfn.XLOOKUP($B$3,teams[Seleção],teams[FS_Norm],"",0,1)*'Monte Carlo'!$B$11)+(_xlfn.XLOOKUP($B$3,teams[Seleção],teams[ER_norm],"",0,1)*'Monte Carlo'!$B$12)),$B$14),0))) -> 48 | G9: =_xlfn.POISSON.DIST(0,($B$18*E9/'Monte Carlo'!$B$21),FALSE) -> 0.12631172 | H9: =_xlfn.POISSON.DIST(1,($B$18*E9/'Monte Carlo'!$B$21),0) -> 0.26133926 | I9: =_xlfn.POISSON.DIST(2,($B$18*E9/'Monte Carlo'!$B$21),0) -> 0.27035579 | J9: =_xlfn.POISSON.DIST(3,($B$18*E9/'Monte Carlo'!$B$21),0) -> 0.18645559 | K9: =_xlfn.POISSON.DIST(0,($B$19*F9/'Monte Carlo'!$B$21),0) -> 0.52028987 | L9: =_xlfn.POISSON.DIST(1,($B$19*F9/'Monte Carlo'!$B$21),0) -> 0.33994137 | M9: =_xlfn.POISSON.DIST(2,($B$19*F9/'Monte Carlo'!$B$21),0) -> 0.11105361 | N9: =_xlfn.POISSON.DIST(3,($B$19*F9/'Monte Carlo'!$B$21),0) -> 0.024186335
A10: =RANDBETWEEN(10,20) -> 14 | B10: =A10/SUM($A$9:$A$12) -> 0.1627907 | D10: 9 | E10: =MAX(0,MIN(100,ROUNDDOWN(_xlfn.NORM.INV(RAND(),((_xlfn.XLOOKUP($B$1,teams[Seleção],teams[Média dos jogadores],"",0,1)*'Monte Carlo'!$B$9)+(_xlfn.XLOOKUP($B$1,teams[Seleção],teams[Comissão Técnica],"",0,1)*'Monte Carlo'!$B$10)+(_xlfn.XLOOKUP($B$1,teams[Seleção],teams[FS_Norm],"",0,1)*'Monte Carlo'!$B$11)+(_xlfn.XLOOKUP($B$1,teams[Seleção],teams[ER_norm],"",0,1)*'Monte Carlo'!$B$12)),$B$14),0))) -> 82 | F10: =MAX(0,MIN(100,ROUNDDOWN(_xlfn.NORM.INV(RAND(),((_xlfn.XLOOKUP($B$3,teams[Seleção],teams[Média dos jogadores],"",0,1)*'Monte Carlo'!$B$9)+(_xlfn.XLOOKUP($B$3,teams[Seleção],teams[Comissão Técnica],"",0,1)*'Monte Carlo'!$B$10)+(_xlfn.XLOOKUP($B$3,teams[Seleção],teams[FS_Norm],"",0,1)*'Monte Carlo'!$B$11)+(_xlfn.XLOOKUP($B$3,teams[Seleção],teams[ER_norm],"",0,1)*'Monte Carlo'!$B$12)),$B$14),0))) -> 74 | G10: =_xlfn.POISSON.DIST(0,($B$18*E10/'Monte Carlo'!$B$21),FALSE) -> 0.1072766 | H10: =_xlfn.POISSON.DIST(1,($B$18*E10/'Monte Carlo'!$B$21),0) -> 0.23947835 | I10: =_xlfn.POISSON.DIST(2,($B$18*E10/'Monte Carlo'!$B$21),0) -> 0.26729912 | J10: =_xlfn.POISSON.DIST(3,($B$18*E10/'Monte Carlo'!$B$21),0) -> 0.19890126 | K10: =_xlfn.POISSON.DIST(0,($B$19*F10/'Monte Carlo'!$B$21),0) -> 0.36521192 | L10: =_xlfn.POISSON.DIST(1,($B$19*F10/'Monte Carlo'!$B$21),0) -> 0.36786975 | M10: =_xlfn.POISSON.DIST(2,($B$19*F10/'Monte Carlo'!$B$21),0) -> 0.18527346 | N10: =_xlfn.POISSON.DIST(3,($B$19*F10/'Monte Carlo'!$B$21),0) -> 0.062207262
A11: =RANDBETWEEN(10,20) -> 16 | B11: =A11/SUM($A$9:$A$12) -> 0.18604651 | D11: 10 | E11: =MAX(0,MIN(100,ROUNDDOWN(_xlfn.NORM.INV(RAND(),((_xlfn.XLOOKUP($B$1,teams[Seleção],teams[Média dos jogadores],"",0,1)*'Monte Carlo'!$B$9)+(_xlfn.XLOOKUP($B$1,teams[Seleção],teams[Comissão Técnica],"",0,1)*'Monte Carlo'!$B$10)+(_xlfn.XLOOKUP($B$1,teams[Seleção],teams[FS_Norm],"",0,1)*'Monte Carlo'!$B$11)+(_xlfn.XLOOKUP($B$1,teams[Seleção],teams[ER_norm],"",0,1)*'Monte Carlo'!$B$12)),$B$14),0))) -> 80 | F11: =MAX(0,MIN(100,ROUNDDOWN(_xlfn.NORM.INV(RAND(),((_xlfn.XLOOKUP($B$3,teams[Seleção],teams[Média dos jogadores],"",0,1)*'Monte Carlo'!$B$9)+(_xlfn.XLOOKUP($B$3,teams[Seleção],teams[Comissão Técnica],"",0,1)*'Monte Carlo'!$B$10)+(_xlfn.XLOOKUP($B$3,teams[Seleção],teams[FS_Norm],"",0,1)*'Monte Carlo'!$B$11)+(_xlfn.XLOOKUP($B$3,teams[Seleção],teams[ER_norm],"",0,1)*'Monte Carlo'!$B$12)),$B$14),0))) -> 45 | G11: =_xlfn.POISSON.DIST(0,($B$18*E11/'Monte Carlo'!$B$21),FALSE) -> 0.11327947 | H11: =_xlfn.POISSON.DIST(1,($B$18*E11/'Monte Carlo'!$B$21),0) -> 0.24671106 | I11: =_xlfn.POISSON.DIST(2,($B$18*E11/'Monte Carlo'!$B$21),0) -> 0.26865567 | J11: =_xlfn.POISSON.DIST(3,($B$18*E11/'Monte Carlo'!$B$21),0) -> 0.19503482 | K11: =_xlfn.POISSON.DIST(0,($B$19*F11/'Monte Carlo'!$B$21),0) -> 0.54197597 | L11: =_xlfn.POISSON.DIST(1,($B$19*F11/'Monte Carlo'!$B$21),0) -> 0.3319785 | M11: =_xlfn.POISSON.DIST(2,($B$19*F11/'Monte Carlo'!$B$21),0) -> 0.10167399 | N11: =_xlfn.POISSON.DIST(3,($B$19*F11/'Monte Carlo'!$B$21),0) -> 0.02075958 | Q11: A | R11: B | S11: Prob
A12: =RANDBETWEEN(10,40) -> 37 | B12: =A12/SUM($A$9:$A$12) -> 0.43023256 | D12: 11 | E12: =MAX(0,MIN(100,ROUNDDOWN(_xlfn.NORM.INV(RAND(),((_xlfn.XLOOKUP($B$1,teams[Seleção],teams[Média dos jogadores],"",0,1)*'Monte Carlo'!$B$9)+(_xlfn.XLOOKUP($B$1,teams[Seleção],teams[Comissão Técnica],"",0,1)*'Monte Carlo'!$B$10)+(_xlfn.XLOOKUP($B$1,teams[Seleção],teams[FS_Norm],"",0,1)*'Monte Carlo'!$B$11)+(_xlfn.XLOOKUP($B$1,teams[Seleção],teams[ER_norm],"",0,1)*'Monte Carlo'!$B$12)),$B$14),0))) -> 78 | F12: =MAX(0,MIN(100,ROUNDDOWN(_xlfn.NORM.INV(RAND(),((_xlfn.XLOOKUP($B$3,teams[Seleção],teams[Média dos jogadores],"",0,1)*'Monte Carlo'!$B$9)+(_xlfn.XLOOKUP($B$3,teams[Seleção],teams[Comissão Técnica],"",0,1)*'Monte Carlo'!$B$10)+(_xlfn.XLOOKUP($B$3,teams[Seleção],teams[FS_Norm],"",0,1)*'Monte Carlo'!$B$11)+(_xlfn.XLOOKUP($B$3,teams[Seleção],teams[ER_norm],"",0,1)*'Monte Carlo'!$B$12)),$B$14),0))) -> 72 | G12: =_xlfn.POISSON.DIST(0,($B$18*E12/'Monte Carlo'!$B$21),FALSE) -> 0.11961825 | H12: =_xlfn.POISSON.DIST(1,($B$18*E12/'Monte Carlo'!$B$21),0) -> 0.25400336 | I12: =_xlfn.POISSON.DIST(2,($B$18*E12/'Monte Carlo'!$B$21),0) -> 0.26968169 | J12: =_xlfn.POISSON.DIST(3,($B$18*E12/'Monte Carlo'!$B$21),0) -> 0.19088519 | K12: =_xlfn.POISSON.DIST(0,($B$19*F12/'Monte Carlo'!$B$21),0) -> 0.37529091 | L12: =_xlfn.POISSON.DIST(1,($B$19*F12/'Monte Carlo'!$B$21),0) -> 0.36780528 | M12: =_xlfn.POISSON.DIST(2,($B$19*F12/'Monte Carlo'!$B$21),0) -> 0.18023448 | N12: =_xlfn.POISSON.DIST(3,($B$19*F12/'Monte Carlo'!$B$21),0) -> 0.058879827 | Q12: 0 | R12: 0 | S12: =AVERAGE($G$2:$G$1001)*AVERAGE($K$2:$K$1001) -> 0.049546996
D13: 12 | E13: =MAX(0,MIN(100,ROUNDDOWN(_xlfn.NORM.INV(RAND(),((_xlfn.XLOOKUP($B$1,teams[Seleção],teams[Média dos jogadores],"",0,1)*'Monte Carlo'!$B$9)+(_xlfn.XLOOKUP($B$1,teams[Seleção],teams[Comissão Técnica],"",0,1)*'Monte Carlo'!$B$10)+(_xlfn.XLOOKUP($B$1,teams[Seleção],teams[FS_Norm],"",0,1)*'Monte Carlo'!$B$11)+(_xlfn.XLOOKUP($B$1,teams[Seleção],teams[ER_norm],"",0,1)*'Monte Carlo'!$B$12)),$B$14),0))) -> 84 | F13: =MAX(0,MIN(100,ROUNDDOWN(_xlfn.NORM.INV(RAND(),((_xlfn.XLOOKUP($B$3,teams[Seleção],teams[Média dos jogadores],"",0,1)*'Monte Carlo'!$B$9)+(_xlfn.XLOOKUP($B$3,teams[Seleção],teams[Comissão Técnica],"",0,1)*'Monte Carlo'!$B$10)+(_xlfn.XLOOKUP($B$3,teams[Seleção],teams[FS_Norm],"",0,1)*'Monte Carlo'!$B$11)+(_xlfn.XLOOKUP($B$3,teams[Seleção],teams[ER_norm],"",0,1)*'Monte Carlo'!$B$12)),$B$14),0))) -> 66 | G13: =_xlfn.POISSON.DIST(0,($B$18*E13/'Monte Carlo'!$B$21),FALSE) -> 0.10159183 | H13: =_xlfn.POISSON.DIST(1,($B$18*E13/'Monte Carlo'!$B$21),0) -> 0.2323194 | I13: =_xlfn.POISSON.DIST(2,($B$18*E13/'Monte Carlo'!$B$21),0) -> 0.26563309 | J13: =_xlfn.POISSON.DIST(3,($B$18*E13/'Monte Carlo'!$B$21),0) -> 0.20248256 | K13: =_xlfn.POISSON.DIST(0,($B$19*F13/'Monte Carlo'!$B$21),0) -> 0.40722776 | L13: =_xlfn.POISSON.DIST(1,($B$19*F13/'Monte Carlo'!$B$21),0) -> 0.36584635 | M13: =_xlfn.POISSON.DIST(2,($B$19*F13/'Monte Carlo'!$B$21),0) -> 0.164335 | N13: =_xlfn.POISSON.DIST(3,($B$19*F13/'Monte Carlo'!$B$21),0) -> 0.049211905 | Q13: 0 | R13: 1 | S13: =AVERAGE($G$2:$G$1001)*AVERAGE($L$2:$L$1001) -> 0.043362408
A14: Zebra | B14: 10 | D14: 13 | E14: =MAX(0,MIN(100,ROUNDDOWN(_xlfn.NORM.INV(RAND(),((_xlfn.XLOOKUP($B$1,teams[Seleção],teams[Média dos jogadores],"",0,1)*'Monte Carlo'!$B$9)+(_xlfn.XLOOKUP($B$1,teams[Seleção],teams[Comissão Técnica],"",0,1)*'Monte Carlo'!$B$10)+(_xlfn.XLOOKUP($B$1,teams[Seleção],teams[FS_Norm],"",0,1)*'Monte Carlo'!$B$11)+(_xlfn.XLOOKUP($B$1,teams[Seleção],teams[ER_norm],"",0,1)*'Monte Carlo'!$B$12)),$B$14),0))) -> 79 | F14: =MAX(0,MIN(100,ROUNDDOWN(_xlfn.NORM.INV(RAND(),((_xlfn.XLOOKUP($B$3,teams[Seleção],teams[Média dos jogadores],"",0,1)*'Monte Carlo'!$B$9)+(_xlfn.XLOOKUP($B$3,teams[Seleção],teams[Comissão Técnica],"",0,1)*'Monte Carlo'!$B$10)+(_xlfn.XLOOKUP($B$3,teams[Seleção],teams[FS_Norm],"",0,1)*'Monte Carlo'!$B$11)+(_xlfn.XLOOKUP($B$3,teams[Seleção],teams[ER_norm],"",0,1)*'Monte Carlo'!$B$12)),$B$14),0))) -> 62 | G14: =_xlfn.POISSON.DIST(0,($B$18*E14/'Monte Carlo'!$B$21),FALSE) -> 0.11640572 | H14: =_xlfn.POISSON.DIST(1,($B$18*E14/'Monte Carlo'!$B$21),0) -> 0.25035071 | I14: =_xlfn.POISSON.DIST(2,($B$18*E14/'Monte Carlo'!$B$21),0) -> 0.26921133 | J14: =_xlfn.POISSON.DIST(3,($B$18*E14/'Monte Carlo'!$B$21),0) -> 0.19299523 | K14: =_xlfn.POISSON.DIST(0,($B$19*F14/'Monte Carlo'!$B$21),0) -> 0.43001499 | L14: =_xlfn.POISSON.DIST(1,($B$19*F14/'Monte Carlo'!$B$21),0) -> 0.36290479 | M14: =_xlfn.POISSON.DIST(2,($B$19*F14/'Monte Carlo'!$B$21),0) -> 0.15313406 | N14: =_xlfn.POISSON.DIST(3,($B$19*F14/'Monte Carlo'!$B$21),0) -> 0.043078409 | Q14: 0 | R14: 2 | S14: =AVERAGE($G$2:$G$1001)*AVERAGE($M$2:$M$1001) -> 0.019477619
D15: 14 | E15: =MAX(0,MIN(100,ROUNDDOWN(_xlfn.NORM.INV(RAND(),((_xlfn.XLOOKUP($B$1,teams[Seleção],teams[Média dos jogadores],"",0,1)*'Monte Carlo'!$B$9)+(_xlfn.XLOOKUP($B$1,teams[Seleção],teams[Comissão Técnica],"",0,1)*'Monte Carlo'!$B$10)+(_xlfn.XLOOKUP($B$1,teams[Seleção],teams[FS_Norm],"",0,1)*'Monte Carlo'!$B$11)+(_xlfn.XLOOKUP($B$1,teams[Seleção],teams[ER_norm],"",0,1)*'Monte Carlo'!$B$12)),$B$14),0))) -> 85 | F15: =MAX(0,MIN(100,ROUNDDOWN(_xlfn.NORM.INV(RAND(),((_xlfn.XLOOKUP($B$3,teams[Seleção],teams[Média dos jogadores],"",0,1)*'Monte Carlo'!$B$9)+(_xlfn.XLOOKUP($B$3,teams[Seleção],teams[Comissão Técnica],"",0,1)*'Monte Carlo'!$B$10)+(_xlfn.XLOOKUP($B$3,teams[Seleção],teams[FS_Norm],"",0,1)*'Monte Carlo'!$B$11)+(_xlfn.XLOOKUP($B$3,teams[Seleção],teams[ER_norm],"",0,1)*'Monte Carlo'!$B$12)),$B$14),0))) -> 62 | G15: =_xlfn.POISSON.DIST(0,($B$18*E15/'Monte Carlo'!$B$21),FALSE) -> 0.09886343 | H15: =_xlfn.POISSON.DIST(1,($B$18*E15/'Monte Carlo'!$B$21),0) -> 0.22877155 | I15: =_xlfn.POISSON.DIST(2,($B$18*E15/'Monte Carlo'!$B$21),0) -> 0.2646905 | J15: =_xlfn.POISSON.DIST(3,($B$18*E15/'Monte Carlo'!$B$21),0) -> 0.204166 | K15: =_xlfn.POISSON.DIST(0,($B$19*F15/'Monte Carlo'!$B$21),0) -> 0.43001499 | L15: =_xlfn.POISSON.DIST(1,($B$19*F15/'Monte Carlo'!$B$21),0) -> 0.36290479 | M15: =_xlfn.POISSON.DIST(2,($B$19*F15/'Monte Carlo'!$B$21),0) -> 0.15313406 | N15: =_xlfn.POISSON.DIST(3,($B$19*F15/'Monte Carlo'!$B$21),0) -> 0.043078409 | Q15: 0 | R15: 3 | S15: =AVERAGE($G$2:$G$1001)*AVERAGE($N$2:$N$1001) -> 0.0059772877
D16: 15 | E16: =MAX(0,MIN(100,ROUNDDOWN(_xlfn.NORM.INV(RAND(),((_xlfn.XLOOKUP($B$1,teams[Seleção],teams[Média dos jogadores],"",0,1)*'Monte Carlo'!$B$9)+(_xlfn.XLOOKUP($B$1,teams[Seleção],teams[Comissão Técnica],"",0,1)*'Monte Carlo'!$B$10)+(_xlfn.XLOOKUP($B$1,teams[Seleção],teams[FS_Norm],"",0,1)*'Monte Carlo'!$B$11)+(_xlfn.XLOOKUP($B$1,teams[Seleção],teams[ER_norm],"",0,1)*'Monte Carlo'!$B$12)),$B$14),0))) -> 90 | F16: =MAX(0,MIN(100,ROUNDDOWN(_xlfn.NORM.INV(RAND(),((_xlfn.XLOOKUP($B$3,teams[Seleção],teams[Média dos jogadores],"",0,1)*'Monte Carlo'!$B$9)+(_xlfn.XLOOKUP($B$3,teams[Seleção],teams[Comissão Técnica],"",0,1)*'Monte Carlo'!$B$10)+(_xlfn.XLOOKUP($B$3,teams[Seleção],teams[FS_Norm],"",0,1)*'Monte Carlo'!$B$11)+(_xlfn.XLOOKUP($B$3,teams[Seleção],teams[ER_norm],"",0,1)*'Monte Carlo'!$B$12)),$B$14),0))) -> 92 | G16: =_xlfn.POISSON.DIST(0,($B$18*E16/'Monte Carlo'!$B$21),FALSE) -> 0.086281985 | H16: =_xlfn.POISSON.DIST(1,($B$18*E16/'Monte Carlo'!$B$21),0) -> 0.21140246 | I16: =_xlfn.POISSON.DIST(2,($B$18*E16/'Monte Carlo'!$B$21),0) -> 0.25898223 | J16: =_xlfn.POISSON.DIST(3,($B$18*E16/'Monte Carlo'!$B$21),0) -> 0.21151376 | K16: =_xlfn.POISSON.DIST(0,($B$19*F16/'Monte Carlo'!$B$21),0) -> 0.28584918 | L16: =_xlfn.POISSON.DIST(1,($B$19*F16/'Monte Carlo'!$B$21),0) -> 0.35796634 | M16: =_xlfn.POISSON.DIST(2,($B$19*F16/'Monte Carlo'!$B$21),0) -> 0.224139 | N16: =_xlfn.POISSON.DIST(3,($B$19*F16/'Monte Carlo'!$B$21),0) -> 0.093562415 | Q16: 1 | R16: 0 | S16: =AVERAGE($H$2:$H$1001)*AVERAGE($K$2:$K$1001) -> 0.10317936
A17: Poisson (gols) | D17: 16 | E17: =MAX(0,MIN(100,ROUNDDOWN(_xlfn.NORM.INV(RAND(),((_xlfn.XLOOKUP($B$1,teams[Seleção],teams[Média dos jogadores],"",0,1)*'Monte Carlo'!$B$9)+(_xlfn.XLOOKUP($B$1,teams[Seleção],teams[Comissão Técnica],"",0,1)*'Monte Carlo'!$B$10)+(_xlfn.XLOOKUP($B$1,teams[Seleção],teams[FS_Norm],"",0,1)*'Monte Carlo'!$B$11)+(_xlfn.XLOOKUP($B$1,teams[Seleção],teams[ER_norm],"",0,1)*'Monte Carlo'!$B$12)),$B$14),0))) -> 73 | F17: =MAX(0,MIN(100,ROUNDDOWN(_xlfn.NORM.INV(RAND(),((_xlfn.XLOOKUP($B$3,teams[Seleção],teams[Média dos jogadores],"",0,1)*'Monte Carlo'!$B$9)+(_xlfn.XLOOKUP($B$3,teams[Seleção],teams[Comissão Técnica],"",0,1)*'Monte Carlo'!$B$10)+(_xlfn.XLOOKUP($B$3,teams[Seleção],teams[FS_Norm],"",0,1)*'Monte Carlo'!$B$11)+(_xlfn.XLOOKUP($B$3,teams[Seleção],teams[ER_norm],"",0,1)*'Monte Carlo'!$B$12)),$B$14),0))) -> 36 | G17: =_xlfn.POISSON.DIST(0,($B$18*E17/'Monte Carlo'!$B$21),FALSE) -> 0.13706071 | H17: =_xlfn.POISSON.DIST(1,($B$18*E17/'Monte Carlo'!$B$21),0) -> 0.27238505 | I17: =_xlfn.POISSON.DIST(2,($B$18*E17/'Monte Carlo'!$B$21),0) -> 0.27065966 | J17: =_xlfn.POISSON.DIST(3,($B$18*E17/'Monte Carlo'!$B$21),0) -> 0.1792968 | K17: =_xlfn.POISSON.DIST(0,($B$19*F17/'Monte Carlo'!$B$21),0) -> 0.61260992 | L17: =_xlfn.POISSON.DIST(1,($B$19*F17/'Monte Carlo'!$B$21),0) -> 0.30019533 | M17: =_xlfn.POISSON.DIST(2,($B$19*F17/'Monte Carlo'!$B$21),0) -> 0.073551893 | N17: =_xlfn.POISSON.DIST(3,($B$19*F17/'Monte Carlo'!$B$21),0) -> 0.012014135 | Q17: 1 | R17: 1 | S17: =AVERAGE($H$2:$H$1001)*AVERAGE($L$2:$L$1001) -> 0.090300238
A18: λA | B18: =ROUND((_xlfn.XLOOKUP($B$1,Tabela8[Seleção],Tabela8[Média de gols feitos],"",0,1)+_xlfn.XLOOKUP('Monte Carlo'!$B$3,Tabela8[Seleção],Tabela8[Média de gols sofridos],"",0,1))/2,0) -> 2 | D18: 17 | E18: =MAX(0,MIN(100,ROUNDDOWN(_xlfn.NORM.INV(RAND(),((_xlfn.XLOOKUP($B$1,teams[Seleção],teams[Média dos jogadores],"",0,1)*'Monte Carlo'!$B$9)+(_xlfn.XLOOKUP($B$1,teams[Seleção],teams[Comissão Técnica],"",0,1)*'Monte Carlo'!$B$10)+(_xlfn.XLOOKUP($B$1,teams[Seleção],teams[FS_Norm],"",0,1)*'Monte Carlo'!$B$11)+(_xlfn.XLOOKUP($B$1,teams[Seleção],teams[ER_norm],"",0,1)*'Monte Carlo'!$B$12)),$B$14),0))) -> 85 | F18: =MAX(0,MIN(100,ROUNDDOWN(_xlfn.NORM.INV(RAND(),((_xlfn.XLOOKUP($B$3,teams[Seleção],teams[Média dos jogadores],"",0,1)*'Monte Carlo'!$B$9)+(_xlfn.XLOOKUP($B$3,teams[Seleção],teams[Comissão Técnica],"",0,1)*'Monte Carlo'!$B$10)+(_xlfn.XLOOKUP($B$3,teams[Seleção],teams[FS_Norm],"",0,1)*'Monte Carlo'!$B$11)+(_xlfn.XLOOKUP($B$3,teams[Seleção],teams[ER_norm],"",0,1)*'Monte Carlo'!$B$12)),$B$14),0))) -> 68 | G18: =_xlfn.POISSON.DIST(0,($B$18*E18/'Monte Carlo'!$B$21),FALSE) -> 0.09886343 | H18: =_xlfn.POISSON.DIST(1,($B$18*E18/'Monte Carlo'!$B$21),0) -> 0.22877155 | I18: =_xlfn.POISSON.DIST(2,($B$18*E18/'Monte Carlo'!$B$21),0) -> 0.2646905 | J18: =_xlfn.POISSON.DIST(3,($B$18*E18/'Monte Carlo'!$B$21),0) -> 0.204166 | K18: =_xlfn.POISSON.DIST(0,($B$19*F18/'Monte Carlo'!$B$21),0) -> 0.39629106 | L18: =_xlfn.POISSON.DIST(1,($B$19*F18/'Monte Carlo'!$B$21),0) -> 0.36680952 | M18: =_xlfn.POISSON.DIST(2,($B$19*F18/'Monte Carlo'!$B$21),0) -> 0.16976061 | N18: =_xlfn.POISSON.DIST(3,($B$19*F18/'Monte Carlo'!$B$21),0) -> 0.052377166 | Q18: 1 | R18: 2 | S18: =AVERAGE($H$2:$H$1001)*AVERAGE($M$2:$M$1001) -> 0.040561254
A19: λB | B19: =ROUND((_xlfn.XLOOKUP($B$3,Tabela8[Seleção],Tabela8[Média de gols feitos],"",0,1)+_xlfn.XLOOKUP($B$1,Tabela8[Seleção],Tabela8[Média de gols sofridos],"",0,1))/2,0) -> 1 | D19: 18 | E19: =MAX(0,MIN(100,ROUNDDOWN(_xlfn.NORM.INV(RAND(),((_xlfn.XLOOKUP($B$1,teams[Seleção],teams[Média dos jogadores],"",0,1)*'Monte Carlo'!$B$9)+(_xlfn.XLOOKUP($B$1,teams[Seleção],teams[Comissão Técnica],"",0,1)*'Monte Carlo'!$B$10)+(_xlfn.XLOOKUP($B$1,teams[Seleção],teams[FS_Norm],"",0,1)*'Monte Carlo'!$B$11)+(_xlfn.XLOOKUP($B$1,teams[Seleção],teams[ER_norm],"",0,1)*'Monte Carlo'!$B$12)),$B$14),0))) -> 83 | F19: =MAX(0,MIN(100,ROUNDDOWN(_xlfn.NORM.INV(RAND(),((_xlfn.XLOOKUP($B$3,teams[Seleção],teams[Média dos jogadores],"",0,1)*'Monte Carlo'!$B$9)+(_xlfn.XLOOKUP($B$3,teams[Seleção],teams[Comissão Técnica],"",0,1)*'Monte Carlo'!$B$10)+(_xlfn.XLOOKUP($B$3,teams[Seleção],teams[FS_Norm],"",0,1)*'Monte Carlo'!$B$11)+(_xlfn.XLOOKUP($B$3,teams[Seleção],teams[ER_norm],"",0,1)*'Monte Carlo'!$B$12)),$B$14),0))) -> 60 | G19: =_xlfn.POISSON.DIST(0,($B$18*E19/'Monte Carlo'!$B$21),FALSE) -> 0.10439553 | H19: =_xlfn.POISSON.DIST(1,($B$18*E19/'Monte Carlo'!$B$21),0) -> 0.23588884 | I19: =_xlfn.POISSON.DIST(2,($B$18*E19/'Monte Carlo'!$B$21),0) -> 0.26650349 | J19: =_xlfn.POISSON.DIST(3,($B$18*E19/'Monte Carlo'!$B$21),0) -> 0.20072762 | K19: =_xlfn.POISSON.DIST(0,($B$19*F19/'Monte Carlo'!$B$21),0) -> 0.4418824 | L19: =_xlfn.POISSON.DIST(1,($B$19*F19/'Monte Carlo'!$B$21),0) -> 0.36089043 | M19: =_xlfn.POISSON.DIST(2,($B$19*F19/'Monte Carlo'!$B$21),0) -> 0.14737168 | N19: =_xlfn.POISSON.DIST(3,($B$19*F19/'Monte Carlo'!$B$21),0) -> 0.040120048 | Q19: 1 | R19: 3 | S19: =AVERAGE($H$2:$H$1001)*AVERAGE($N$2:$N$1001) -> 0.012447429
D20: 19 | E20: =MAX(0,MIN(100,ROUNDDOWN(_xlfn.NORM.INV(RAND(),((_xlfn.XLOOKUP($B$1,teams[Seleção],teams[Média dos jogadores],"",0,1)*'Monte Carlo'!$B$9)+(_xlfn.XLOOKUP($B$1,teams[Seleção],teams[Comissão Técnica],"",0,1)*'Monte Carlo'!$B$10)+(_xlfn.XLOOKUP($B$1,teams[Seleção],teams[FS_Norm],"",0,1)*'Monte Carlo'!$B$11)+(_xlfn.XLOOKUP($B$1,teams[Seleção],teams[ER_norm],"",0,1)*'Monte Carlo'!$B$12)),$B$14),0))) -> 81 | F20: =MAX(0,MIN(100,ROUNDDOWN(_xlfn.NORM.INV(RAND(),((_xlfn.XLOOKUP($B$3,teams[Seleção],teams[Média dos jogadores],"",0,1)*'Monte Carlo'!$B$9)+(_xlfn.XLOOKUP($B$3,teams[Seleção],teams[Comissão Técnica],"",0,1)*'Monte Carlo'!$B$10)+(_xlfn.XLOOKUP($B$3,teams[Seleção],teams[FS_Norm],"",0,1)*'Monte Carlo'!$B$11)+(_xlfn.XLOOKUP($B$3,teams[Seleção],teams[ER_norm],"",0,1)*'Monte Carlo'!$B$12)),$B$14),0))) -> 67 | G20: =_xlfn.POISSON.DIST(0,($B$18*E20/'Monte Carlo'!$B$21),FALSE) -> 0.11023718 | H20: =_xlfn.POISSON.DIST(1,($B$18*E20/'Monte Carlo'!$B$21),0) -> 0.24308633 | I20: =_xlfn.POISSON.DIST(2,($B$18*E20/'Monte Carlo'!$B$21),0) -> 0.26801739 | J20: =_xlfn.POISSON.DIST(3,($B$18*E20/'Monte Carlo'!$B$21),0) -> 0.19700359 | K20: =_xlfn.POISSON.DIST(0,($B$19*F20/'Monte Carlo'!$B$21),0) -> 0.40172219 | L20: =_xlfn.POISSON.DIST(1,($B$19*F20/'Monte Carlo'!$B$21),0) -> 0.36636843 | M20: =_xlfn.POISSON.DIST(2,($B$19*F20/'Monte Carlo'!$B$21),0) -> 0.16706299 | N20: =_xlfn.POISSON.DIST(3,($B$19*F20/'Monte Carlo'!$B$21),0) -> 0.050786843 | Q20: 2 | R20: 0 | S20: =AVERAGE($I$2:$I$1001)*AVERAGE($K$2:$K$1001) -> 0.10928481
A21: Overall | B21: =AVERAGE(Seleções!M2:M5) -> 73.465356 | D21: 20 | E21: =MAX(0,MIN(100,ROUNDDOWN(_xlfn.NORM.INV(RAND(),((_xlfn.XLOOKUP($B$1,teams[Seleção],teams[Média dos jogadores],"",0,1)*'Monte Carlo'!$B$9)+(_xlfn.XLOOKUP($B$1,teams[Seleção],teams[Comissão Técnica],"",0,1)*'Monte Carlo'!$B$10)+(_xlfn.XLOOKUP($B$1,teams[Seleção],teams[FS_Norm],"",0,1)*'Monte Carlo'!$B$11)+(_xlfn.XLOOKUP($B$1,teams[Seleção],teams[ER_norm],"",0,1)*'Monte Carlo'!$B$12)),$B$14),0))) -> 69 | F21: =MAX(0,MIN(100,ROUNDDOWN(_xlfn.NORM.INV(RAND(),((_xlfn.XLOOKUP($B$3,teams[Seleção],teams[Média dos jogadores],"",0,1)*'Monte Carlo'!$B$9)+(_xlfn.XLOOKUP($B$3,teams[Seleção],teams[Comissão Técnica],"",0,1)*'Monte Carlo'!$B$10)+(_xlfn.XLOOKUP($B$3,teams[Seleção],teams[FS_Norm],"",0,1)*'Monte Carlo'!$B$11)+(_xlfn.XLOOKUP($B$3,teams[Seleção],teams[ER_norm],"",0,1)*'Monte Carlo'!$B$12)),$B$14),0))) -> 55 | G21: =_xlfn.POISSON.DIST(0,($B$18*E21/'Monte Carlo'!$B$21),FALSE) -> 0.15282888 | H21: =_xlfn.POISSON.DIST(1,($B$18*E21/'Monte Carlo'!$B$21),0) -> 0.28707933 | I21: =_xlfn.POISSON.DIST(2,($B$18*E21/'Monte Carlo'!$B$21),0) -> 0.26963014 | J21: =_xlfn.POISSON.DIST(3,($B$18*E21/'Monte Carlo'!$B$21),0) -> 0.16882769 | K21: =_xlfn.POISSON.DIST(0,($B$19*F21/'Monte Carlo'!$B$21),0) -> 0.47300364 | L21: =_xlfn.POISSON.DIST(1,($B$19*F21/'Monte Carlo'!$B$21),0) -> 0.35411521 | M21: =_xlfn.POISSON.DIST(2,($B$19*F21/'Monte Carlo'!$B$21),0) -> 0.13255457 | N21: =_xlfn.POISSON.DIST(3,($B$19*F21/'Monte Carlo'!$B$21),0) -> 0.033079089 | Q21: 2 | R21: 1 | S21: =AVERAGE($I$2:$I$1001)*AVERAGE($L$2:$L$1001) -> 0.095643589
D22: 21 | E22: =MAX(0,MIN(100,ROUNDDOWN(_xlfn.NORM.INV(RAND(),((_xlfn.XLOOKUP($B$1,teams[Seleção],teams[Média dos jogadores],"",0,1)*'Monte Carlo'!$B$9)+(_xlfn.XLOOKUP($B$1,teams[Seleção],teams[Comissão Técnica],"",0,1)*'Monte Carlo'!$B$10)+(_xlfn.XLOOKUP($B$1,teams[Seleção],teams[FS_Norm],"",0,1)*'Monte Carlo'!$B$11)+(_xlfn.XLOOKUP($B$1,teams[Seleção],teams[ER_norm],"",0,1)*'Monte Carlo'!$B$12)),$B$14),0))) -> 72 | F22: =MAX(0,MIN(100,ROUNDDOWN(_xlfn.NORM.INV(RAND(),((_xlfn.XLOOKUP($B$3,teams[Seleção],teams[Média dos jogadores],"",0,1)*'Monte Carlo'!$B$9)+(_xlfn.XLOOKUP($B$3,teams[Seleção],teams[Comissão Técnica],"",0,1)*'Monte Carlo'!$B$10)+(_xlfn.XLOOKUP($B$3,teams[Seleção],teams[FS_Norm],"",0,1)*'Monte Carlo'!$B$11)+(_xlfn.XLOOKUP($B$3,teams[Seleção],teams[ER_norm],"",0,1)*'Monte Carlo'!$B$12)),$B$14),0))) -> 67 | G22: =_xlfn.POISSON.DIST(0,($B$18*E22/'Monte Carlo'!$B$21),FALSE) -> 0.14084327 | H22: =_xlfn.POISSON.DIST(1,($B$18*E22/'Monte Carlo'!$B$21),0) -> 0.27606796 | I22: =_xlfn.POISSON.DIST(2,($B$18*E22/'Monte Carlo'!$B$21),0) -> 0.27056145 | J22: =_xlfn.POISSON.DIST(3,($B$18*E22/'Monte Carlo'!$B$21),0) -> 0.17677651 | K22: =_xlfn.POISSON.DIST(0,($B$19*F22/'Monte Carlo'!$B$21),0) -> 0.40172219 | L22: =_xlfn.POISSON.DIST(1,($B$19*F22/'Monte Carlo'!$B$21),0) -> 0.36636843 | M22: =_xlfn.POISSON.DIST(2,($B$19*F22/'Monte Carlo'!$B$21),0) -> 0.16706299 | N22: =_xlfn.POISSON.DIST(3,($B$19*F22/'Monte Carlo'!$B$21),0) -> 0.050786843 | Q22: 2 | R22: 2 | S22: =AVERAGE($I$2:$I$1001)*AVERAGE($M$2:$M$1001) -> 0.042961392
D23: 22 | E23: =MAX(0,MIN(100,ROUNDDOWN(_xlfn.NORM.INV(RAND(),((_xlfn.XLOOKUP($B$1,teams[Seleção],teams[Média dos jogadores],"",0,1)*'Monte Carlo'!$B$9)+(_xlfn.XLOOKUP($B$1,teams[Seleção],teams[Comissão Técnica],"",0,1)*'Monte Carlo'!$B$10)+(_xlfn.XLOOKUP($B$1,teams[Seleção],teams[FS_Norm],"",0,1)*'Monte Carlo'!$B$11)+(_xlfn.XLOOKUP($B$1,teams[Seleção],teams[ER_norm],"",0,1)*'Monte Carlo'!$B$12)),$B$14),0))) -> 83 | F23: =MAX(0,MIN(100,ROUNDDOWN(_xlfn.NORM.INV(RAND(),((_xlfn.XLOOKUP($B$3,teams[Seleção],teams[Média dos jogadores],"",0,1)*'Monte Carlo'!$B$9)+(_xlfn.XLOOKUP($B$3,teams[Seleção],teams[Comissão Técnica],"",0,1)*'Monte Carlo'!$B$10)+(_xlfn.XLOOKUP($B$3,teams[Seleção],teams[FS_Norm],"",0,1)*'Monte Carlo'!$B$11)+(_xlfn.XLOOKUP($B$3,teams[Seleção],teams[ER_norm],"",0,1)*'Monte Carlo'!$B$12)),$B$14),0))) -> 74 | G23: =_xlfn.POISSON.DIST(0,($B$18*E23/'Monte Carlo'!$B$21),FALSE) -> 0.10439553 | H23: =_xlfn.POISSON.DIST(1,($B$18*E23/'Monte Carlo'!$B$21),0) -> 0.23588884 | I23: =_xlfn.POISSON.DIST(2,($B$18*E23/'Monte Carlo'!$B$21),0) -> 0.26650349 | J23: =_xlfn.POISSON.DIST(3,($B$18*E23/'Monte Carlo'!$B$21),0) -> 0.20072762 | K23: =_xlfn.POISSON.DIST(0,($B$19*F23/'Monte Carlo'!$B$21),0) -> 0.36521192 | L23: =_xlfn.POISSON.DIST(1,($B$19*F23/'Monte Carlo'!$B$21),0) -> 0.36786975 | M23: =_xlfn.POISSON.DIST(2,($B$19*F23/'Monte Carlo'!$B$21),0) -> 0.18527346 | N23: =_xlfn.POISSON.DIST(3,($B$19*F23/'Monte Carlo'!$B$21),0) -> 0.062207262 | Q23: 2 | R23: 3 | S23: =AVERAGE($I$2:$I$1001)*AVERAGE($N$2:$N$1001) -> 0.013183983
D24: 23 | E24: =MAX(0,MIN(100,ROUNDDOWN(_xlfn.NORM.INV(RAND(),((_xlfn.XLOOKUP($B$1,teams[Seleção],teams[Média dos jogadores],"",0,1)*'Monte Carlo'!$B$9)+(_xlfn.XLOOKUP($B$1,teams[Seleção],teams[Comissão Técnica],"",0,1)*'Monte Carlo'!$B$10)+(_xlfn.XLOOKUP($B$1,teams[Seleção],teams[FS_Norm],"",0,1)*'Monte Carlo'!$B$11)+(_xlfn.XLOOKUP($B$1,teams[Seleção],teams[ER_norm],"",0,1)*'Monte Carlo'!$B$12)),$B$14),0))) -> 78 | F24: =MAX(0,MIN(100,ROUNDDOWN(_xlfn.NORM.INV(RAND(),((_xlfn.XLOOKUP($B$3,teams[Seleção],teams[Média dos jogadores],"",0,1)*'Monte Carlo'!$B$9)+(_xlfn.XLOOKUP($B$3,teams[Seleção],teams[Comissão Técnica],"",0,1)*'Monte Carlo'!$B$10)+(_xlfn.XLOOKUP($B$3,teams[Seleção],teams[FS_Norm],"",0,1)*'Monte Carlo'!$B$11)+(_xlfn.XLOOKUP($B$3,teams[Seleção],teams[ER_norm],"",0,1)*'Monte Carlo'!$B$12)),$B$14),0))) -> 67 | G24: =_xlfn.POISSON.DIST(0,($B$18*E24/'Monte Carlo'!$B$21),FALSE) -> 0.11961825 | H24: =_xlfn.POISSON.DIST(1,($B$18*E24/'Monte Carlo'!$B$21),0) -> 0.25400336 | I24: =_xlfn.POISSON.DIST(2,($B$18*E24/'Monte Carlo'!$B$21),0) -> 0.26968169 | J24: =_xlfn.POISSON.DIST(3,($B$18*E24/'Monte Carlo'!$B$21),0) -> 0.19088519 | K24: =_xlfn.POISSON.DIST(0,($B$19*F24/'Monte Carlo'!$B$21),0) -> 0.40172219 | L24: =_xlfn.POISSON.DIST(1,($B$19*F24/'Monte Carlo'!$B$21),0) -> 0.36636843 | M24: =_xlfn.POISSON.DIST(2,($B$19*F24/'Monte Carlo'!$B$21),0) -> 0.16706299 | N24: =_xlfn.POISSON.DIST(3,($B$19*F24/'Monte Carlo'!$B$21),0) -> 0.050786843 | Q24: 3 | R24: 0 | S24: =AVERAGE($J$2:$J$1001)*AVERAGE($K$2:$K$1001) -> 0.078415752
D25: 24 | E25: =MAX(0,MIN(100,ROUNDDOWN(_xlfn.NORM.INV(RAND(),((_xlfn.XLOOKUP($B$1,teams[Seleção],teams[Média dos jogadores],"",0,1)*'Monte Carlo'!$B$9)+(_xlfn.XLOOKUP($B$1,teams[Seleção],teams[Comissão Técnica],"",0,1)*'Monte Carlo'!$B$10)+(_xlfn.XLOOKUP($B$1,teams[Seleção],teams[FS_Norm],"",0,1)*'Monte Carlo'!$B$11)+(_xlfn.XLOOKUP($B$1,teams[Seleção],teams[ER_norm],"",0,1)*'Monte Carlo'!$B$12)),$B$14),0))) -> 70 | F25: =MAX(0,MIN(100,ROUNDDOWN(_xlfn.NORM.INV(RAND(),((_xlfn.XLOOKUP($B$3,teams[Seleção],teams[Média dos jogadores],"",0,1)*'Monte Carlo'!$B$9)+(_xlfn.XLOOKUP($B$3,teams[Seleção],teams[Comissão Técnica],"",0,1)*'Monte Carlo'!$B$10)+(_xlfn.XLOOKUP($B$3,teams[Seleção],teams[FS_Norm],"",0,1)*'Monte Carlo'!$B$11)+(_xlfn.XLOOKUP($B$3,teams[Seleção],teams[ER_norm],"",0,1)*'Monte Carlo'!$B$12)),$B$14),0))) -> 61 | G25: =_xlfn.POISSON.DIST(0,($B$18*E25/'Monte Carlo'!$B$21),FALSE) -> 0.14872443 | H25: =_xlfn.POISSON.DIST(1,($B$18*E25/'Monte Carlo'!$B$21),0) -> 0.28341822 | I25: =_xlfn.POISSON.DIST(2,($B$18*E25/'Monte Carlo'!$B$21),0) -> 0.2700494 | J25: =_xlfn.POISSON.DIST(3,($B$18*E25/'Monte Carlo'!$B$21),0) -> 0.17154079 | K25: =_xlfn.POISSON.DIST(0,($B$19*F25/'Monte Carlo'!$B$21),0) -> 0.43590832 | L25: =_xlfn.POISSON.DIST(1,($B$19*F25/'Monte Carlo'!$B$21),0) -> 0.36194485 | M25: =_xlfn.POISSON.DIST(2,($B$19*F25/'Monte Carlo'!$B$21),0) -> 0.15026563 | N25: =_xlfn.POISSON.DIST(3,($B$19*F25/'Monte Carlo'!$B$21),0) -> 0.041589686 | Q25: 3 | R25: 1 | S25: =AVERAGE($J$2:$J$1001)*AVERAGE($L$2:$L$1001) -> 0.06862769
D26: 25 | E26: =MAX(0,MIN(100,ROUNDDOWN(_xlfn.NORM.INV(RAND(),((_xlfn.XLOOKUP($B$1,teams[Seleção],teams[Média dos jogadores],"",0,1)*'Monte Carlo'!$B$9)+(_xlfn.XLOOKUP($B$1,teams[Seleção],teams[Comissão Técnica],"",0,1)*'Monte Carlo'!$B$10)+(_xlfn.XLOOKUP($B$1,teams[Seleção],teams[FS_Norm],"",0,1)*'Monte Carlo'!$B$11)+(_xlfn.XLOOKUP($B$1,teams[Seleção],teams[ER_norm],"",0,1)*'Monte Carlo'!$B$12)),$B$14),0))) -> 85 | F26: =MAX(0,MIN(100,ROUNDDOWN(_xlfn.NORM.INV(RAND(),((_xlfn.XLOOKUP($B$3,teams[Seleção],teams[Média dos jogadores],"",0,1)*'Monte Carlo'!$B$9)+(_xlfn.XLOOKUP($B$3,teams[Seleção],teams[Comissão Técnica],"",0,1)*'Monte Carlo'!$B$10)+(_xlfn.XLOOKUP($B$3,teams[Seleção],teams[FS_Norm],"",0,1)*'Monte Carlo'!$B$11)+(_xlfn.XLOOKUP($B$3,teams[Seleção],teams[ER_norm],"",0,1)*'Monte Carlo'!$B$12)),$B$14),0))) -> 58 | G26: =_xlfn.POISSON.DIST(0,($B$18*E26/'Monte Carlo'!$B$21),FALSE) -> 0.09886343 | H26: =_xlfn.POISSON.DIST(1,($B$18*E26/'Monte Carlo'!$B$21),0) -> 0.22877155 | I26: =_xlfn.POISSON.DIST(2,($B$18*E26/'Monte Carlo'!$B$21),0) -> 0.2646905 | J26: =_xlfn.POISSON.DIST(3,($B$18*E26/'Monte Carlo'!$B$21),0) -> 0.204166 | K26: =_xlfn.POISSON.DIST(0,($B$19*F26/'Monte Carlo'!$B$21),0) -> 0.45407733 | L26: =_xlfn.POISSON.DIST(1,($B$19*F26/'Monte Carlo'!$B$21),0) -> 0.3584885 | M26: =_xlfn.POISSON.DIST(2,($B$19*F26/'Monte Carlo'!$B$21),0) -> 0.14151114 | N26: =_xlfn.POISSON.DIST(3,($B$19*F26/'Monte Carlo'!$B$21),0) -> 0.037240438 | Q26: 3 | R26: 2 | S26: =AVERAGE($J$2:$J$1001)*AVERAGE($M$2:$M$1001) -> 0.030826333
D27: 26 | E27: =MAX(0,MIN(100,ROUNDDOWN(_xlfn.NORM.INV(RAND(),((_xlfn.XLOOKUP($B$1,teams[Seleção],teams[Média dos jogadores],"",0,1)*'Monte Carlo'!$B$9)+(_xlfn.XLOOKUP($B$1,teams[Seleção],teams[Comissão Técnica],"",0,1)*'Monte Carlo'!$B$10)+(_xlfn.XLOOKUP($B$1,teams[Seleção],teams[FS_Norm],"",0,1)*'Monte Carlo'!$B$11)+(_xlfn.XLOOKUP($B$1,teams[Seleção],teams[ER_norm],"",0,1)*'Monte Carlo'!$B$12)),$B$14),0))) -> 85 | F27: =MAX(0,MIN(100,ROUNDDOWN(_xlfn.NORM.INV(RAND(),((_xlfn.XLOOKUP($B$3,teams[Seleção],teams[Média dos jogadores],"",0,1)*'Monte Carlo'!$B$9)+(_xlfn.XLOOKUP($B$3,teams[Seleção],teams[Comissão Técnica],"",0,1)*'Monte Carlo'!$B$10)+(_xlfn.XLOOKUP($B$3,teams[Seleção],teams[FS_Norm],"",0,1)*'Monte Carlo'!$B$11)+(_xlfn.XLOOKUP($B$3,teams[Seleção],teams[ER_norm],"",0,1)*'Monte Carlo'!$B$12)),$B$14),0))) -> 68 | G27: =_xlfn.POISSON.DIST(0,($B$18*E27/'Monte Carlo'!$B$21),FALSE) -> 0.09886343 | H27: =_xlfn.POISSON.DIST(1,($B$18*E27/'Monte Carlo'!$B$21),0) -> 0.22877155 | I27: =_xlfn.POISSON.DIST(2,($B$18*E27/'Monte Carlo'!$B$21),0) -> 0.2646905 | J27: =_xlfn.POISSON.DIST(3,($B$18*E27/'Monte Carlo'!$B$21),0) -> 0.204166 | K27: =_xlfn.POISSON.DIST(0,($B$19*F27/'Monte Carlo'!$B$21),0) -> 0.39629106 | L27: =_xlfn.POISSON.DIST(1,($B$19*F27/'Monte Carlo'!$B$21),0) -> 0.36680952 | M27: =_xlfn.POISSON.DIST(2,($B$19*F27/'Monte Carlo'!$B$21),0) -> 0.16976061 | N27: =_xlfn.POISSON.DIST(3,($B$19*F27/'Monte Carlo'!$B$21),0) -> 0.052377166 | Q27: 3 | R27: 3 | S27: =AVERAGE($J$2:$J$1001)*AVERAGE($N$2:$N$1001) -> 0.0094599784
D28: 27 | E28: =MAX(0,MIN(100,ROUNDDOWN(_xlfn.NORM.INV(RAND(),((_xlfn.XLOOKUP($B$1,teams[Seleção],teams[Média dos jogadores],"",0,1)*'Monte Carlo'!$B$9)+(_xlfn.XLOOKUP($B$1,teams[Seleção],teams[Comissão Técnica],"",0,1)*'Monte Carlo'!$B$10)+(_xlfn.XLOOKUP($B$1,teams[Seleção],teams[FS_Norm],"",0,1)*'Monte Carlo'!$B$11)+(_xlfn.XLOOKUP($B$1,teams[Seleção],teams[ER_norm],"",0,1)*'Monte Carlo'!$B$12)),$B$14),0))) -> 80 | F28: =MAX(0,MIN(100,ROUNDDOWN(_xlfn.NORM.INV(RAND(),((_xlfn.XLOOKUP($B$3,teams[Seleção],teams[Média dos jogadores],"",0,1)*'Monte Carlo'!$B$9)+(_xlfn.XLOOKUP($B$3,teams[Seleção],teams[Comissão Técnica],"",0,1)*'Monte Carlo'!$B$10)+(_xlfn.XLOOKUP($B$3,teams[Seleção],teams[FS_Norm],"",0,1)*'Monte Carlo'!$B$11)+(_xlfn.XLOOKUP($B$3,teams[Seleção],teams[ER_norm],"",0,1)*'Monte Carlo'!$B$12)),$B$14),0))) -> 66 | G28: =_xlfn.POISSON.DIST(0,($B$18*E28/'Monte Carlo'!$B$21),FALSE) -> 0.11327947 | H28: =_xlfn.POISSON.DIST(1,($B$18*E28/'Monte Carlo'!$B$21),0) -> 0.24671106 | I28: =_xlfn.POISSON.DIST(2,($B$18*E28/'Monte Carlo'!$B$21),0) -> 0.26865567 | J28: =_xlfn.POISSON.DIST(3,($B$18*E28/'Monte Carlo'!$B$21),0) -> 0.19503482 | K28: =_xlfn.POISSON.DIST(0,($B$19*F28/'Monte Carlo'!$B$21),0) -> 0.40722776 | L28: =_xlfn.POISSON.DIST(1,($B$19*F28/'Monte Carlo'!$B$21),0) -> 0.36584635 | M28: =_xlfn.POISSON.DIST(2,($B$19*F28/'Monte Carlo'!$B$21),0) -> 0.164335 | N28: =_xlfn.POISSON.DIST(3,($B$19*F28/'Monte Carlo'!$B$21),0) -> 0.049211905
D29: 28 | E29: =MAX(0,MIN(100,ROUNDDOWN(_xlfn.NORM.INV(RAND(),((_xlfn.XLOOKUP($B$1,teams[Seleção],teams[Média dos jogadores],"",0,1)*'Monte Carlo'!$B$9)+(_xlfn.XLOOKUP($B$1,teams[Seleção],teams[Comissão Técnica],"",0,1)*'Monte Carlo'!$B$10)+(_xlfn.XLOOKUP($B$1,teams[Seleção],teams[FS_Norm],"",0,1)*'Monte Carlo'!$B$11)+(_xlfn.XLOOKUP($B$1,teams[Seleção],teams[ER_norm],"",0,1)*'Monte Carlo'!$B$12)),$B$14),0))) -> 91 | F29: =MAX(0,MIN(100,ROUNDDOWN(_xlfn.NORM.INV(RAND(),((_xlfn.XLOOKUP($B$3,teams[Seleção],teams[Média dos jogadores],"",0,1)*'Monte Carlo'!$B$9)+(_xlfn.XLOOKUP($B$3,teams[Seleção],teams[Comissão Técnica],"",0,1)*'Monte Carlo'!$B$10)+(_xlfn.XLOOKUP($B$3,teams[Seleção],teams[FS_Norm],"",0,1)*'Monte Carlo'!$B$11)+(_xlfn.XLOOKUP($B$3,teams[Seleção],teams[ER_norm],"",0,1)*'Monte Carlo'!$B$12)),$B$14),0))) -> 66 | G29: =_xlfn.POISSON.DIST(0,($B$18*E29/'Monte Carlo'!$B$21),FALSE) -> 0.083964753 | H29: =_xlfn.POISSON.DIST(1,($B$18*E29/'Monte Carlo'!$B$21),0) -> 0.20801077 | I29: =_xlfn.POISSON.DIST(2,($B$18*E29/'Monte Carlo'!$B$21),0) -> 0.25765859 | J29: =_xlfn.POISSON.DIST(3,($B$18*E29/'Monte Carlo'!$B$21),0) -> 0.21277087 | K29: =_xlfn.POISSON.DIST(0,($B$19*F29/'Monte Carlo'!$B$21),0) -> 0.40722776 | L29: =_xlfn.POISSON.DIST(1,($B$19*F29/'Monte Carlo'!$B$21),0) -> 0.36584635 | M29: =_xlfn.POISSON.DIST(2,($B$19*F29/'Monte Carlo'!$B$21),0) -> 0.164335 | N29: =_xlfn.POISSON.DIST(3,($B$19*F29/'Monte Carlo'!$B$21),0) -> 0.049211905
D30: 29 | E30: =MAX(0,MIN(100,ROUNDDOWN(_xlfn.NORM.INV(RAND(),((_xlfn.XLOOKUP($B$1,teams[Seleção],teams[Média dos jogadores],"",0,1)*'Monte Carlo'!$B$9)+(_xlfn.XLOOKUP($B$1,teams[Seleção],teams[Comissão Técnica],"",0,1)*'Monte Carlo'!$B$10)+(_xlfn.XLOOKUP($B$1,teams[Seleção],teams[FS_Norm],"",0,1)*'Monte Carlo'!$B$11)+(_xlfn.XLOOKUP($B$1,teams[Seleção],teams[ER_norm],"",0,1)*'Monte Carlo'!$B$12)),$B$14),0))) -> 74 | F30: =MAX(0,MIN(100,ROUNDDOWN(_xlfn.NORM.INV(RAND(),((_xlfn.XLOOKUP($B$3,teams[Seleção],teams[Média dos jogadores],"",0,1)*'Monte Carlo'!$B$9)+(_xlfn.XLOOKUP($B$3,teams[Seleção],teams[Comissão Técnica],"",0,1)*'Monte Carlo'!$B$10)+(_xlfn.XLOOKUP($B$3,teams[Seleção],teams[FS_Norm],"",0,1)*'Monte Carlo'!$B$11)+(_xlfn.XLOOKUP($B$3,teams[Seleção],teams[ER_norm],"",0,1)*'Monte Carlo'!$B$12)),$B$14),0))) -> 57 | G30: =_xlfn.POISSON.DIST(0,($B$18*E30/'Monte Carlo'!$B$21),FALSE) -> 0.13337974 | H30: =_xlfn.POISSON.DIST(1,($B$18*E30/'Monte Carlo'!$B$21),0) -> 0.26870083 | I30: =_xlfn.POISSON.DIST(2,($B$18*E30/'Monte Carlo'!$B$21),0) -> 0.2706563 | J30: =_xlfn.POISSON.DIST(3,($B$18*E30/'Monte Carlo'!$B$21),0) -> 0.18175067 | K30: =_xlfn.POISSON.DIST(0,($B$19*F30/'Monte Carlo'!$B$21),0) -> 0.46030042 | L30: =_xlfn.POISSON.DIST(1,($B$19*F30/'Monte Carlo'!$B$21),0) -> 0.35713601 | M30: =_xlfn.POISSON.DIST(2,($B$19*F30/'Monte Carlo'!$B$21),0) -> 0.13854661 | N30: =_xlfn.POISSON.DIST(3,($B$19*F30/'Monte Carlo'!$B$21),0) -> 0.03583166
D31: 30 | E31: =MAX(0,MIN(100,ROUNDDOWN(_xlfn.NORM.INV(RAND(),((_xlfn.XLOOKUP($B$1,teams[Seleção],teams[Média dos jogadores],"",0,1)*'Monte Carlo'!$B$9)+(_xlfn.XLOOKUP($B$1,teams[Seleção],teams[Comissão Técnica],"",0,1)*'Monte Carlo'!$B$10)+(_xlfn.XLOOKUP($B$1,teams[Seleção],teams[FS_Norm],"",0,1)*'Monte Carlo'!$B$11)+(_xlfn.XLOOKUP($B$1,teams[Seleção],teams[ER_norm],"",0,1)*'Monte Carlo'!$B$12)),$B$14),0))) -> 74 | F31: =MAX(0,MIN(100,ROUNDDOWN(_xlfn.NORM.INV(RAND(),((_xlfn.XLOOKUP($B$3,teams[Seleção],teams[Média dos jogadores],"",0,1)*'Monte Carlo'!$B$9)+(_xlfn.XLOOKUP($B$3,teams[Seleção],teams[Comissão Técnica],"",0,1)*'Monte Carlo'!$B$10)+(_xlfn.XLOOKUP($B$3,teams[Seleção],teams[FS_Norm],"",0,1)*'Monte Carlo'!$B$11)+(_xlfn.XLOOKUP($B$3,teams[Seleção],teams[ER_norm],"",0,1)*'Monte Carlo'!$B$12)),$B$14),0))) -> 60 | G31: =_xlfn.POISSON.DIST(0,($B$18*E31/'Monte Carlo'!$B$21),FALSE) -> 0.13337974 | H31: =_xlfn.POISSON.DIST(1,($B$18*E31/'Monte Carlo'!$B$21),0) -> 0.26870083 | I31: =_xlfn.POISSON.DIST(2,($B$18*E31/'Monte Carlo'!$B$21),0) -> 0.2706563 | J31: =_xlfn.POISSON.DIST(3,($B$18*E31/'Monte Carlo'!$B$21),0) -> 0.18175067 | K31: =_xlfn.POISSON.DIST(0,($B$19*F31/'Monte Carlo'!$B$21),0) -> 0.4418824 | L31: =_xlfn.POISSON.DIST(1,($B$19*F31/'Monte Carlo'!$B$21),0) -> 0.36089043 | M31: =_xlfn.POISSON.DIST(2,($B$19*F31/'Monte Carlo'!$B$21),0) -> 0.14737168 | N31: =_xlfn.POISSON.DIST(3,($B$19*F31/'Monte Carlo'!$B$21),0) -> 0.040120048
D32: 31 | E32: =MAX(0,MIN(100,ROUNDDOWN(_xlfn.NORM.INV(RAND(),((_xlfn.XLOOKUP($B$1,teams[Seleção],teams[Média dos jogadores],"",0,1)*'Monte Carlo'!$B$9)+(_xlfn.XLOOKUP($B$1,teams[Seleção],teams[Comissão Técnica],"",0,1)*'Monte Carlo'!$B$10)+(_xlfn.XLOOKUP($B$1,teams[Seleção],teams[FS_Norm],"",0,1)*'Monte Carlo'!$B$11)+(_xlfn.XLOOKUP($B$1,teams[Seleção],teams[ER_norm],"",0,1)*'Monte Carlo'!$B$12)),$B$14),0))) -> 66 | F32: =MAX(0,MIN(100,ROUNDDOWN(_xlfn.NORM.INV(RAND(),((_xlfn.XLOOKUP($B$3,teams[Seleção],teams[Média dos jogadores],"",0,1)*'Monte Carlo'!$B$9)+(_xlfn.XLOOKUP($B$3,teams[Seleção],teams[Comissão Técnica],"",0,1)*'Monte Carlo'!$B$10)+(_xlfn.XLOOKUP($B$3,teams[Seleção],teams[FS_Norm],"",0,1)*'Monte Carlo'!$B$11)+(_xlfn.XLOOKUP($B$3,teams[Seleção],teams[ER_norm],"",0,1)*'Monte Carlo'!$B$12)),$B$14),0))) -> 75 | G32: =_xlfn.POISSON.DIST(0,($B$18*E32/'Monte Carlo'!$B$21),FALSE) -> 0.16583445 | H32: =_xlfn.POISSON.DIST(1,($B$18*E32/'Monte Carlo'!$B$21),0) -> 0.29796558 | I32: =_xlfn.POISSON.DIST(2,($B$18*E32/'Monte Carlo'!$B$21),0) -> 0.26768711 | J32: =_xlfn.POISSON.DIST(3,($B$18*E32/'Monte Carlo'!$B$21),0) -> 0.16032363 | K32: =_xlfn.POISSON.DIST(0,($B$19*F32/'Monte Carlo'!$B$21),0) -> 0.36027439 | L32: =_xlfn.POISSON.DIST(1,($B$19*F32/'Monte Carlo'!$B$21),0) -> 0.36780029 | M32: =_xlfn.POISSON.DIST(2,($B$19*F32/'Monte Carlo'!$B$21),0) -> 0.1877417 | N32: =_xlfn.POISSON.DIST(3,($B$19*F32/'Monte Carlo'!$B$21),0) -> 0.063887834
D33: 32 | E33: =MAX(0,MIN(100,ROUNDDOWN(_xlfn.NORM.INV(RAND(),((_xlfn.XLOOKUP($B$1,teams[Seleção],teams[Média dos jogadores],"",0,1)*'Monte Carlo'!$B$9)+(_xlfn.XLOOKUP($B$1,teams[Seleção],teams[Comissão Técnica],"",0,1)*'Monte Carlo'!$B$10)+(_xlfn.XLOOKUP($B$1,teams[Seleção],teams[FS_Norm],"",0,1)*'Monte Carlo'!$B$11)+(_xlfn.XLOOKUP($B$1,teams[Seleção],teams[ER_norm],"",0,1)*'Monte Carlo'!$B$12)),$B$14),0))) -> 57 | F33: =MAX(0,MIN(100,ROUNDDOWN(_xlfn.NORM.INV(RAND(),((_xlfn.XLOOKUP($B$3,teams[Seleção],teams[Média dos jogadores],"",0,1)*'Monte Carlo'!$B$9)+(_xlfn.XLOOKUP($B$3,teams[Seleção],teams[Comissão Técnica],"",0,1)*'Monte Carlo'!$B$10)+(_xlfn.XLOOKUP($B$3,teams[Seleção],teams[FS_Norm],"",0,1)*'Monte Carlo'!$B$11)+(_xlfn.XLOOKUP($B$3,teams[Seleção],teams[ER_norm],"",0,1)*'Monte Carlo'!$B$12)),$B$14),0))) -> 54 | G33: =_xlfn.POISSON.DIST(0,($B$18*E33/'Monte Carlo'!$B$21),FALSE) -> 0.21187648 | H33: =_xlfn.POISSON.DIST(1,($B$18*E33/'Monte Carlo'!$B$21),0) -> 0.32877971 | I33: =_xlfn.POISSON.DIST(2,($B$18*E33/'Monte Carlo'!$B$21),0) -> 0.25509226 | J33: =_xlfn.POISSON.DIST(3,($B$18*E33/'Monte Carlo'!$B$21),0) -> 0.13194663 | K33: =_xlfn.POISSON.DIST(0,($B$19*F33/'Monte Carlo'!$B$21),0) -> 0.47948612 | L33: =_xlfn.POISSON.DIST(1,($B$19*F33/'Monte Carlo'!$B$21),0) -> 0.35244164 | M33: =_xlfn.POISSON.DIST(2,($B$19*F33/'Monte Carlo'!$B$21),0) -> 0.12952941 | N33: =_xlfn.POISSON.DIST(3,($B$19*F33/'Monte Carlo'!$B$21),0) -> 0.031736447
D34: 33 | E34: =MAX(0,MIN(100,ROUNDDOWN(_xlfn.NORM.INV(RAND(),((_xlfn.XLOOKUP($B$1,teams[Seleção],teams[Média dos jogadores],"",0,1)*'Monte Carlo'!$B$9)+(_xlfn.XLOOKUP($B$1,teams[Seleção],teams[Comissão Técnica],"",0,1)*'Monte Carlo'!$B$10)+(_xlfn.XLOOKUP($B$1,teams[Seleção],teams[FS_Norm],"",0,1)*'Monte Carlo'!$B$11)+(_xlfn.XLOOKUP($B$1,teams[Seleção],teams[ER_norm],"",0,1)*'Monte Carlo'!$B$12)),$B$14),0))) -> 83 | F34: =MAX(0,MIN(100,ROUNDDOWN(_xlfn.NORM.INV(RAND(),((_xlfn.XLOOKUP($B$3,teams[Seleção],teams[Média dos jogadores],"",0,1)*'Monte Carlo'!$B$9)+(_xlfn.XLOOKUP($B$3,teams[Seleção],teams[Comissão Técnica],"",0,1)*'Monte Carlo'!$B$10)+(_xlfn.XLOOKUP($B$3,teams[Seleção],teams[FS_Norm],"",0,1)*'Monte Carlo'!$B$11)+(_xlfn.XLOOKUP($B$3,teams[Seleção],teams[ER_norm],"",0,1)*'Monte Carlo'!$B$12)),$B$14),0))) -> 77 | G34: =_xlfn.POISSON.DIST(0,($B$18*E34/'Monte Carlo'!$B$21),FALSE) -> 0.10439553 | H34: =_xlfn.POISSON.DIST(1,($B$18*E34/'Monte Carlo'!$B$21),0) -> 0.23588884 | I34: =_xlfn.POISSON.DIST(2,($B$18*E34/'Monte Carlo'!$B$21),0) -> 0.26650349 | J34: =_xlfn.POISSON.DIST(3,($B$18*E34/'Monte Carlo'!$B$21),0) -> 0.20072762 | K34: =_xlfn.POISSON.DIST(0,($B$19*F34/'Monte Carlo'!$B$21),0) -> 0.35059868 | L34: =_xlfn.POISSON.DIST(1,($B$19*F34/'Monte Carlo'!$B$21),0) -> 0.36746706 | M34: =_xlfn.POISSON.DIST(2,($B$19*F34/'Monte Carlo'!$B$21),0) -> 0.19257351 | N34: =_xlfn.POISSON.DIST(3,($B$19*F34/'Monte Carlo'!$B$21),0) -> 0.067279606
D35: 34 | E35: =MAX(0,MIN(100,ROUNDDOWN(_xlfn.NORM.INV(RAND(),((_xlfn.XLOOKUP($B$1,teams[Seleção],teams[Média dos jogadores],"",0,1)*'Monte Carlo'!$B$9)+(_xlfn.XLOOKUP($B$1,teams[Seleção],teams[Comissão Técnica],"",0,1)*'Monte Carlo'!$B$10)+(_xlfn.XLOOKUP($B$1,teams[Seleção],teams[FS_Norm],"",0,1)*'Monte Carlo'!$B$11)+(_xlfn.XLOOKUP($B$1,teams[Seleção],teams[ER_norm],"",0,1)*'Monte Carlo'!$B$12)),$B$14),0))) -> 83 | F35: =MAX(0,MIN(100,ROUNDDOWN(_xlfn.NORM.INV(RAND(),((_xlfn.XLOOKUP($B$3,teams[Seleção],teams[Média dos jogadores],"",0,1)*'Monte Carlo'!$B$9)+(_xlfn.XLOOKUP($B$3,teams[Seleção],teams[Comissão Técnica],"",0,1)*'Monte Carlo'!$B$10)+(_xlfn.XLOOKUP($B$3,teams[Seleção],teams[FS_Norm],"",0,1)*'Monte Carlo'!$B$11)+(_xlfn.XLOOKUP($B$3,teams[Seleção],teams[ER_norm],"",0,1)*'Monte Carlo'!$B$12)),$B$14),0))) -> 69 | G35: =_xlfn.POISSON.DIST(0,($B$18*E35/'Monte Carlo'!$B$21),FALSE) -> 0.10439553 | H35: =_xlfn.POISSON.DIST(1,($B$18*E35/'Monte Carlo'!$B$21),0) -> 0.23588884 | I35: =_xlfn.POISSON.DIST(2,($B$18*E35/'Monte Carlo'!$B$21),0) -> 0.26650349 | J35: =_xlfn.POISSON.DIST(3,($B$18*E35/'Monte Carlo'!$B$21),0) -> 0.20072762 | K35: =_xlfn.POISSON.DIST(0,($B$19*F35/'Monte Carlo'!$B$21),0) -> 0.39093334 | L35: =_xlfn.POISSON.DIST(1,($B$19*F35/'Monte Carlo'!$B$21),0) -> 0.36717172 | M35: =_xlfn.POISSON.DIST(2,($B$19*F35/'Monte Carlo'!$B$21),0) -> 0.17242718 | N35: =_xlfn.POISSON.DIST(3,($B$19*F35/'Monte Carlo'!$B$21),0) -> 0.053982249
D36: 35 | E36: =MAX(0,MIN(100,ROUNDDOWN(_xlfn.NORM.INV(RAND(),((_xlfn.XLOOKUP($B$1,teams[Seleção],teams[Média dos jogadores],"",0,1)*'Monte Carlo'!$B$9)+(_xlfn.XLOOKUP($B$1,teams[Seleção],teams[Comissão Técnica],"",0,1)*'Monte Carlo'!$B$10)+(_xlfn.XLOOKUP($B$1,teams[Seleção],teams[FS_Norm],"",0,1)*'Monte Carlo'!$B$11)+(_xlfn.XLOOKUP($B$1,teams[Seleção],teams[ER_norm],"",0,1)*'Monte Carlo'!$B$12)),$B$14),0))) -> 74 | F36: =MAX(0,MIN(100,ROUNDDOWN(_xlfn.NORM.INV(RAND(),((_xlfn.XLOOKUP($B$3,teams[Seleção],teams[Média dos jogadores],"",0,1)*'Monte Carlo'!$B$9)+(_xlfn.XLOOKUP($B$3,teams[Seleção],teams[Comissão Técnica],"",0,1)*'Monte Carlo'!$B$10)+(_xlfn.XLOOKUP($B$3,teams[Seleção],teams[FS_Norm],"",0,1)*'Monte Carlo'!$B$11)+(_xlfn.XLOOKUP($B$3,teams[Seleção],teams[ER_norm],"",0,1)*'Monte Carlo'!$B$12)),$B$14),0))) -> 53 | G36: =_xlfn.POISSON.DIST(0,($B$18*E36/'Monte Carlo'!$B$21),FALSE) -> 0.13337974 | H36: =_xlfn.POISSON.DIST(1,($B$18*E36/'Monte Carlo'!$B$21),0) -> 0.26870083 | I36: =_xlfn.POISSON.DIST(2,($B$18*E36/'Monte Carlo'!$B$21),0) -> 0.2706563 | J36: =_xlfn.POISSON.DIST(3,($B$18*E36/'Monte Carlo'!$B$21),0) -> 0.18175067 | K36: =_xlfn.POISSON.DIST(0,($B$19*F36/'Monte Carlo'!$B$21),0) -> 0.48605744 | L36: =_xlfn.POISSON.DIST(1,($B$19*F36/'Monte Carlo'!$B$21),0) -> 0.35065568 | M36: =_xlfn.POISSON.DIST(2,($B$19*F36/'Monte Carlo'!$B$21),0) -> 0.1264865 | N36: =_xlfn.POISSON.DIST(3,($B$19*F36/'Monte Carlo'!$B$21),0) -> 0.030416987
D37: 36 | E37: =MAX(0,MIN(100,ROUNDDOWN(_xlfn.NORM.INV(RAND(),((_xlfn.XLOOKUP($B$1,teams[Seleção],teams[Média dos jogadores],"",0,1)*'Monte Carlo'!$B$9)+(_xlfn.XLOOKUP($B$1,teams[Seleção],teams[Comissão Técnica],"",0,1)*'Monte Carlo'!$B$10)+(_xlfn.XLOOKUP($B$1,teams[Seleção],teams[FS_Norm],"",0,1)*'Monte Carlo'!$B$11)+(_xlfn.XLOOKUP($B$1,teams[Seleção],teams[ER_norm],"",0,1)*'Monte Carlo'!$B$12)),$B$14),0))) -> 70 | F37: =MAX(0,MIN(100,ROUNDDOWN(_xlfn.NORM.INV(RAND(),((_xlfn.XLOOKUP($B$3,teams[Seleção],teams[Média dos jogadores],"",0,1)*'Monte Carlo'!$B$9)+(_xlfn.XLOOKUP($B$3,teams[Seleção],teams[Comissão Técnica],"",0,1)*'Monte Carlo'!$B$10)+(_xlfn.XLOOKUP($B$3,teams[Seleção],teams[FS_Norm],"",0,1)*'Monte Carlo'!$B$11)+(_xlfn.XLOOKUP($B$3,teams[Seleção],teams[ER_norm],"",0,1)*'Monte Carlo'!$B$12)),$B$14),0))) -> 50 | G37: =_xlfn.POISSON.DIST(0,($B$18*E37/'Monte Carlo'!$B$21),FALSE) -> 0.14872443 | H37: =_xlfn.POISSON.DIST(1,($B$18*E37/'Monte Carlo'!$B$21),0) -> 0.28341822 | I37: =_xlfn.POISSON.DIST(2,($B$18*E37/'Monte Carlo'!$B$21),0) -> 0.2700494 | J37: =_xlfn.POISSON.DIST(3,($B$18*E37/'Monte Carlo'!$B$21),0) -> 0.17154079 | K37: =_xlfn.POISSON.DIST(0,($B$19*F37/'Monte Carlo'!$B$21),0) -> 0.50631671 | L37: =_xlfn.POISSON.DIST(1,($B$19*F37/'Monte Carlo'!$B$21),0) -> 0.34459556 | M37: =_xlfn.POISSON.DIST(2,($B$19*F37/'Monte Carlo'!$B$21),0) -> 0.11726465 | N37: =_xlfn.POISSON.DIST(3,($B$19*F37/'Monte Carlo'!$B$21),0) -> 0.026603162
D38: 37 | E38: =MAX(0,MIN(100,ROUNDDOWN(_xlfn.NORM.INV(RAND(),((_xlfn.XLOOKUP($B$1,teams[Seleção],teams[Média dos jogadores],"",0,1)*'Monte Carlo'!$B$9)+(_xlfn.XLOOKUP($B$1,teams[Seleção],teams[Comissão Técnica],"",0,1)*'Monte Carlo'!$B$10)+(_xlfn.XLOOKUP($B$1,teams[Seleção],teams[FS_Norm],"",0,1)*'Monte Carlo'!$B$11)+(_xlfn.XLOOKUP($B$1,teams[Seleção],teams[ER_norm],"",0,1)*'Monte Carlo'!$B$12)),$B$14),0))) -> 75 | F38: =MAX(0,MIN(100,ROUNDDOWN(_xlfn.NORM.INV(RAND(),((_xlfn.XLOOKUP($B$3,teams[Seleção],teams[Média dos jogadores],"",0,1)*'Monte Carlo'!$B$9)+(_xlfn.XLOOKUP($B$3,teams[Seleção],teams[Comissão Técnica],"",0,1)*'Monte Carlo'!$B$10)+(_xlfn.XLOOKUP($B$3,teams[Seleção],teams[FS_Norm],"",0,1)*'Monte Carlo'!$B$11)+(_xlfn.XLOOKUP($B$3,teams[Seleção],teams[ER_norm],"",0,1)*'Monte Carlo'!$B$12)),$B$14),0))) -> 70 | G38: =_xlfn.POISSON.DIST(0,($B$18*E38/'Monte Carlo'!$B$21),FALSE) -> 0.12979763 | H38: =_xlfn.POISSON.DIST(1,($B$18*E38/'Monte Carlo'!$B$21),0) -> 0.26501804 | I38: =_xlfn.POISSON.DIST(2,($B$18*E38/'Monte Carlo'!$B$21),0) -> 0.2705541 | J38: =_xlfn.POISSON.DIST(3,($B$18*E38/'Monte Carlo'!$B$21),0) -> 0.1841372 | K38: =_xlfn.POISSON.DIST(0,($B$19*F38/'Monte Carlo'!$B$21),0) -> 0.38564807 | L38: =_xlfn.POISSON.DIST(1,($B$19*F38/'Monte Carlo'!$B$21),0) -> 0.36745707 | M38: =_xlfn.POISSON.DIST(2,($B$19*F38/'Monte Carlo'!$B$21),0) -> 0.17506207 | N38: =_xlfn.POISSON.DIST(3,($B$19*F38/'Monte Carlo'!$B$21),0) -> 0.055601469
D39: 38 | E39: =MAX(0,MIN(100,ROUNDDOWN(_xlfn.NORM.INV(RAND(),((_xlfn.XLOOKUP($B$1,teams[Seleção],teams[Média dos jogadores],"",0,1)*'Monte Carlo'!$B$9)+(_xlfn.XLOOKUP($B$1,teams[Seleção],teams[Comissão Técnica],"",0,1)*'Monte Carlo'!$B$10)+(_xlfn.XLOOKUP($B$1,teams[Seleção],teams[FS_Norm],"",0,1)*'Monte Carlo'!$B$11)+(_xlfn.XLOOKUP($B$1,teams[Seleção],teams[ER_norm],"",0,1)*'Monte Carlo'!$B$12)),$B$14),0))) -> 74 | F39: =MAX(0,MIN(100,ROUNDDOWN(_xlfn.NORM.INV(RAND(),((_xlfn.XLOOKUP($B$3,teams[Seleção],teams[Média dos jogadores],"",0,1)*'Monte Carlo'!$B$9)+(_xlfn.XLOOKUP($B$3,teams[Seleção],teams[Comissão Técnica],"",0,1)*'Monte Carlo'!$B$10)+(_xlfn.XLOOKUP($B$3,teams[Seleção],teams[FS_Norm],"",0,1)*'Monte Carlo'!$B$11)+(_xlfn.XLOOKUP($B$3,teams[Seleção],teams[ER_norm],"",0,1)*'Monte Carlo'!$B$12)),$B$14),0))) -> 60 | G39: =_xlfn.POISSON.DIST(0,($B$18*E39/'Monte Carlo'!$B$21),FALSE) -> 0.13337974 | H39: =_xlfn.POISSON.DIST(1,($B$18*E39/'Monte Carlo'!$B$21),0) -> 0.26870083 | I39: =_xlfn.POISSON.DIST(2,($B$18*E39/'Monte Carlo'!$B$21),0) -> 0.2706563 | J39: =_xlfn.POISSON.DIST(3,($B$18*E39/'Monte Carlo'!$B$21),0) -> 0.18175067 | K39: =_xlfn.POISSON.DIST(0,($B$19*F39/'Monte Carlo'!$B$21),0) -> 0.4418824 | L39: =_xlfn.POISSON.DIST(1,($B$19*F39/'Monte Carlo'!$B$21),0) -> 0.36089043 | M39: =_xlfn.POISSON.DIST(2,($B$19*F39/'Monte Carlo'!$B$21),0) -> 0.14737168 | N39: =_xlfn.POISSON.DIST(3,($B$19*F39/'Monte Carlo'!$B$21),0) -> 0.040120048
... D1001: 1000 | E1001: =MAX(0,MIN(100,ROUNDDOWN(_xlfn.NORM.INV(RAND(),((_xlfn.XLOOKUP($B$1,teams[Seleção],teams[Média dos jogadores],"",0,1)*'Monte Carlo'!$B$9)+(_xlfn.XLOOKUP($B$1,teams[Seleção],teams[Comissão Técnica],"",0,1)*'Monte Carlo'!$B$10)+(_xlfn.XLOOKUP($B$1,teams[Seleção],teams[FS_Norm],"",0,1)*'Monte Carlo'!$B$11)+(_xlfn.XLOOKUP($B$1,teams[Seleção],teams[ER_norm],"",0,1)*'Monte Carlo'!$B$12)),$B$14),0))) -> 81 | F1001: =MAX(0,MIN(100,ROUNDDOWN(_xlfn.NORM.INV(RAND(),((_xlfn.XLOOKUP($B$3,teams[Seleção],teams[Média dos jogadores],"",0,1)*'Monte Carlo'!$B$9)+(_xlfn.XLOOKUP($B$3,teams[Seleção],teams[Comissão Técnica],"",0,1)*'Monte Carlo'!$B$10)+(_xlfn.XLOOKUP($B$3,teams[Seleção],teams[FS_Norm],"",0,1)*'Monte Carlo'!$B$11)+(_xlfn.XLOOKUP($B$3,teams[Seleção],teams[ER_norm],"",0,1)*'Monte Carlo'!$B$12)),$B$14),0))) -> 61 | G1001: =_xlfn.POISSON.DIST(0,($B$18*E1001/'Monte Carlo'!$B$21),FALSE) -> 0.11023718 | H1001: =_xlfn.POISSON.DIST(1,($B$18*E1001/'Monte Carlo'!$B$21),0) -> 0.24308633 | I1001: =_xlfn.POISSON.DIST(2,($B$18*E1001/'Monte Carlo'!$B$21),0) -> 0.26801739 | J1001: =_xlfn.POISSON.DIST(3,($B$18*E1001/'Monte Carlo'!$B$21),0) -> 0.19700359 | K1001: =_xlfn.POISSON.DIST(0,($B$19*F1001/'Monte Carlo'!$B$21),0) -> 0.43590832 | L1001: =_xlfn.POISSON.DIST(1,($B$19*F1001/'Monte Carlo'!$B$21),0) -> 0.36194485 | M1001: =_xlfn.POISSON.DIST(2,($B$19*F1001/'Monte Carlo'!$B$21),0) -> 0.15026563 | N1001: =_xlfn.POISSON.DIST(3,($B$19*F1001/'Monte Carlo'!$B$21),0) -> 0.041589686
E10003: =AVERAGE(E2:E10001) -> 79.199 | F10003: =AVERAGE(F2:F10001) -> 65.794

Sheet Probabilidades
A1: A/B | B1: Mexico | C1: South Africa | D1: South Korea | E1: Czechia | F1: Canada | G1: Bosnia-Herzegovina | H1: Qatar | I1: Switzerland | J1: Brazil | K1: Morocco | L1: Haiti | M1: Scotland | N1: USA | O1: Paraguay | P1: Australia | Q1: Turkiye | R1: Germany | S1: Curaçao | T1: Côte d'Ivoire | U1: Ecuador | V1: Netherlands | W1: Japan | X1: Sweden | Y1: Tunisia | Z1: Belgium | AA1: Egypt | AB1: IR Iran | AC1: New Zealand | AD1: Spain | AE1: Cabo Verde | AF1: Saudi Arabia | AG1: Uruguay | AH1: France | AI1: Senegal | AJ1: Iraq | AK1: Norway | AL1: Argentina | AM1: Algeria | AN1: Austria | AO1: Jordan | AP1: Portugal | AQ1: Congo | AR1: Uzbekistan | AS1: Colombia | AT1: England | AU1: Croatia | AV1: Ghana | AW1: Panama | BB1: Média
A2: Mexico | B2: 0 | C2: 0.8261 | D2: 0.6583 | E2: 0.8325 | F2: 0.6404 | G2: 0.7455 | H2: 0.9004 | I2: 0.6601 | J2: 0.622 | K2: 0.6851 | L2: 0.8161 | M2: 0.688 | N2: 0.606 | O2: 0.6987 | P2: 0.7261 | Q2: 0.4096 | R2: 0.2978 | S2: 0.9366 | T2: 0.6884 | U2: 0.6201 | V2: 0.376 | W2: 0.3869 | X2: 0.7842 | Y2: 0.8636 | Z2: 0.5112 | AA2: 0.6165 | AB2: 0.6666 | AC2: 0.8669 | AD2: 0.2503 | AE2: 0.8049 | AF2: 0.8779 | AG2: 0.5845 | AH2: 0.2318 | AI2: 0.4144 | AJ2: 0.8125 | AK2: 0.5687 | AL2: 0.2229 | AM2: 0.5949 | AN2: 0.5254 | AO2: 0.7519 | AP2: 0.4209 | AQ2: 0.6438 | AR2: 0.7758 | AS2: 0.5069 | AT2: 0.4051 | AU2: 0.4806 | AV2: 0.9236 | AW2: 0.677 | AX2: 0 | AY2: 0 | AZ2: 0 | BA2: 0 | BB2: 0.6436
A3: South Africa | B3: 0.1739 | C3: 0 | D3: 0.284 | E3: 0.5081 | F3: 0.2803 | G3: 0.3722 | H3: 0.6388 | I3: 0.2922 | J3: 0.2589 | K3: 0.303 | L3: 0.4787 | M3: 0.3209 | N3: 0.245 | O3: 0.3322 | P3: 0.3588 | Q3: 0.1135 | R3: 0.0606 | S3: 0.7194 | T3: 0.3108 | U3: 0.2453 | V3: 0.0915 | W3: 0.1059 | X3: 0.4259 | Y3: 0.5516 | Z3: 0.1651 | AA3: 0.2499 | AB3: 0.2871 | AC3: 0.553 | AD3: 0.0521 | AE3: 0.4579 | AF3: 0.5782 | AG3: 0.2329 | AH3: 0.0496 | AI3: 0.1224 | AJ3: 0.4696 | AK3: 0.216 | AL3: 0.0433 | AM3: 0.2318 | AN3: 0.18 | AO3: 0.3935 | AP3: 0.1187 | AQ3: 0.2737 | AR3: 0.4237 | AS3: 0.1719 | AT3: 0.1151 | AU3: 0.152 | AV3: 0.6796 | AW3: 0.3131 | AX3: 0 | AY3: 0 | AZ3: 0 | BA3: 0 | BB3: 0.2712
A4: South Korea | B4: 0.3417 | C4: 0.716 | D4: 0 | E4: 0.7224 | F4: 0.496 | G4: 0.6046 | H4: 0.8291 | I4: 0.5125 | J4: 0.4598 | K4: 0.5412 | L4: 0.7099 | M4: 0.5474 | N4: 0.4639 | O4: 0.5477 | P4: 0.5892 | Q4: 0.2691 | R4: 0.1754 | S4: 0.8779 | T4: 0.5497 | U4: 0.4608 | V4: 0.2335 | W4: 0.2464 | X4: 0.6602 | Y4: 0.7656 | Z4: 0.3495 | AA4: 0.4677 | AB4: 0.5115 | AC4: 0.7559 | AD4: 0.1494 | AE4: 0.6833 | AF4: 0.7863 | AG4: 0.4368 | AH4: 0.1368 | AI4: 0.2811 | AJ4: 0.6796 | AK4: 0.4162 | AL4: 0.1184 | AM4: 0.443 | AN4: 0.3726 | AO4: 0.6231 | AP4: 0.291 | AQ4: 0.4935 | AR4: 0.6499 | AS4: 0.3556 | AT4: 0.2593 | AU4: 0.3302 | AV4: 0.8499 | AW4: 0.5295 | AX4: 0 | AY4: 0 | AZ4: 0 | BA4: 0 | BB4: 0.4874
A5: Czechia | B5: 0.1675 | C5: 0.4919 | D5: 0.2776 | E5: 0 | F5: 0.2752 | G5: 0.381 | H5: 0.6329 | I5: 0.2927 | J5: 0.2443 | K5: 0.3106 | L5: 0.4742 | M5: 0.3119 | N5: 0.2469 | O5: 0.3202 | P5: 0.3578 | Q5: 0.1171 | R5: 0.0638 | S5: 0.7159 | T5: 0.3229 | U5: 0.2504 | V5: 0.1011 | W5: 0.1084 | X5: 0.4216 | Y5: 0.5512 | Z5: 0.1642 | AA5: 0.251 | AB5: 0.2916 | AC5: 0.5447 | AD5: 0.0513 | AE5: 0.4511 | AF5: 0.5744 | AG5: 0.2257 | AH5: 0.044 | AI5: 0.1192 | AJ5: 0.4666 | AK5: 0.2126 | AL5: 0.0392 | AM5: 0.2459 | AN5: 0.1771 | AO5: 0.3988 | AP5: 0.1209 | AQ5: 0.2767 | AR5: 0.4125 | AS5: 0.1692 | AT5: 0.1087 | AU5: 0.1528 | AV5: 0.6764 | AW5: 0.3114 | AX5: 0 | AY5: 0 | AZ5: 0 | BA5: 0 | BB5: 0.2781
A6: Canada | B6: 0.3596 | C6: 0.7197 | D6: 0.504 | E6: 0.7248 | F6: 0 | G6: 0.6148 | H6: 0.8307 | I6: 0.5274 | J6: 0.4722 | K6: 0.5483 | L6: 0.7133 | M6: 0.5406 | N6: 0.4652 | O6: 0.5614 | P6: 0.6006 | Q6: 0.277 | R6: 0.1813 | S6: 0.8798 | T6: 0.5623 | U6: 0.4762 | V6: 0.2327 | W6: 0.2548 | X6: 0.6596 | Y6: 0.7638 | Z6: 0.3578 | AA6: 0.4748 | AB6: 0.5259 | AC6: 0.7656 | AD6: 0.1467 | AE6: 0.6829 | AF6: 0.7834 | AG6: 0.4413 | AH6: 0.1418 | AI6: 0.2827 | AJ6: 0.6936 | AK6: 0.4228 | AL6: 0.1287 | AM6: 0.4569 | AN6: 0.3668 | AO6: 0.6304 | AP6: 0.2863 | AQ6: 0.4925 | AR6: 0.6566 | AS6: 0.3644 | AT6: 0.2705 | AU6: 0.3343 | AV6: 0.851 | AW6: 0.5332 | AX6: 0 | AY6: 0 | AZ6: 0 | BA6: 0 | BB6: 0.5082
A7: Bosnia-Herzegovina | B7: 0.2545 | C7: 0.6278 | D7: 0.3954 | E7: 0.619 | F7: 0.3852 | G7: 0 | H7: 0.7498 | I7: 0.4162 | J7: 0.3516 | K7: 0.4248 | L7: 0.5968 | M7: 0.4351 | N7: 0.3529 | O7: 0.454 | P7: 0.4768 | Q7: 0.1901 | R7: 0.1182 | S7: 0.8161 | T7: 0.4487 | U7: 0.345 | V7: 0.1543 | W7: 0.1757 | X7: 0.5523 | Y7: 0.6745 | Z7: 0.2562 | AA7: 0.3589 | AB7: 0.4041 | AC7: 0.6626 | AD7: 0.0879 | AE7: 0.5795 | AF7: 0.6924 | AG7: 0.3292 | AH7: 0.0851 | AI7: 0.1952 | AJ7: 0.594 | AK7: 0.3192 | AL7: 0.0833 | AM7: 0.3456 | AN7: 0.2769 | AO7: 0.5226 | AP7: 0.1978 | AQ7: 0.3873 | AR7: 0.5438 | AS7: 0.2629 | AT7: 0.1909 | AU7: 0.2437 | AV7: 0.7729 | AW7: 0.4201 | AX7: 0 | AY7: 0 | AZ7: 0 | BA7: 0 | BB7: 0.3963
A8: Qatar | B8: 0.0996 | C8: 0.3612 | D8: 0.1709 | E8: 0.3671 | F8: 0.1693 | G8: 0.2502 | H8: 0 | I8: 0.1822 | J8: 0.1556 | K8: 0.201 | L8: 0.3425 | M8: 0.1981 | N8: 0.1512 | O8: 0.2138 | P8: 0.2409 | Q8: 0.06 | R8: 0.0308 | S8: 0.5906 | T8: 0.2051 | U8: 0.1496 | V8: 0.0426 | W8: 0.0596 | X8: 0.2935 | Y8: 0.4094 | Z8: 0.0948 | AA8: 0.1533 | AB8: 0.1809 | AC8: 0.4104 | AD8: 0.0245 | AE8: 0.3219 | AF8: 0.4348 | AG8: 0.1373 | AH8: 0.0242 | AI8: 0.0692 | AJ8: 0.3243 | AK8: 0.1277 | AL8: 0.0182 | AM8: 0.1413 | AN8: 0.1066 | AO8: 0.2704 | AP8: 0.063 | AQ8: 0.1629 | AR8: 0.2734 | AS8: 0.1016 | AT8: 0.0632 | AU8: 0.0854 | AV8: 0.5532 | AW8: 0.1916 | AX8: 0 | AY8: 0 | AZ8: 0 | BA8: 0 | BB8: 0.1717
A9: Switzerland | B9: 0.3399 | C9: 0.7078 | D9: 0.4875 | E9: 0.7073 | F9: 0.4726 | G9: 0.5838 | H9: 0.8178 | I9: 0 | J9: 0.4433 | K9: 0.523 | L9: 0.6894 | M9: 0.5224 | N9: 0.4485 | O9: 0.5372 | P9: 0.5749 | Q9: 0.254 | R9: 0.1685 | S9: 0.866 | T9: 0.5306 | U9: 0.4494 | V9: 0.2181 | W9: 0.2425 | X9: 0.6276 | Y9: 0.7466 | Z9: 0.3358 | AA9: 0.4472 | AB9: 0.5024 | AC9: 0.7536 | AD9: 0.1394 | AE9: 0.6708 | AF9: 0.7715 | AG9: 0.4227 | AH9: 0.1331 | AI9: 0.2632 | AJ9: 0.6744 | AK9: 0.4025 | AL9: 0.1129 | AM9: 0.4334 | AN9: 0.3566 | AO9: 0.6088 | AP9: 0.2643 | AQ9: 0.474 | AR9: 0.6252 | AS9: 0.3459 | AT9: 0.25 | AU9: 0.3251 | AV9: 0.8468 | AW9: 0.5189 | AX9: 0 | AY9: 0 | AZ9: 0 | BA9: 0 | BB9: 0.4758
A10: Brazil | B10: 0.378 | C10: 0.7411 | D10: 0.5402 | E10: 0.7557 | F10: 0.5278 | G10: 0.6484 | H10: 0.8444 | I10: 0.5567 | J10: 0 | K10: 0.5718 | L10: 0.7352 | M10: 0.5789 | N10: 0.4911 | O10: 0.5926 | P10: 0.6334 | Q10: 0.3043 | R10: 0.1986 | S10: 0.8916 | T10: 0.578 | U10: 0.4983 | V10: 0.2675 | W10: 0.2815 | X10: 0.6957 | Y10: 0.7931 | Z10: 0.3875 | AA10: 0.5015 | AB10: 0.5464 | AC10: 0.7897 | AD10: 0.1765 | AE10: 0.7152 | AF10: 0.806 | AG10: 0.4735 | AH10: 0.1636 | AI10: 0.3186 | AJ10: 0.7154 | AK10: 0.4656 | AL10: 0.1421 | AM10: 0.4823 | AN10: 0.4096 | AO10: 0.6617 | AP10: 0.3178 | AQ10: 0.5331 | AR10: 0.6781 | AS10: 0.3912 | AT10: 0.3024 | AU10: 0.3546 | AV10: 0.8735 | AW10: 0.5628 | AX10: 0 | AY10: 0 | AZ10: 0 | BA10: 0 | BB10: 0.5417
A11: Morocco | B11: 0.3149 | C11: 0.697 | D11: 0.4588 | E11: 0.6894 | F11: 0.4517 | G11: 0.5752 | H11: 0.799 | I11: 0.477 | J11: 0.4282 | K11: 0 | L11: 0.6589 | M11: 0.504 | N11: 0.434 | O11: 0.5138 | P11: 0.5541 | Q11: 0.2455 | R11: 0.1536 | S11: 0.8496 | T11: 0.5043 | U11: 0.4207 | V11: 0.2109 | W11: 0.2227 | X11: 0.6137 | Y11: 0.7324 | Z11: 0.3182 | AA11: 0.4304 | AB11: 0.4723 | AC11: 0.743 | AD11: 0.129 | AE11: 0.6457 | AF11: 0.7604 | AG11: 0.3999 | AH11: 0.1182 | AI11: 0.2519 | AJ11: 0.6554 | AK11: 0.3731 | AL11: 0.1144 | AM11: 0.4022 | AN11: 0.325 | AO11: 0.5752 | AP11: 0.2454 | AQ11: 0.4703 | AR11: 0.6099 | AS11: 0.3159 | AT11: 0.234 | AU11: 0.3038 | AV11: 0.8284 | AW11: 0.4941 | AX11: 0 | AY11: 0 | AZ11: 0 | BA11: 0 | BB11: 0.4563
A12: Haiti | B12: 0.1839 | C12: 0.5213 | D12: 0.2901 | E12: 0.5258 | F12: 0.2867 | G12: 0.4032 | H12: 0.6575 | I12: 0.3106 | J12: 0.2648 | K12: 0.3411 | L12: 0 | M12: 0.3342 | N12: 0.2609 | O12: 0.3515 | P12: 0.3904 | Q12: 0.1306 | R12: 0.0687 | S12: 0.7393 | T12: 0.3405 | U12: 0.2632 | V12: 0.1017 | W12: 0.1124 | X12: 0.4598 | Y12: 0.5668 | Z12: 0.1798 | AA12: 0.265 | AB12: 0.3099 | AC12: 0.5681 | AD12: 0.0534 | AE12: 0.4767 | AF12: 0.5977 | AG12: 0.2442 | AH12: 0.0505 | AI12: 0.1378 | AJ12: 0.4823 | AK12: 0.2358 | AL12: 0.0472 | AM12: 0.2597 | AN12: 0.1861 | AO12: 0.4227 | AP12: 0.1375 | AQ12: 0.2858 | AR12: 0.4425 | AS12: 0.1883 | AT12: 0.12 | AU12: 0.169 | AV12: 0.6994 | AW12: 0.3232 | AX12: 0 | AY12: 0 | AZ12: 0 | BA12: 0 | BB12: 0.2851
A13: Scotland | B13: 0.312 | C13: 0.6791 | D13: 0.4526 | E13: 0.6881 | F13: 0.4594 | G13: 0.5649 | H13: 0.8019 | I13: 0.4776 | J13: 0.4211 | K13: 0.496 | L13: 0.6658 | M13: 0 | N13: 0.426 | O13: 0.5132 | P13: 0.5556 | Q13: 0.2389 | R13: 0.1513 | S13: 0.8578 | T13: 0.5057 | U13: 0.4277 | V13: 0.2073 | W13: 0.2289 | X13: 0.6125 | Y13: 0.7219 | Z13: 0.3266 | AA13: 0.4308 | AB13: 0.473 | AC13: 0.7302 | AD13: 0.1268 | AE13: 0.6435 | AF13: 0.7504 | AG13: 0.3947 | AH13: 0.1107 | AI13: 0.2529 | AJ13: 0.6627 | AK13: 0.3863 | AL13: 0.1054 | AM13: 0.399 | AN13: 0.3265 | AO13: 0.594 | AP13: 0.2511 | AQ13: 0.4516 | AR13: 0.6127 | AS13: 0.3159 | AT13: 0.2312 | AU13: 0.296 | AV13: 0.8259 | AW13: 0.502 | AX13: 0 | AY13: 0 | AZ13: 0 | BA13: 0 | BB13: 0.4614
... A49: Panama | B49: 0.323 | C49: 0.6869 | D49: 0.4705 | E49: 0.6886 | F49: 0.4668 | G49: 0.5799 | H49: 0.8084 | I49: 0.4811 | J49: 0.4372 | K49: 0.5059 | L49: 0.6768 | M49: 0.498 | N49: 0.4273 | O49: 0.5232 | P49: 0.5628 | Q49: 0.2547 | R49: 0.1477 | S49: 0.8571 | T49: 0.5188 | U49: 0.4273 | V49: 0.2075 | W49: 0.2203 | X49: 0.6229 | Y49: 0.7371 | Z49: 0.3277 | AA49: 0.4275 | AB49: 0.483 | AC49: 0.7351 | AD49: 0.1263 | AE49: 0.6599 | AF49: 0.7582 | AG49: 0.4112 | AH49: 0.1203 | AI49: 0.2565 | AJ49: 0.6582 | AK49: 0.3959 | AL49: 0.1063 | AM49: 0.4155 | AN49: 0.3363 | AO49: 0.5923 | AP49: 0.2574 | AQ49: 0.4634 | AR49: 0.6242 | AS49: 0.3214 | AT49: 0.2424 | AU49: 0.3015 | AV49: 0.8307 | AW49: 0 | AX49: 0 | AY49: 0 | AZ49: 0 | BA49: 0 | BB49: 0.4543
B50: 1 | C50: 1 | D50: 1 | E50: 1 | F50: 1 | G50: 1 | H50: 1 | I50: 1 | J50: 1 | K50: 1 | L50: 1 | M50: 1 | N50: 1 | O50: 1 | P50: 1 | Q50: 1 | R50: 1 | S50: 1 | T50: 1 | U50: 1 | V50: 1 | W50: 1 | X50: 1 | Y50: 1 | Z50: 1 | AA50: 1 | AB50: 1 | AC50: 1 | AD50: 1 | AE50: 1 | AF50: 1 | AG50: 1 | AH50: 1 | AI50: 1 | AJ50: 1 | AK50: 1 | AL50: 1 | AM50: 1 | AN50: 1 | AO50: 1 | AP50: 1 | AQ50: 1 | AR50: 1 | AS50: 1 | AT50: 1 | AU50: 1 | AV50: 1 | AW50: 1 | AX50: 0 | AY50: 0 | AZ50: 0 | BA50: 0 | BB50: 0
B51: 1 | C51: 1 | D51: 1 | E51: 1 | F51: 1 | G51: 1 | H51: 1 | I51: 1 | J51: 1 | K51: 1 | L51: 1 | M51: 1 | N51: 1 | O51: 1 | P51: 1 | Q51: 1 | R51: 1 | S51: 1 | T51: 1 | U51: 1 | V51: 1 | W51: 1 | X51: 1 | Y51: 1 | Z51: 1 | AA51: 1 | AB51: 1 | AC51: 1 | AD51: 1 | AE51: 1 | AF51: 1 | AG51: 1 | AH51: 1 | AI51: 1 | AJ51: 1 | AK51: 1 | AL51: 1 | AM51: 1 | AN51: 1 | AO51: 1 | AP51: 1 | AQ51: 1 | AR51: 1 | AS51: 1 | AT51: 1 | AU51: 1 | AV51: 1 | AW51: 1 | AX51: 1 | AY51: 0 | AZ51: 0 | BA51: 0 | BB51: 0
B52: 1 | C52: 1 | D52: 1 | E52: 1 | F52: 1 | G52: 1 | H52: 1 | I52: 1 | J52: 1 | K52: 1 | L52: 1 | M52: 1 | N52: 1 | O52: 1 | P52: 1 | Q52: 1 | R52: 1 | S52: 1 | T52: 1 | U52: 1 | V52: 1 | W52: 1 | X52: 1 | Y52: 1 | Z52: 1 | AA52: 1 | AB52: 1 | AC52: 1 | AD52: 1 | AE52: 1 | AF52: 1 | AG52: 1 | AH52: 1 | AI52: 1 | AJ52: 1 | AK52: 1 | AL52: 1 | AM52: 1 | AN52: 1 | AO52: 1 | AP52: 1 | AQ52: 1 | AR52: 1 | AS52: 1 | AT52: 1 | AU52: 1 | AV52: 1 | AW52: 1 | AX52: 1 | AY52: 1 | AZ52: 0 | BA52: 0 | BB52: 0
B53: 1 | C53: 1 | D53: 1 | E53: 1 | F53: 1 | G53: 1 | H53: 1 | I53: 1 | J53: 1 | K53: 1 | L53: 1 | M53: 1 | N53: 1 | O53: 1 | P53: 1 | Q53: 1 | R53: 1 | S53: 1 | T53: 1 | U53: 1 | V53: 1 | W53: 1 | X53: 1 | Y53: 1 | Z53: 1 | AA53: 1 | AB53: 1 | AC53: 1 | AD53: 1 | AE53: 1 | AF53: 1 | AG53: 1 | AH53: 1 | AI53: 1 | AJ53: 1 | AK53: 1 | AL53: 1 | AM53: 1 | AN53: 1 | AO53: 1 | AP53: 1 | AQ53: 1 | AR53: 1 | AS53: 1 | AT53: 1 | AU53: 1 | AV53: 1 | AW53: 1 | AX53: 1 | AY53: 1 | AZ53: 1 | BA53: 0 | BB53: 0
A54: Média | B54: 0.3564 | C54: 0.7288 | D54: 0.5126 | E54: 0.7219 | F54: 0.4918 | G54: 0.6037 | H54: 0.8283 | I54: 0.5242 | J54: 0.4583 | K54: 0.5437 | L54: 0.7149 | M54: 0.5386 | N54: 0.4583 | O54: 0.5583 | P54: 0.5915 | Q54: 0.2817 | R54: 0.1783 | S54: 0.8774 | T54: 0.5521 | U54: 0.4665 | V54: 0.2458 | W54: 0.2528 | X54: 0.6698 | Y54: 0.7657 | Z54: 0.3541 | AA54: 0.4687 | AB54: 0.5186 | AC54: 0.7682 | AD54: 0.1459 | AE54: 0.6838 | AF54: 0.7896 | AG54: 0.4378 | AH54: 0.1406 | AI54: 0.2916 | AJ54: 0.6961 | AK54: 0.4216 | AL54: 0.1254 | AM54: 0.4476 | AN54: 0.3673 | AO54: 0.6283 | AP54: 0.2929 | AQ54: 0.4959 | AR54: 0.6521 | AS54: 0.3586 | AT54: 0.269 | AU54: 0.3378 | AV54: 0.8519 | AW54: 0.5457 | AX54: 1 | AY54: 1 | AZ54: 1 | BA54: 1 | BB54: 0

Sheet Chaveamento
A1: Rodada | B1: Time A | C1: Time B | D1: Coluna1 | E1: Coluna2 | F1: Coluna3 | G1: Coluna4 | H1: Coluna5
A2: Match 1 | B2: Mexico | C2: South Africa
A3: Match 2 | B3: Korea Republic | C3: Czechia
A4: Match 3 | B4: Canada | C4: Bosnia and Herzegovina
A5: Match 4 | B5: USA | C5: Paraguay
A6: Match 5 | B6: Haiti | C6: Scotland
A7: Match 6 | B7: Australia | C7: Türkiye
A8: Match 7 | B8: Brazil | C8: Morocco
A9: Match 8 | B9: Qatar | C9: Switzerland
A10: Match 9 | B10: Côte d'Ivoire | C10: Ecuador
A11: Match 10 | B11: Germany | C11: Curaçao
A12: Match 11 | B12: Netherlands | C12: Japan
A13: Match 12 | B13: Sweden | C13: Tunisia
... A105: Match 104 | B105: Winner match 101 | C105: Winner match 102

Sheet Planilha1
B1: {=TRANSPOSE(A2:A49)} -> Mexico | C1: South Africa | D1: South Korea | E1: Czechia | F1: Canada | G1: Bosnia-Herzegovina | H1: Qatar | I1: Switzerland | J1: Brazil | K1: Morocco | L1: Haiti | M1: Scotland | N1: USA | O1: Paraguay | P1: Australia | Q1: Turkiye | R1: Germany | S1: Curaçao | T1: Côte d'Ivoire | U1: Ecuador | V1: Netherlands | W1: Japan | X1: Sweden | Y1: Tunisia | Z1: Belgium | AA1: Egypt | AB1: IR Iran | AC1: New Zealand | AD1: Spain | AE1: Cabo Verde | AF1: Saudi Arabia | AG1: Uruguay | AH1: France | AI1: Senegal | AJ1: Iraq | AK1: Norway | AL1: Argentina | AM1: Algeria | AN1: Austria | AO1: Jordan | AP1: Portugal | AQ1: Congo | AR1: Uzbekistan | AS1: Colombia | AT1: England | AU1: Croatia | AV1: Ghana | AW1: Panama
A2: Mexico
A3: South Africa
A4: South Korea
A5: Czechia
A6: Canada
A7: Bosnia-Herzegovina
A8: Qatar
A9: Switzerland
A10: Brazil
A11: Morocco
A12: Haiti
A13: Scotland
... A49: Panama

Sheet Treinadores
A1: Treinador | B1: Longevidade | C1: Copa do Mundo - Treinadores | Transfermarkt
A2: Amir Ghalenoei | B2: 03 anos 28 dias
A3: Bubista | B3: 06 anos 02 meses 11 dias
A4: Carlo Ancelotti | B4: 10 meses 14 dias
A5: Darren Bazeley | B5: 02 anos 09 meses 09 dias
A6: Didier Deschamps | B6: 13 anos 09 meses 01 dias
A7: Emerse Faé | B7: 02 anos 01 meses 20 dias
A8: Fabio Cannavaro | B8: 06 meses 03 dias
A9: Fred Rutten | B9: 01 meses 17 dias
A10: Graham Arnold | B10: 11 meses 00 dias
A11: Graham Potter | B11: 05 meses 20 dias
A12: Gustavo Alfaro | B12: 01 anos 07 meses 24 dias
A13: Hajime Moriyasu | B13: 07 anos 08 meses 08 dias
... A48: Zlatko Dalic | B48: 08 anos 06 meses 02 dias

Sheet Jogadores (1)
A1: Column1 | B1: Rank | C1: Name | D1: OVR | E1: Position | F1: Nation
A2: 0 | B2: 1 | C2: Kylian Mbappé | D2: 91 | E2: ST | F2: France | H2: GK | I2: Goleiro
A3: 1 | B3: 2 | C3: Rodri | D3: 91 | E3: CDM | F3: Spain | H3: CB | I3: Zagueiro
A4: 2 | B4: 4 | C4: Erling Haaland | D4: 91 | E4: ST | F4: Norway | H4: RB | I4: Lateral Direito
A5: 3 | B5: 5 | C5: Jude Bellingham | D5: 90 | E5: CAM | F5: England | H5: LB | I5: Lateral Esquerdo
A6: 4 | B6: 7 | C6: Vini Jr. | D6: 90 | E6: LW | F6: Brazil | H6: CDM | I6: Volante
A7: 5 | B7: 9 | C7: Kevin De Bruyne | D7: 90 | E7: CM | F7: Belgium | H7: CM | I7: Meio campo
A8: 6 | B8: 11 | C8: Harry Kane | D8: 90 | E8: ST | F8: England | H8: CAM | I8: Armador
A9: 7 | B9: 12 | C9: Martin Ødegaard | D9: 89 | E9: CM | F9: Norway | H9: RM | I9: Meia direita
A10: 8 | B10: 13 | C10: Gianluigi Donnarumma | D10: 89 | E10: GK | F10: Italy | H10: LM | I10: Meia esquerda
A11: 9 | B11: 15 | C11: Alisson | D11: 89 | E11: GK | F11: Brazil | H11: ST | I11: Centroavante
A12: 10 | B12: 16 | C12: Thibaut Courtois | D12: 89 | E12: GK | F12: Belgium | H12: CF | I12: Atacante
A13: 11 | B13: 18 | C13: Lautaro Martínez | D13: 89 | E13: ST | F13: Argentina | H13: RW | I13: Ponta direita
A14: 12 | B14: 20 | C14: Virgil van Dijk | D14: 89 | E14: CB | F14: Holland | H14: LW | I14: Ponta esquerda
A15: 13 | B15: 21 | C15: Marc-André ter Stegen | D15: 89 | E15: GK | F15: Germany
A16: 14 | B16: 22 | C16: Mohamed Salah | D16: 89 | E16: RW | F16: Egypt
A17: 15 | B17: 23 | C17: Phil Foden | D17: 88 | E17: RW | F17: England
A18: 16 | B18: 25 | C18: Lionel Messi | D18: 88 | E18: RW | F18: Argentina
A19: 17 | B19: 28 | C19: Antoine Griezmann | D19: 88 | E19: ST | F19: France
A20: 18 | B20: 29 | C20: Rúben Dias | D20: 88 | E20: CB | F20: Portugal
A21: 19 | B21: 30 | C21: Robert Lewandowski | D21: 88 | E21: ST | F21: Poland
A22: 20 | B22: 32 | C22: Federico Valverde | D22: 88 | E22: CM | F22: Uruguay
A23: 21 | B23: 33 | C23: Ederson | D23: 88 | E23: GK | F23: Brazil
A24: 22 | B24: 34 | C24: Bernardo Silva | D24: 88 | E24: CM | F24: Portugal
A25: 23 | B25: 38 | C25: Jan Oblak | D25: 88 | E25: GK | F25: Slovenia
A26: 24 | B26: 40 | C26: Antonio Rüdiger | D26: 88 | E26: CB | F26: Germany
... A16162: 16160 | B16162: 17717 | C16162: Wu Yuhang | D16162: 47 | E16162: CDM | F16162: China PR

Sheet Jogadores (2)
A1: rank | B1: Name | C1: overallRating | D1: position | E1: nationality
A2: 1 | B2: Mohamed Salah | C2: 91 | D2: RM | E2: Egypt
A3: 3 | B3: Kylian Mbappé | C3: 91 | D3: ST | E3: France
A4: 5 | B4: Ousmane Dembélé | C4: 90 | D4: ST | E4: France
A5: 6 | B5: Rodrigo Hernández Cascante | C5: 90 | D5: CDM | E5: Spain
A6: 8 | B6: Virgil van Dijk | C6: 90 | D6: CB | E6: Holland
A7: 9 | B7: Jude Bellingham | C7: 90 | D7: CAM | E7: England
A8: 10 | B8: Erling Haaland | C8: 90 | D8: ST | E8: Norway
A9: 11 | B9: Raphael Dias Belloli | C9: 89 | D9: LM | E9: Brazil
A10: 12 | B10: Achraf Hakimi | C10: 89 | D10: RB | E10: Morocco
A11: 14 | B11: Lamine Yamal Nasraoui Ebana | C11: 89 | D11: RM | E11: Spain
A12: 15 | B12: Vítor Machado Ferreira | C12: 89 | D12: CM | E12: Portugal
A13: 18 | B13: Gianluigi Donnarumma | C13: 89 | D13: GK | E13: Italy
... A16229: 17873 | B16229: Jiaqiang Lyu | C16229: 47 | D16229: CB | E16229: China PR

Sheet Grupo A
A2: Mexico | C2: =Seleções!B3 -> South Africa | E2: =Seleções!B4 -> South Korea | G2: Czechia
A3: Guillermo Ochoa | B3: 74 | C3: Ricardo Goss | D3: 61 | E3: Kim Seung-Gyu | F3: 72 | G3: ='Jogadores (2)'!B3141 -> Lukas Hornicek | H3: =_xlfn.XLOOKUP(G3,'Jogadores (2)'!B:B,'Jogadores (2)'!C:C,0) -> 72
A4: Carlos Acevedo | B4: 74 | C4: Ronwen Williams | D4: 73 | E4: Jo Hyeon-Woo | F4: ='Jogadores (2)'!C7926 -> 66 | G4: ='Jogadores (2)'!B3689 -> Karel Spáčil | H4: =_xlfn.XLOOKUP(G4,'Jogadores (2)'!B:B,'Jogadores (2)'!C:C,0) -> 71
A5: Raúl Rangel | B5: 76 | C5: Renaldo Leaner | D5: 72 | E5: Song Bum-Keun | F5: ='Jogadores (2)'!C1018 -> 77 | G5: ='Jogadores (2)'!B2585 -> Jiří Pavlenka | H5: =_xlfn.XLOOKUP(G5,'Jogadores (2)'!B:B,'Jogadores (2)'!C:C,0) -> 73
A6: Jesús Gallardo | B6: 77 | C6: Aubrey Modiba | D6: 71 | E6: Kim Min-Jae | F6: ='Jogadores (2)'!C14017 -> 59 | G6: ='Jogadores (2)'!B2337 -> Lukáš Sadílek | H6: =_xlfn.XLOOKUP(G6,'Jogadores (2)'!B:B,'Jogadores (2)'!C:C,0) -> 73
A7: Jorge Sánchez | B7: 73 | C7: Nkosinathi Sibisi | D7: 69 | E7: Kim Ju-Sung | F7: 58 | G7: ='Jogadores (2)'!B12163 -> Lukáš Ambros | H7: =_xlfn.XLOOKUP(G7,'Jogadores (2)'!B:B,'Jogadores (2)'!C:C,0) -> 62
A8: César Montes | B8: 75 | C8: Khuliso Mudau | D8: 70 | E8: Kim Moon-Hwan | F8: ='Jogadores (2)'!C14576 -> 58 | G8: ='Jogadores (2)'!B2132 -> David Zima | H8: =_xlfn.XLOOKUP(G8,'Jogadores (2)'!B:B,'Jogadores (2)'!C:C,0) -> 74
A9: Jesús Ângulo | B9: 74 | C9: Ime Okon | D9: 67 | E9: Kim Tae-Hyeon | F9: ='Jogadores (2)'!C16100 -> 50 | G9: ='Jogadores (2)'!B6571 -> Christophe Kabongo | H9: =_xlfn.XLOOKUP(G9,'Jogadores (2)'!B:B,'Jogadores (2)'!C:C,0) -> 68
A10: Johan Vásquez | B10: 75 | C10: Tholo Matuludi | D10: 65 | E10: Lee Tae-Seok | F10: 69 | G10: ='Jogadores (2)'!B3456 -> Michal Sáček | H10: =_xlfn.XLOOKUP(G10,'Jogadores (2)'!B:B,'Jogadores (2)'!C:C,0) -> 71
A11: Richard Ledezma | B11: 73 | C11: Samukelo Kabini | D11: 63 | E11: Han-Beom Lee | F11: 69 | G11: ='Jogadores (2)'!B5954 -> Matěj Valenta | H11: =_xlfn.XLOOKUP(G11,'Jogadores (2)'!B:B,'Jogadores (2)'!C:C,0) -> 68
A12: Israel Reyes | B12: 75 | C12: Khulumani Ndamane | D12: 68 | E12: Seol Young-Woo | F12: 65 | G12: ='Jogadores (2)'!B1556 -> Matěj Kovář | H12: =_xlfn.XLOOKUP(G12,'Jogadores (2)'!B:B,'Jogadores (2)'!C:C,0) -> 75
A13: Everardo López | B13: 72 | C13: Mbekezeli Mbokazi | D13: 72 | E13: Cho Yu-Min | F13: 69 | G13: ='Jogadores (2)'!B6005 -> Ondřej Karafiát | H13: 68
A14: Brian Gutiérrez | B14: 68 | C14: Themba Zwane | D14: 75 | E14: Jin-Gyu Kim | F14: 70 | G14: Vladimír Darida | H14: 71
A15: Érick Sánchez | B15: 76 | C15: Yaya Sithole | D15: 73 | E15: Lee Jae-Sung | F15: 77 | G15: ='Jogadores (2)'!B7671 -> Adam Ševínský | H15: 67
A16: Orbelín Pineda | B16: 77 | C16: Teboho Mokoena | D16: 72 | E16: Paik Seung-Ho | F16: 72 | G16: ='Jogadores (2)'!B4073 -> Patrik Vydra | H16: 70
A17: Carlos Rodríguez | B17: 75 | C17: Thalente Mbatha | D17: 71 | E17: Hong Hyun-Seok | F17: 73 | G17: ='Jogadores (2)'!B4985 -> Václav Hladký | H17: 69
A18: Erik Lira | B18: 75 | C18: Jayden Adams | D18: 70 | E18: Lee Kang-in | F18: 79 | G18: ='Jogadores (2)'!B699 -> Ladislav Krejčí | H18: 78
A19: Álvaro Fidalgo | B19: 78 | C19: Tshepang Moremi | D19: 71 | E19: Jens Castrop | F19: 70 | G19: ='Jogadores (2)'!B1604 -> Antonín Kinský | H19: 75
A20: Obed Vargas | B20: 69 | C20: Lyle Foster | D20: 72 | E20: Park Jin-Seop | F20: 71 | G20: ='Jogadores (2)'!B2496 -> Jan Kuchta | H20: 73
A21: Denzell García | B21: 57 | C21: Bongokuhle Hlongwane | D21: 71 | E21: Bae Jun-Ho | F21: 71 | G21: ='Jogadores (2)'!B4807 -> Lukáš Hejda | H21: 70
A22: Raúl Jiménez | B22: 77 | C22: Oswin Appollis | D22: 70 | E22: Kwon Hyeok-Kyu | F22: 67 | G22: Jan Kliment | H22: 73
A23: Guillermo Martínez | B23: 74 | C23: Evidence Makgopa | D23: 67 | E23: Son Heung-Min | F23: 85 | G23: ='Jogadores (2)'!B6198 -> Denis Višinský | H23: 68
A24: Roberto Alvarado | B24: 76 | C24: Thapelo Maseko | D24: 70 | E24: Hwang Hee-Chan | F24: 75 | G24: ='Jogadores (2)'!B7066 -> Ondřej Kolář | H24: 67
A25: Germán Berterame | B25: 78 | C25: Relebohile Ratomo | D25: 70 | E25: Eom Ji-Sung | F25: 71 | G25: ='Jogadores (2)'!B4219 -> Václav Jurečka | H25: 70
A26: Alexis Vega | B26: 78 | E26: Oh Hyun-Gyu | F26: 70
A27: Julián Quiñones | B27: 80 | E27: Cho Gue-Sung | F27: 70
A28: Armando González | B28: 74 | E28: Yang Hyun-Jun | F28: 71
A30: Média | B30: =AVERAGE(B3:B28) -> 74.230769 | C30: Média | D30: =AVERAGE(D3:D25) -> 69.695652 | E30: Média | F30: =AVERAGE(F3:F28) -> 69.384615 | G30: Média | H30: =AVERAGE(H3:H25) -> 70.695652

Sheet Grupo B
A2: =Seleções!B6 -> Canada | C2: Bosnia-Herzegovina | E2: =Seleções!B8 -> Qatar | G2: =Seleções!B9 -> Switzerland
A3: ='Jogadores (1)'!C2244 -> Maxime Crépeau | B3: ='Jogadores (1)'!D2244 -> 73 | C3: ='Jogadores (2)'!B1055 -> Amar Dedić | D3: ='Jogadores (2)'!C1055 -> 73 | E3: Shehab Ellethy | F3: 61 | G3: ='Jogadores (1)'!C964 -> Andi Zeqiri | H3: ='Jogadores (1)'!D964 -> 70
A4: ='Jogadores (1)'!C3888 -> Dayne St. Clair | B4: ='Jogadores (1)'!D3888 -> 71 | C4: Osman Hadzikic | D4: 62 | E4: Meshaal Barsham | F4: 69 | G4: ='Jogadores (1)'!C28 -> Aaron Keller | H4: ='Jogadores (1)'!D28 -> 65
A5: ='Jogadores (1)'!C11913 -> Owen Goodman | B5: ='Jogadores (1)'!D11913 -> 62 | C5: Martin Zlomislic | D5: 67 | E5: Salah Zakaria | F5: 64 | G5: ='Jogadores (1)'!C4360 -> Fabio Daprelà | H5: ='Jogadores (1)'!D4360 -> 67
A6: ='Jogadores (1)'!C3638 -> Richie Laryea | B6: ='Jogadores (1)'!D3638 -> 71 | C6: ='Jogadores (1)'!C539 -> Ajdin Hasić | D6: ='Jogadores (1)'!D539 -> 64 | E6: Mahmud Ibrahim Abunada | F6: 64 | G6: ='Jogadores (1)'!C990 -> Andrin Hunziker | H6: ='Jogadores (1)'!D990 -> 57
A7: ='Jogadores (1)'!C7613 -> Joel Waterman | B7: ='Jogadores (1)'!D7613 -> 67 | C7: ='Jogadores (2)'!B5740 -> Elvis Sarić | D7: ='Jogadores (2)'!C5740 -> 71 | E7: Ró-Ró | F7: 66 | G7: ='Jogadores (1)'!C2128 -> Boris Babić | H7: ='Jogadores (1)'!D2128 -> 62
A8: ='Jogadores (1)'!C2804 -> Derek Cornelius | B8: ='Jogadores (1)'!D2804 -> 72 | C8: ='Jogadores (2)'!B7752 -> Josip Ćorluka | D8: ='Jogadores (2)'!C7752 -> 63 | E8: Lucas Mendes | F8: 68 | G8: ='Jogadores (1)'!C1123 -> Anthony Racioppi | H8: ='Jogadores (1)'!D1123 -> 71
A9: ='Jogadores (1)'!C3714 -> Kamal Miller | B9: ='Jogadores (1)'!D3714 -> 71 | C9: Stjepan Radeljic | D9: 70 | E9: Boualem Khoukhi | F9: 71 | G9: ='Jogadores (1)'!C95 -> Ahmedin Avdic | H9: ='Jogadores (1)'!D95 -> 55
A10: ='Jogadores (1)'!C12835 -> Jahkeele Marshall-Rutty | B10: ='Jogadores (1)'!D12835 -> 61 | C10: ='Jogadores (1)'!C2262 -> Belmin Dizdarević | D10: ='Jogadores (1)'!D2262 -> 61 | E10: Bassam Al Rawi | F10: 69 | G10: ='Jogadores (1)'!C2238 -> Bryan Okoh | H10: ='Jogadores (1)'!D2238 -> 65
A11: Luc Rollet | B11: 68 | C11: ='Jogadores (2)'!B4852 -> Edin Džeko | D11: ='Jogadores (2)'!C4852 -> 81 | E11: Niall Mason | F11: 64 | G11: ='Jogadores (1)'!C3071 -> Corsin Konietzke | H11: ='Jogadores (1)'!D3071 -> 59
A12: ='Jogadores (1)'!C3102 -> Jonathan Osorio | B12: ='Jogadores (1)'!D3102 -> 72 | C12: ='Jogadores (2)'!B10677 -> Milan Đurić | D12: ='Jogadores (2)'!C10677 -> 71 | E12: Eisa Palangi | F12: 62 | G12: ='Jogadores (1)'!C4028 -> Elias Maluvunu | H12: ='Jogadores (1)'!D4028 -> 60
A13: Marcelo Flores | B13: 71 | C13: Ivan Sunjic | D13: 69 | E13: Al Hashmi Al Hussain Mohi Aldin | F13: 64 | G13: ='Jogadores (1)'!C9157 -> Marco Burch | H13: ='Jogadores (1)'!D9157 -> 66
A14: ='Jogadores (1)'!C4152 -> Mathieu Choinière | B14: ='Jogadores (1)'!D4152 -> 70 | C14: ='Jogadores (1)'!C1860 -> Armin Gigović | D14: ='Jogadores (1)'!D1860 -> 67 | E14: Marwan Sharaf Salaheldin Hassan | F14: 63 | G14: ='Jogadores (1)'!C49 -> Adrian Gantenbein | H14: ='Jogadores (1)'!D49 -> 66
A15: ='Jogadores (1)'!C13590 -> Ralph Priso | B15: ='Jogadores (1)'!D13590 -> 60 | C15: ='Jogadores (2)'!B5840 -> Ermedin Demirović | D15: ='Jogadores (2)'!C5840 -> 80 | E15: Gueye Seydinaissa Laye | F15: 65 | G15: ='Jogadores (1)'!C302 -> Albian Hajdari | H15: ='Jogadores (1)'!D302 -> 67
A16: ='Jogadores (2)'!B5957 -> Nathan-Dylan Saliba | B16: ='Jogadores (2)'!C5957 -> 68 | C16: ='Jogadores (1)'!C6973 -> Imad Rondić | D16: ='Jogadores (1)'!D6973 -> 62 | E16: Karim Boudiaf | F16: 71 | G16: ='Jogadores (1)'!C1624 -> Ardon Jashari | H16: ='Jogadores (1)'!D1624 -> 73
A17: ='Jogadores (1)'!C2981 -> Ismaël Koné | B17: ='Jogadores (1)'!D2981 -> 72 | C17: Ivan Basic | D17: 65 | E17: Assim Madibo | F17: 65 | G17: ='Jogadores (1)'!C783 -> Alvyn Sanches | H17: ='Jogadores (1)'!D783 -> 67
A18: ='Jogadores (1)'!C9776 -> Ali Ahmed | B18: ='Jogadores (1)'!D9776 -> 64 | C18: ='Jogadores (2)'!B2981 -> Benjamin Tahirović | D18: ='Jogadores (2)'!C2981 -> 67 | E18: Ahmed Fathi | F18: 67 | G18: ='Jogadores (1)'!C618 -> Alexandre Jankewitz | H18: ='Jogadores (1)'!D618 -> 64
A19: ='Jogadores (2)'!B4165 -> Niko Sigur | B19: ='Jogadores (2)'!C4165 -> 70 | C19: ='Jogadores (2)'!B7434 -> Imad Rondić | D19: ='Jogadores (2)'!C7434 -> 66 | E19: Mohammed Waad | F19: 66 | G19: ='Jogadores (1)'!C1049 -> Anel Husic | H19: ='Jogadores (1)'!D1049 -> 66
A20: ='Jogadores (2)'!B4983 -> Junior Hoilett | B20: ='Jogadores (2)'!C4983 -> 69 | C20: ='Jogadores (2)'!B364 -> Adrian Barišić | D20: ='Jogadores (2)'!C364 -> 72 | E20: Moustafa Tarek Mashal | F20: 64 | G20: ='Jogadores (1)'!C1662 -> Basil Stillhart | H20: ='Jogadores (1)'!D1662 -> 67
A21: ='Jogadores (1)'!C1498 -> Cyle Larin | B21: ='Jogadores (1)'!D1498 -> 75 | C21: ='Jogadores (2)'!B2713 -> Asmir Begović | D21: ='Jogadores (2)'!C2713 -> 70 | E21: Mohamed Naceur Almanai | F21: 65 | G21: ='Jogadores (1)'!C2351 -> Carmine Chiappetta | H21: ='Jogadores (1)'!D2351 -> 56
A22: ='Jogadores (1)'!C3056 -> Liam Millar | B22: ='Jogadores (1)'!D3056 -> 72 | C22: ='Jogadores (2)'!B441 -> Ajdin Hasić | D22: ='Jogadores (2)'!C441 -> 70 | E22: Anas Abweny | F22: 62 | G22: ='Jogadores (1)'!C2028 -> Benjamin Siegrist | H22: ='Jogadores (1)'!D2028 -> 66
A23: ='Jogadores (1)'!C295 -> Jonathan David | B23: ='Jogadores (1)'!D295 -> 81 | C23: ='Jogadores (2)'!B8761 -> Jovo Lukić | D23: ='Jogadores (2)'!C8761 -> 64 | E23: Ayoub Al Oui | F23: 60 | G23: ='Jogadores (1)'!C7470 -> Junior Eyamba | H23: ='Jogadores (1)'!D7470 -> 62
A24: ='Jogadores (1)'!C1732 -> Tajon Buchanan | B24: ='Jogadores (1)'!D1732 -> 74 | C24: ='Jogadores (2)'!B12436 -> Samed Baždar | D24: ='Jogadores (2)'!C12436 -> 69 | E24: Ibrahim Mohammad Al Hassan Ibrahim Mohammad Ali | F24: 65 | G24: ='Jogadores (1)'!C6869 -> Johan Manzambi | H24: ='Jogadores (1)'!D6869 -> 58
A25: ='Jogadores (2)'!B4607 -> Tani Oluwaseyi | B25: ='Jogadores (2)'!C4607 -> 70 | C25: ='Jogadores (2)'!B6057 -> Esmir Bajraktarević | D25: ='Jogadores (2)'!C6057 -> 67 | E25: Edmílson Junior | F25: 74 | G25: ='Jogadores (1)'!C2159 -> Breel Embolo | H25: ='Jogadores (1)'!D2159 -> 77
A26: ='Jogadores (1)'!C12294 -> Jacen Russell-Rowe | B26: ='Jogadores (1)'!D12294 -> 62 | C26: ='Jogadores (2)'!B9698 -> Kerim Alajbegović | D26: ='Jogadores (2)'!C9698 -> 61 | E26: Almoez Ali | F26: 73 | G26: ='Jogadores (1)'!C11641 -> Noah Okafor | H26: ='Jogadores (1)'!D11641 -> 78
A27: ='Jogadores (2)'!B9466 -> Daniel Jebbison | B27: ='Jogadores (2)'!C9466 -> 65 | E27: Akram Afif | F27: 78 | G27: ='Jogadores (1)'!C3379 -> Dan Ndoye | H27: ='Jogadores (1)'!D3379 -> 75
A28: ='Jogadores (1)'!C14808 -> Aribim Pepple | B28: ='Jogadores (1)'!D14808 -> 57 | E28: Hassan Al-Haydos | F28: 70 | G28: ='Jogadores (2)'!B2353 -> Joël Almada Monteiro | H28: ='Jogadores (2)'!C2353 -> 73
E29: Yusuf Abdurisag | F29: 65
A30: Média | B30: =AVERAGE(B3:B28) -> 68.769231 | C30: Média | D30: =AVERAGE(D3:D28) -> 68 | E30: Mubark Shanan | F30: 67 | G30: Média | H30: =AVERAGE(H3:H28) -> 65.846154
E31: Khaled Ali Binsabaa | F31: 70
E32: Ahmed Husham Ali Alrawi | F32: 65
E33: Ahmed Al Ganehi | F33: 67
E34: Mohamed Khaled Ahmed Gamal Al Deen Gouda | F34: 62

Sheet Grupo C
A2: =Seleções!B10 -> Brazil | C2: =Seleções!B11 -> Morocco | E2: =Seleções!B12 -> Haiti | G2: =Seleções!B13 -> Scotland
A3: Ederson | B3: ='Jogadores (2)'!C1664 -> 75 | C3: Yassine Bounou | D3: 82 | E3: Johny Placide | F3: 69 | G3: Liam Kelly | H3: 67
A4: Hugo Souza | B4: 68 | C4: El Mehdi Benabid | D4: 75 | E4: Josue Duverger | F4: 65 | G4: Scott Bain | H4: 66
A5: Bento | B5: ='Jogadores (2)'!C485 -> 80 | C5: Mehdi Harrar | D5: 75 | E5: Alexandre Pierre | F5: 60 | G5: Angus Gunn | H5: 72
A6: Léo Pereira | B6: 66 | C6: Issa Diop | D6: 76 | E6: Ricardo Adé | F6: 72 | G6: Andrew Robertson | H6: 82
A7: Marquinhos | B7: ='Jogadores (2)'!C5886 -> 68 | C7: Noussair Mazraoui | D7: 80 | E7: Carlens Arcus | F7: 71 | G7: Grant Hanley | H7: 71
A8: Danilo | B8: 72 | C8: Achraf Hakimi | D8: 89 | E8: Duke Lacroix | F8: 70 | G8: John Souttar | H8: 73
A9: Douglas Santos | B9: 77 | C9: Souffian El Karouani | D9: 75 | E9: Jean-Kévin Duverne | F9: 71 | G9: Scott McKenna | H9: 75
A10: Bremer | B10: ='Jogadores (2)'!C3012 -> 72 | C10: Anass Salah-Eddine | D10: 71 | E10: Hannes Delcroix | F10: 71 | G10: Ross McCrorie | H10: 70
A11: Ibañez | B11: ='Jogadores (2)'!C9495 -> 65 | C11: Chadi Riad | D11: 72 | E11: Delentz Pierre | F11: 53 | G11: Jack Hendry | H11: 74
A12: Kaiki | B12: 54 | C12: Zakaria El Ouahdi | D12: 76 | E12: Martin Expérience | F12: 62 | G12: Kieran Tierney | H12: 77
A13: Vitor Reis | B13: ='Jogadores (2)'!C12947 -> 61 | C13: Redouane Halal | D13: 72 | E13: Wilguens Paugain | F13: 55 | G13: Anthony Ralston | H13: 71
A14: Casemiro | B14: ='Jogadores (2)'!C910 -> 77 | C14: Ismaël Baouf | D14: 72 | E14: Jean-Ricner Bellegarde | F14: 75 | G14: Dominic Hyam | H14: 71
A15: Fabinho | B15: ='Jogadores (2)'!C2091 -> 74 | C15: Abdelhamid Aït Boudlal | D15: 70 | E15: Leverton Pierre | F15: 64 | G15: Nathan Patterson | H15: 71
A16: Gabriel Sara | B16: ='Jogadores (2)'!C2589 -> 73 | C16: Brahim Díaz | D16: 82 | E16: Carl-Fred Sainte | F16: 70 | G16: Ryan Christie | H16: 79
A17: Danilo | B17: 76 | C17: Azzedine Ounahi | D17: 76 | E17: Danley Jean Jacques | F17: 70 | G17: Kenny McLean | H17: 72
A18: Andrey Santos | B18: ='Jogadores (2)'!C341 -> 81 | C18: Ismael Saibari | D18: 79 | E18: Woodensky Pierre | F18: 70 | G18: John McGinn | H18: 81
A19: Vinícius Júnior | B19: ='Jogadores (2)'!C11638 -> 63 | C19: Oussama Targhaline | D19: 76 | E19: Duckens Nazon | F19: 69 | G19: Lewis Ferguson | H19: 78
A20: Matheus Cunha | B20: ='Jogadores (2)'!C6716 -> 68 | C20: Neil El Aynaoui | D20: 77 | E20: Derrick Etienne Jr. | F20: 66 | G20: Andrew Irving | H20: 75
A21: Gabriel Martinelli | B21: ='Jogadores (2)'!C2832 -> 72 | C21: Bilal El Khannouss | D21: 76 | E21: Frantzdy Pierrot | F21: 72 | G21: Scott McTominay | H21: 85
A22: João Pedro | B22: ='Jogadores (2)'!C4052 -> 70 | C22: Mohamed Hrimat | D22: 70 | E22: Wilson Isidor | F22: 72 | G22: Billy Gilmour | H22: 74
A23: Igor Thiago | B23: ='Jogadores (2)'!C3801 -> 71 | C23: Samir El Mourabet | D23: 65 | E23: Yassine Fortune | F23: 70 | G23: Lennon Miller | H23: 71
A24: Luiz Henrique | B24: 72 | C24: Ayoub El Kaabi | D24: 80 | E24: Louicius Don Deedson | F24: 70 | G24: Findlay Curtis | H24: 63
A25: Endrick | B25: ='Jogadores (2)'!C1868 -> 74 | C25: Soufiane Rahimi | D25: 78 | E25: Josué Casimir | F25: 71 | G25: Lyndon Dykes | H25: 68
A26: Rayan | B26: 77 | C26: Amine Adli | D26: 78 | E26: Ruben Providence | F26: 66 | G26: Ché Adams | H26: 77
C27: Abde Ezzalzouli | D27: 75 | E27: Woobens Pacius | F27: 60 | G27: George Hirst | H27: 72
C28: Chemsdine Talbi | D28: 73 | G28: Tommy Conway | H28: 70
C29: Gessime Yassine | D29: 65
C30: Yassir Zabiri | D30: 66
C31: Rayane Bounida | D31: 63
A33: média | B33: =AVERAGE(B3:B26) -> 71.083333 | C33: média | D33: =AVERAGE(D3:D31) -> 74.62069 | E33: média | F33: =AVERAGE(F3:F27) -> 67.36 | G33: média | H33: =AVERAGE(H3:H28) -> 73.269231

Sheet Grupo D
A2: =Seleções!B14 -> USA | C2: =Seleções!B15 -> Paraguay | E2: =Seleções!B16 -> Australia | G2: Turkiye
A3: Matthew Freese | B3: 70 | C3: Gatito Fernández | D3: 70 | E3: Mathew Ryan | F3: 79 | G3: ='Jogadores (2)'!B675 -> Mert Günok | H3: ='Jogadores (2)'!C675 -> 78
A4: ='Jogadores (2)'!B3757 -> Patrick Schulte | B4: ='Jogadores (2)'!C3757 -> 71 | C4: Gastón Olveira | D4: 73 | E4: ='Jogadores (2)'!B4166 -> Paul Izzo | F4: ='Jogadores (2)'!C4166 -> 70 | G4: ='Jogadores (2)'!B401 -> Uğurcan Çakır | H4: ='Jogadores (2)'!C401 -> 80
A5: ='Jogadores (2)'!B5490 -> Chris Brady | B5: ='Jogadores (2)'!C5490 -> 69 | C5: ='Jogadores (2)'!B12192 -> Orlando Gill | D5: ='Jogadores (2)'!C12192 -> 62 | E5: ='Jogadores (2)'!B9300 -> Patrick Beach | F5: ='Jogadores (2)'!C9300 -> 65 | G5: ='Jogadores (2)'!B3777 -> Muhammed Şengezer | H5: ='Jogadores (2)'!C3777 -> 71
A6: ='Jogadores (2)'!B2010 -> Matt Turner | B6: ='Jogadores (2)'!C2010 -> 74 | C6: Juan Cáceres | D6: 64 | E6: Milos Degenek | F6: 68 | G6: ='Jogadores (2)'!B1612 -> Altay Bayındır | H6: ='Jogadores (2)'!C1612 -> 75
A7: ='Jogadores (2)'!B2122 -> Mark McKenzie | B7: ='Jogadores (2)'!C2122 -> 74 | C7: Gustavo Gómez | D7: 73 | E7: Jason Geria | F7: 66 | G7: ='Jogadores (2)'!B1213 -> Kaan Ayhan | H7: ='Jogadores (2)'!C1213 -> 76
A8: ='Jogadores (2)'!B3311 -> Tim Ream | B8: ='Jogadores (2)'!C3311 -> 72 | C8: ='Jogadores (2)'!B2716 -> Gustavo Velázquez | D8: ='Jogadores (2)'!C2716 -> 73 | E8: ='Jogadores (2)'!B6847 -> Aziz Behich | F8: ='Jogadores (2)'!C6847 -> 67 | G8: ='Jogadores (2)'!B470 -> Abdülkerim Bardakcı | H8: ='Jogadores (2)'!C470 -> 80
A9: ='Jogadores (2)'!B231 -> Antonee Robinson | B9: ='Jogadores (2)'!C231 -> 82 | C9: Júnior Alonso | D9: 74 | E9: ='Jogadores (2)'!B2735 -> Cameron Burgess | F9: ='Jogadores (2)'!C2735 -> 73 | G9: ='Jogadores (2)'!B509 -> Ferdi Kadıoğlu | H9: ='Jogadores (2)'!C509 -> 79
A10: ='Jogadores (2)'!B2039 -> Auston Trusty | B10: ='Jogadores (2)'!C2039 -> 74 | C10: Alan Benítez | D10: 68 | E10: ='Jogadores (2)'!B4035 -> Kye Rowles | F10: ='Jogadores (2)'!C4035 -> 71 | G10: ='Jogadores (2)'!B1883 -> Mert Müldür | H10: ='Jogadores (2)'!C1883 -> 74
A11: ='Jogadores (2)'!B8862 -> Alex Freeman | B11: ='Jogadores (2)'!C8862 -> 65 | C11: Fabián Balbuena | D11: 75 | E11: ='Jogadores (2)'!B6032 -> Fran Karačić | F11: ='Jogadores (2)'!C6032 -> 68 | G11: ='Jogadores (2)'!B1717 -> Ozan Kabak | H11: ='Jogadores (2)'!C1717 -> 75
A12: ='Jogadores (2)'!B1945 -> Joe Scally | B12: ='Jogadores (2)'!C1945 -> 74 | C12: ='Jogadores (2)'!B807 -> Omar Alderete | D12: ='Jogadores (2)'!C807 -> 78 | E12: ='Jogadores (2)'!B5396 -> Kai Trewin | F12: ='Jogadores (2)'!C5396 -> 69 | G12: ='Jogadores (2)'!B860 -> Merih Demiral | H12: ='Jogadores (2)'!C860 -> 78
A13: ='Jogadores (2)'!B1117 -> Chris Richards | B13: ='Jogadores (2)'!C1117 -> 77 | C13: ='Jogadores (2)'!B5729 -> José Canale | D13: ='Jogadores (2)'!C5729 -> 69 | E13: ='Jogadores (2)'!B4884 -> Jordan Bos | F13: ='Jogadores (2)'!C4884 -> 69 | G13: ='Jogadores (2)'!B3469 -> Mustafa Eskihellaç | H13: ='Jogadores (2)'!C3469 -> 71
A14: ='Jogadores (2)'!B1777 -> Cristian Roldan | B14: ='Jogadores (2)'!C1777 -> 74 | C14: ='Jogadores (2)'!B2652 -> Julio César Enciso | D14: ='Jogadores (2)'!C2652 -> 73 | E14: ='Jogadores (2)'!B4006 -> Alessandro Circati | F14: ='Jogadores (2)'!C4006 -> 71 | G14: ='Jogadores (2)'!B1215 -> Zeki Çelik | H14: ='Jogadores (2)'!C1215 -> 76
A15: ='Jogadores (2)'!B123 -> Christian Pulisic | B15: ='Jogadores (2)'!C123 -> 84 | C15: Lucas Romero | D15: 67 | E15: ='Jogadores (2)'!B14093 -> Lucas Herrington | F15: ='Jogadores (2)'!C14093 -> 59 | G15: ='Jogadores (2)'!B1453 -> Eren Elmalı | H15: ='Jogadores (2)'!C1453 -> 75
A16: ='Jogadores (2)'!B652 -> Weston McKennie | B16: ='Jogadores (2)'!C652 -> 78 | C16: Kaku | D16: 79 | E16: ='Jogadores (2)'!B7280 -> Awer Mabil | F16: ='Jogadores (2)'!C7280 -> 67 | G16: ='Jogadores (2)'!B3994 -> Ahmetcan Kaplan | H16: ='Jogadores (2)'!C3994 -> 71
A17: ='Jogadores (2)'!B1905 -> Brenden Aaronson | B17: ='Jogadores (2)'!C1905 -> 74 | C17: ='Jogadores (2)'!B2238 -> Diego Gómez | D17: ='Jogadores (2)'!C2238 -> 73 | E17: ='Jogadores (2)'!B7126 -> Ajdin Hrustić | F17: ='Jogadores (2)'!C7126 -> 67 | G17: ='Jogadores (2)'!B4848 -> Samet Akaydın | H17: ='Jogadores (2)'!C4848 -> 70
A18: ='Jogadores (2)'!B1640 -> Giovanni Reyna | B18: ='Jogadores (2)'!C1640 -> 75 | C18: ='Jogadores (2)'!B4265 -> Braian Ojeda | D18: ='Jogadores (2)'!C4265 -> 70 | E18: ='Jogadores (2)'!B2776 -> Riley McGree | F18: ='Jogadores (2)'!C2776 -> 72 | G18: ='Jogadores (2)'!B60 -> Hakan Çalhanoğlu | H18: ='Jogadores (2)'!C60 -> 86
A19: Johnny Cardoso | B19: 80 | C19: Mauricio | D19: 72 | E19: ='Jogadores (2)'!B4071 -> Aiden O'Neill | F19: ='Jogadores (2)'!C4071 -> 70 | G19: ='Jogadores (2)'!B702 -> İrfan Can Kahveci | H19: ='Jogadores (2)'!C702 -> 78
A20: ='Jogadores (2)'!B2397 -> Aidan Morris | B20: ='Jogadores (2)'!C2397 -> 73 | C20: ='Jogadores (2)'!B2424 -> Matías Galarza | D20: ='Jogadores (2)'!C2424 -> 73 | E20: ='Jogadores (2)'!B4929 -> Connor Metcalfe | F20: ='Jogadores (2)'!C4929 -> 69 | G20: ='Jogadores (2)'!B1455 -> Salih Özcan | H20: ='Jogadores (2)'!C1455 -> 75
A21: ='Jogadores (2)'!B6896 -> Sebastian Berhalter | B21: ='Jogadores (2)'!C6896 -> 67 | C21: Damián Bobadilla | D21: 65 | E21: ='Jogadores (2)'!B5912 -> Alex Robertson | F21: ='Jogadores (2)'!C5912 -> 68 | G21: ='Jogadores (2)'!B1367 -> Atakan Karazor | H21: ='Jogadores (2)'!C1367 -> 76
A22: ='Jogadores (2)'!B209 -> Malik Tillman | B22: ='Jogadores (2)'!C209 -> 82 | C22: ='Jogadores (2)'!B1169 -> Miguel Almirón | D22: ='Jogadores (2)'!C1169 -> 76 | E22: ='Jogadores (2)'!B8006 -> Patrick Yazbek | F22: ='Jogadores (2)'!C8006 -> 66 | G22: ='Jogadores (2)'!B204 -> Orkun Kökçü | H22: ='Jogadores (2)'!C204 -> 82
A23: ='Jogadores (2)'!B1542 -> Tanner Tessmann | B23: ='Jogadores (2)'!C1542 -> 75 | C23: Gustavo Caballero | D23: 67 | E23: Paul Okon | F23: 60 | G23: ='Jogadores (2)'!B947 -> İsmail Yüksek | H23: ='Jogadores (2)'!C947 -> 77
A24: ='Jogadores (2)'!B7745 -> Patrick Agyemang | B24: ='Jogadores (2)'!C7745 -> 67 | C24: ='Jogadores (2)'!B1335 -> Antonio Sanabria | D24: ='Jogadores (2)'!C1335 -> 76 | E24: ='Jogadores (2)'!B3549 -> Martin Boyle | F24: ='Jogadores (2)'!C3549 -> 71 | G24: ='Jogadores (2)'!B354 -> Arda Güler | H24: ='Jogadores (2)'!C354 -> 81
A25: ='Jogadores (2)'!B876 -> Timothy Weah | B25: ='Jogadores (2)'!C876 -> 77 | C25: ='Jogadores (2)'!B1569 -> Gabriel Ávalos | D25: ='Jogadores (2)'!C1569 -> 75 | E25: ='Jogadores (2)'!B10883 -> Jacob Italiano | F25: ='Jogadores (2)'!C10883 -> 63 | G25: ='Jogadores (2)'!B764 -> Yunus Akgün | H25: ='Jogadores (2)'!C764 -> 78
A26: ='Jogadores (2)'!B1095 -> Folarin Balogun | B26: ='Jogadores (2)'!C1095 -> 77 | C26: ='Jogadores (2)'!B1746 -> Alex Arce | D26: ='Jogadores (2)'!C1746 -> 75 | E26: ='Jogadores (2)'!B9137 -> Nishan Velupillay | F26: ='Jogadores (2)'!C9137 -> 65 | G26: ='Jogadores (2)'!B462 -> Kerem Aktürkoğlu | H26: ='Jogadores (2)'!C462 -> 80
A27: ='Jogadores (2)'!B1298 -> Ricardo Pepi | B27: ='Jogadores (2)'!C1298 -> 76 | C27: Ramón Sosa | D27: 75 | E27: Deni Juric | F27: 65 | G27: ='Jogadores (2)'!B367 -> Barış Alper Yılmaz | H27: ='Jogadores (2)'!C367 -> 80
A28: ='Jogadores (2)'!B6935 -> Max Arfsten | B28: ='Jogadores (2)'!C6935 -> 67 | C28: ='Jogadores (2)'!B14248 -> Alexandro Maidana | D28: ='Jogadores (2)'!C14248 -> 58 | E28: ='Jogadores (2)'!B6833 -> Nestory Irankunda | F28: ='Jogadores (2)'!C6833 -> 67 | G28: ='Jogadores (2)'!B940 -> Oğuz Aydın | H28: ='Jogadores (2)'!C940 -> 77
E29: Ante Suto | F29: 65 | G29: ='Jogadores (2)'!B4458 -> Semih Kılıçsoy | H29: ='Jogadores (2)'!C4458 -> 70
G30: ='Jogadores (2)'!B8541 -> Deniz Gül | H30: ='Jogadores (2)'!C8541 -> 66
G31: ='Jogadores (2)'!B597 -> Kenan Yıldız | H31: ='Jogadores (2)'!C597 -> 79
A33: média | B33: =AVERAGE(B3:B28) -> 74.153846 | C33: média | D33: =AVERAGE(D3:D28) -> 71.269231 | E33: média | F33: =AVERAGE(F3:F29) -> 67.777778 | G33: média | H33: =AVERAGE(H3:H31) -> 76.344828

Sheet Grupo E
A2: =Seleções!B18 -> Germany | C2: =Seleções!B19 -> Curaçao | E2: =Seleções!B20 -> Côte d'Ivoire | G2: =Seleções!B21 -> Ecuador
A3: ='Jogadores (2)'!B166 -> Oliver Baumann | B3: ='Jogadores (2)'!C166 -> 83 | C3: Eloy Room | D3: 67 | E3: ='Jogadores (2)'!B1515 -> Alban Lafont | F3: ='Jogadores (2)'!C1515 -> 75 | G3: ='Jogadores (2)'!B4672 -> Gonzalo Valle | H3: ='Jogadores (2)'!C4672 -> 70
A4: ='Jogadores (2)'!B309 -> Alexander Nübel | B4: ='Jogadores (2)'!C309 -> 81 | C4: Trevor Doornbusch | D4: 62 | E4: ='Jogadores (2)'!B1252 -> Yahia Fofana | F4: ='Jogadores (2)'!C1252 -> 76 | G4: ='Jogadores (2)'!B2022 -> Hernán Galíndez | H4: ='Jogadores (2)'!C2022 -> 74
A5: ='Jogadores (2)'!B905 -> Finn Dahmen | B5: ='Jogadores (2)'!C905 -> 77 | C5: Tyrick Bodak | D5: 60 | E5: ='Jogadores (2)'!B6434 -> Mohamed Koné | F5: ='Jogadores (2)'!C6434 -> 68 | G5: David Cabezas | H5: 72
A6: ='Jogadores (2)'!B1973 -> Jonas Urbig | B6: ='Jogadores (2)'!C1973 -> 74 | C6: Leandro Bacuna | D6: 67 | E6: ='Jogadores (2)'!B342 -> Evan Ndicka | F6: ='Jogadores (2)'!C342 -> 81 | G6: Moisés Ramírez | H6: 70
A7: ='Jogadores (2)'!B1049 -> Nathaniel Brown | B7: ='Jogadores (2)'!C1049 -> 77 | C7: Joshua Brenet | D7: 70 | E7: ='Jogadores (2)'!B2894 -> Ghislain Konan | F7: ='Jogadores (2)'!C2894 -> 72 | G7: Cristian Ramírez | H7: 72
A8: ='Jogadores (2)'!B52 -> Antonio Rüdiger | B8: ='Jogadores (2)'!C52 -> 86 | C8: Riechedly Bazoer | D8: 72 | E8: ='Jogadores (2)'!B476 -> Odilon Kossounou | F8: ='Jogadores (2)'!C476 -> 80 | G8: ='Jogadores (2)'!B548 -> Pervis Estupiñán | H8: ='Jogadores (2)'!C548 -> 79
A9: ='Jogadores (2)'!B43 -> Jonathan Tah | B9: ='Jogadores (2)'!C43 -> 87 | C9: ='Jogadores (2)'!B7999 -> Sherel Floranus | D9: ='Jogadores (2)'!C7999 -> 66 | E9: ='Jogadores (2)'!B400 -> Wilfried Singo | F9: ='Jogadores (2)'!C400 -> 80 | G9: Bryan Ramirez | H9: 73
A10: ='Jogadores (2)'!B264 -> Waldemar Anton | B10: ='Jogadores (2)'!C264 -> 82 | C10: Juriën Gaari | D10: 66 | E10: ='Jogadores (2)'!B604 -> Emmanuel Agbadou | F10: ='Jogadores (2)'!C604 -> 79 | G10: Félix Torres | H10: 71
A11: ='Jogadores (2)'!B215 -> David Raum | B11: ='Jogadores (2)'!C215 -> 82 | C11: Roshon van Eijma | D11: 63 | E11: ='Jogadores (2)'!B482 -> Ousmane Diomande | F11: ='Jogadores (2)'!C482 -> 80 | G11: ='Jogadores (2)'!B1414 -> Ángelo Preciado | H11: ='Jogadores (2)'!C1414 -> 75
A12: ='Jogadores (2)'!B1759 -> Josha Vagnoman | B12: ='Jogadores (2)'!C1759 -> 74 | C12: ='Jogadores (2)'!B6076 -> Shurandy Sambo | D12: ='Jogadores (2)'!C6076 -> 68 | E12: ='Jogadores (2)'!B2102 -> Clément Akpa | F12: ='Jogadores (2)'!C2102 -> 74 | G12: Jackson Porozo | H12: 71
A13: ='Jogadores (2)'!B83 -> Nico Schlotterbeck | B13: ='Jogadores (2)'!C83 -> 85 | C13: ='Jogadores (2)'!B10048 -> Ar'jany Martha | D13: ='Jogadores (2)'!C10048 -> 64 | E13: ='Jogadores (2)'!B1021 -> Guéla Doué | F13: ='Jogadores (2)'!C1021 -> 77 | G13: ='Jogadores (2)'!B58 -> Willian Pacho | H13: ='Jogadores (2)'!C58 -> 86
A14: ='Jogadores (2)'!B776 -> Malick Thiaw | B14: ='Jogadores (2)'!C776 -> 78 | C14: ='Jogadores (2)'!B11955 -> Livano Comenencia | D14: ='Jogadores (2)'!C11955 -> 62 | E14: ='Jogadores (2)'!B877 -> Seko Fofana | F14: ='Jogadores (2)'!C877 -> 77 | G14: Leonardo Realpe | H14: 69
A15: ='Jogadores (2)'!B420 -> Pascal Groß | B15: ='Jogadores (2)'!C420 -> 80 | C15: Tyrese Noslin | D15: 66 | E15: Jean Michaël Seri | F15: 71 | G15: ='Jogadores (2)'!B183 -> Piero Hincapié | H15: ='Jogadores (2)'!C183 -> 83
A16: ='Jogadores (2)'!B198 -> Leon Goretzka | B16: ='Jogadores (2)'!C198 -> 82 | C16: ='Jogadores (2)'!B4875 -> Juninho Bacuna | D16: ='Jogadores (2)'!C4875 -> 69 | E16: ='Jogadores (2)'!B369 -> Franck Yannick Kessié | F16: ='Jogadores (2)'!C369 -> 80 | G16: José Hurtado | H16: 65
A17: ='Jogadores (2)'!B15 -> Joshua Kimmich | B17: ='Jogadores (2)'!C15 -> 89 | C17: Kevin Felida | D17: 63 | E17: ='Jogadores (2)'!B981 -> Ibrahim Sangaré | F17: ='Jogadores (2)'!C981 -> 77 | G17: ='Jogadores (2)'!B4140 -> Yaimar Medina | H17: ='Jogadores (2)'!C4140 -> 70
A18: ='Jogadores (2)'!B1006 -> Chris Führich | B18: ='Jogadores (2)'!C1006 -> 77 | C18: Godfried Roemeratoe | D18: 64 | E18: ='Jogadores (2)'!B10151 -> Christ Ravynel Inao Oulaï | F18: ='Jogadores (2)'!C10151 -> 64 | G18: ='Jogadores (2)'!B1734 -> Joel Ordoñez | H18: ='Jogadores (2)'!C1734 -> 75
A19: ='Jogadores (2)'!B182 -> Angelo Stiller | B19: ='Jogadores (2)'!C182 -> 83 | C19: ='Jogadores (2)'!B3544 -> Tahith Chong | D19: ='Jogadores (2)'!C3544 -> 71 | E19: ='Jogadores (2)'!B3290 -> Parfait Guiagon | F19: ='Jogadores (2)'!C3290 -> 72 | G19: Alan Franco | H19: 68
A20: =ea_fc26_players__2[[#This Row],[Name]] -> Florian Wirtz | B20: =ea_fc26_players__2[[#This Row],[overallRating]] -> 89 | C20: ='Jogadores (2)'!B7284 -> Brandley Kuwas | D20: ='Jogadores (2)'!C7284 -> 67 | E20: ='Jogadores (2)'!B437 -> Nicolas Pépé | F20: ='Jogadores (2)'!C437 -> 80 | G20: ='Jogadores (2)'!B5861 -> Jordy Alcívar | H20: ='Jogadores (2)'!C5861 -> 68
A21: ='Jogadores (2)'!B523 -> Anton Stach | B21: ='Jogadores (2)'!C523 -> 79 | C21: Gervane Kastaneer | D21: 63 | E21: ='Jogadores (2)'!B583 -> Evann Guessand | F21: ='Jogadores (2)'!C583 -> 79 | G21: ='Jogadores (2)'!B35 -> Moisés Caicedo | H21: ='Jogadores (2)'!C35 -> 87
A22: ='Jogadores (2)'!B792 -> Kevin Schade | B22: ='Jogadores (2)'!C792 -> 78 | C22: Kenji Gorré | D22: 69 | E22: ='Jogadores (2)'!B585 -> Amad Diallo | F22: ='Jogadores (2)'!C585 -> 79 | G22: Pedro Vite | H22: 71
A23: ='Jogadores (2)'!B11559 -> Lennart Karl | B23: ='Jogadores (2)'!C11559 -> 63 | C23: Sontje Hansen | D23: 69 | E23: Elye Wahi | F23: 74 | G23: ='Jogadores (2)'!B7115 -> Denil Castillo | H23: ='Jogadores (2)'!C7115 -> 67
A24: ='Jogadores (2)'!B242 -> Serge Gnabry | B24: ='Jogadores (2)'!C242 -> 82 | C24: Jearl Margaritha | D24: 68 | E24: ='Jogadores (2)'!B1603 -> Bénie Traoré | F24: ='Jogadores (2)'!C1603 -> 75 | G24: ='Jogadores (2)'!B2591 -> Kendry Páez | H24: ='Jogadores (2)'!C2591 -> 73
A25: ='Jogadores (2)'!B237 -> Leroy Sané | B25: ='Jogadores (2)'!C237 -> 82 | C25: Jeremy Antonisse | D25: 66 | E25: ='Jogadores (2)'!B1328 -> Simon Adingra | F25: ='Jogadores (2)'!C1328 -> 76 | G25: Enner Valencia | H25: 78
A26: ='Jogadores (2)'!B246 -> Kai Havertz | B26: ='Jogadores (2)'!C246 -> 82 | E26: ='Jogadores (2)'!B11423 -> Martial Godo | F26: ='Jogadores (2)'!C11423 -> 63 | G26: ='Jogadores (2)'!B8559 -> Jordy Caicedo | H26: ='Jogadores (2)'!C8559 -> 66
A27: ='Jogadores (2)'!B465 -> Deniz Undav | B27: ='Jogadores (2)'!C465 -> 80 | E27: ='Jogadores (2)'!B4727 -> Bazoumana Touré | F27: ='Jogadores (2)'!C4727 -> 70 | G27: ='Jogadores (2)'!B3577 -> Janner Corozo | H27: ='Jogadores (2)'!C3577 -> 71
A28: ='Jogadores (2)'!B625 -> Nick Woltemade | B28: ='Jogadores (2)'!C625 -> 79 | E28: ='Jogadores (2)'!B8746 -> Yan Diomande | F28: ='Jogadores (2)'!C8746 -> 66 | G28: ='Jogadores (2)'!B4544 -> John Yeboah | H28: ='Jogadores (2)'!C4544 -> 70
G29: Gonzalo Plata | H29: 77
G30: ='Jogadores (2)'!B7496 -> Kevin Rodríguez | H30: ='Jogadores (2)'!C7496 -> 67
G31: ='Jogadores (2)'!B4580 -> John Mercado | H31: ='Jogadores (2)'!C4580 -> 70
G32: ='Jogadores (2)'!B7075 -> Anthony Valencia | H32: ='Jogadores (2)'!C7075 -> 67
G33: ='Jogadores (2)'!B4333 -> Alan Minda | H33: ='Jogadores (2)'!C4333 -> 70
G34: Jeremy Arévalo | H34: 66
G35: Elias Legendre | H35: 61
A37: média | B37: =AVERAGE(B3:B28) -> 80.423077 | C37: média | D37: =AVERAGE(D3:D25) -> 66.173913 | E37: média | F37: =AVERAGE(F3:F28) -> 74.807692 | G37: média | H37: =AVERAGE(H3:H35) -> 71.878788

Sheet Grupo F
A2: =Seleções!B22 -> Netherlands | C2: =Seleções!B23 -> Japan | E2: Sweden | G2: =Seleções!B25 -> Tunisia
A3: ='Jogadores (1)'!C515 -> Mark Flekken | B3: ='Jogadores (1)'!D515 -> 79 | C3: Keisuke Osako | D3: 68 | E3: ='Jogadores (2)'!B2961 -> Kristoffer Nordfeldt | F3: ='Jogadores (2)'!C2961 -> 72 | G3: Sabri Ben Hessen | H3: 68
A4: ='Jogadores (1)'!C1317 -> Bart Verbruggen | B4: ='Jogadores (1)'!D1317 -> 76 | C4: ='Jogadores (1)'!C3900 -> Zion Suzuki | D4: ='Jogadores (1)'!D3900 -> 71 | E4: ='Jogadores (2)'!B4384 -> Noel Törnqvist | F4: ='Jogadores (2)'!C4384 -> 70 | G4: Aymen Dahmen | H4: 68
A5: ='Jogadores (1)'!C829 -> Justin Bijlow | B5: ='Jogadores (1)'!D829 -> 77 | C5: Tomoko Hayakawa | D5: 70 | E5: ='Jogadores (2)'!B12006 -> Melker Ellborg | F5: ='Jogadores (2)'!C12006 -> 62 | G5: Noureddine Farhati | H5: 68
A6: ='Jogadores (1)'!C140 -> Stefan de Vrij | B6: ='Jogadores (1)'!D140 -> 83 | C6: ='Jogadores (1)'!C532 -> Hiroki Ito | D6: ='Jogadores (1)'!D532 -> 79 | E6: ='Jogadores (2)'!B857 -> Carl Starfelt | F6: ='Jogadores (2)'!C857 -> 78 | G6: Abdelmouhib Chamakh | H6: 70
A7: ='Jogadores (1)'!C14 -> Virgil van Dijk | B7: ='Jogadores (1)'!D14 -> 89 | C7: ='Jogadores (1)'!C3242 -> Shogo Taniguchi | D7: ='Jogadores (1)'!D3242 -> 72 | E7: ='Jogadores (1)'!C723 -> Victor Lindelöf | F7: ='Jogadores (1)'!D723 -> 78 | G7: ='Jogadores (1)'!C3315 -> Anis Slimane | H7: ='Jogadores (1)'!D3315 -> 67
A8: ='Jogadores (1)'!C96 -> Nathan Aké | B8: ='Jogadores (1)'!D96 -> 84 | C8: ='Jogadores (1)'!C4305 -> Daiki Hashioka | D8: ='Jogadores (1)'!D4305 -> 70 | E8: ='Jogadores (1)'!C1853 -> Gabriel Gudmundsson | F8: ='Jogadores (1)'!D1853 -> 74 | G8: Amine Bem Hamida | H8: 70
A9: ='Jogadores (1)'!C219 -> Denzel Dumfries | B9: ='Jogadores (1)'!D219 -> 82 | C9: ='Jogadores (1)'!C8524 -> Ayumu Seko | D9: ='Jogadores (1)'!D8524 -> 66 | E9: ='Jogadores (2)'!B928 -> Daniel Svensson | F9: ='Jogadores (2)'!C928 -> 77 | G9: ='Jogadores (1)'!C10531 -> Sebastian Tounekti | H9: 73
A10: ='Jogadores (1)'!C520 -> Lutsharel Geertruida | B10: ='Jogadores (1)'!D520 -> 79 | C10: ='Jogadores (1)'!C1020 -> Yukinari Sugawara | D10: ='Jogadores (1)'!D1020 -> 77 | E10: ='Jogadores (2)'!B4825 -> Gustaf Lagerbielke | F10: ='Jogadores (2)'!C4825 -> 70 | G10: ='Jogadores (1)'!C9047 -> Omar Rekik | H10: ='Jogadores (1)'!D9047 -> 64
A11: ='Jogadores (2)'!B163 -> Jeremie Frimpong | B11: ='Jogadores (2)'!C163 -> 83 | C11: ='Jogadores (1)'!C2123 -> Tsuyoshi Watanabe | D11: ='Jogadores (1)'!D2123 -> 74 | E11: ='Jogadores (2)'!B2701 -> Victor Eriksson | F11: ='Jogadores (2)'!C2701 -> 73 | G11: ='Jogadores (2)'!B11102 -> Saîf-Eddine Khaoui | H11: 65
A12: ='Jogadores (1)'!C1315 -> Jan Paul van Hecke | B12: ='Jogadores (1)'!D1315 -> 76 | C12: ='Jogadores (2)'!B8286 -> Junnosuke Suzuki | D12: ='Jogadores (2)'!C8286 -> 66 | E12: ='Jogadores (2)'!B1536 -> Eric Smith | F12: ='Jogadores (2)'!C1536 -> 75 | G12: Ghaith Zaalouni | H12: 65
A13: ='Jogadores (1)'!C278 -> Micky van de Ven | B13: ='Jogadores (1)'!D278 -> 82 | C13: ='Jogadores (1)'!C311 -> Daichi Kamada | D13: ='Jogadores (1)'!D311 -> 81 | E13: ='Jogadores (1)'!C1022 -> Mattias Svanberg | F13: ='Jogadores (1)'!D1022 -> 77 | G13: Adem Arous | H13: 62
A14: ='Jogadores (2)'!B777 -> Jorrel Hato | B14: ='Jogadores (2)'!C777 -> 78 | C14: ='Jogadores (1)'!C670 -> Ritsu Doan | D14: ='Jogadores (1)'!D670 -> 78 | E14: ='Jogadores (1)'!C4355 -> Jesper Karlström | F14: ='Jogadores (1)'!D4355 -> 70 | G14: Raed Chikhaoui | H14: 70
A15: ='Jogadores (1)'!C336 -> Jerdy Schouten | B15: ='Jogadores (1)'!D336 -> 81 | C15: ='Jogadores (1)'!C2609 -> Ao Tanaka | D15: ='Jogadores (1)'!D2609 -> 73 | E15: ='Jogadores (1)'!C7707 -> Yasin Ayari | F15: ='Jogadores (1)'!D7707 -> 66 | G15: Rani Khedira | H15: 76
A16: ='Jogadores (1)'!C155 -> Teun Koopmeiners | B16: ='Jogadores (1)'!D155 -> 83 | C16: ='Jogadores (1)'!C325 -> Kaoru Mitoma | D16: ='Jogadores (1)'!D325 -> 81 | E16: Herman Johansson | F16: 73 | G16: Aissa Laidouni | H16: 76
A17: ='Jogadores (1)'!C261 -> Tijjani Reijnders | B17: ='Jogadores (1)'!D261 -> 82 | C17: ='Jogadores (1)'!C6959 -> Joel Chima Fujita | D17: ='Jogadores (1)'!D6959 -> 67 | E17: ='Jogadores (1)'!C5664 -> Taha Abdi Ali | F17: ='Jogadores (1)'!D5664 -> 68 | G17: ='Jogadores (1)'!C8814 -> Mortadha Ben Ouanes | H17: ='Jogadores (1)'!D8814 -> 69
A18: ='Jogadores (1)'!C694 -> Ryan Gravenberch | B18: ='Jogadores (1)'!D694 -> 78 | C18: ='Jogadores (1)'!C6517 -> Yuito Suzuki | D18: ='Jogadores (1)'!D6517 -> 68 | E18: ='Jogadores (1)'!C4674 -> Williot Swedberg | F18: ='Jogadores (1)'!D4674 -> 70 | G18: Hadj Mahmoud | H18: 67
A19: ='Jogadores (1)'!C609 -> Quinten Timber | B19: ='Jogadores (1)'!D609 -> 79 | C19: ='Jogadores (1)'!C6457 -> Kodai Sano | D19: ='Jogadores (1)'!D6457 -> 68 | E19: ='Jogadores (2)'!B3022 -> Besfort Zeneli | F19: ='Jogadores (2)'!C3022 -> 72 | G19: ='Jogadores (1)'!C3315 -> Anis Slimane | H19: ='Jogadores (1)'!D3315 -> 67
A20: ='Jogadores (2)'!B3112 -> Luciano Valente | B20: ='Jogadores (2)'!C3112 -> 72 | C20: ='Jogadores (1)'!C6456 -> Kaishū Sano | D20: ='Jogadores (1)'!D6456 -> 68 | E20: ='Jogadores (1)'!C1915 -> Hugo Larsson | F20: ='Jogadores (1)'!D1915 -> 74 | G20: ='Jogadores (2)'!B6942 -> Louey Ben Farhat | H20: ='Jogadores (2)'!C6942 -> 64
A21: ='Jogadores (1)'!C182 -> Xavi Simons | B21: ='Jogadores (1)'!D182 -> 83 | C21: Ryunosoku Sato | D21: 73 | E21: ='Jogadores (1)'!C5732 -> Lucas Bergvall | F21: ='Jogadores (1)'!D5732 -> 68 | G21: Firas Chaouat | H21: 64
A22: ='Jogadores (2)'!B3048 -> Kees Smit | B22: ='Jogadores (2)'!C3048 -> 72 | C22: ='Jogadores (1)'!C711 -> Junya Ito | D22: ='Jogadores (1)'!D711 -> 78 | E22: ='Jogadores (1)'!C9628 -> Elliot Stroud | F22: ='Jogadores (1)'!D9628 -> 65 | G22: ='Jogadores (1)'!C10531 -> Sebastian Tounekti | H22: ='Jogadores (1)'!D10531 -> 62
A23: ='Jogadores (1)'!C1036 -> Wout Weghorst | B23: ='Jogadores (1)'!D1036 -> 77 | C23: ='Jogadores (1)'!C5357 -> Koki Ogawa | D23: ='Jogadores (1)'!D5357 -> 69 | E23: ='Jogadores (1)'!C2474 -> Gustaf Nilsson | F23: ='Jogadores (1)'!D2474 -> 73 | G23: ='Jogadores (2)'!B6149 -> Ismaël Gharbi | H23: ='Jogadores (2)'!C6149 -> 73
A24: ='Jogadores (1)'!C145 -> Cody Gakpo | B24: ='Jogadores (1)'!D145 -> 83 | C24: ='Jogadores (1)'!C1978 -> Keito Nakamura | D24: ='Jogadores (1)'!D1978 -> 74 | E24: ='Jogadores (1)'!C113 -> Viktor Gyökeres | F24: ='Jogadores (1)'!D113 -> 84 | G24: ='Jogadores (1)'!C3943 -> Elias Saad | H24: ='Jogadores (1)'!D3943 -> 71
A25: ='Jogadores (1)'!C542 -> Noa Lang | B25: ='Jogadores (1)'!D542 -> 79 | C25: ='Jogadores (1)'!C5269 -> Shuto Machino | D25: ='Jogadores (1)'!D5269 -> 69 | E25: ='Jogadores (1)'!C6283 -> Benjamin Nygren | F25: ='Jogadores (1)'!D6283 -> 68 | G25: ='Jogadores (1)'!C9668 -> Sayfallah Ltaief | H25: ='Jogadores (1)'!D9668 -> 71
A26: ='Jogadores (1)'!C162 -> Donyell Malen | B26: ='Jogadores (1)'!D162 -> 83 | C26: ='Jogadores (1)'!C2105 -> Ayase Ueda | D26: ='Jogadores (1)'!D2105 -> 74 | E26: ='Jogadores (1)'!C1122 -> Anthony Elanga | F26: ='Jogadores (1)'!D1122 -> 76 | G26: Hazem Mastouri | H26: 70
A27: ='Jogadores (1)'!C486 -> Brian Brobbey | B27: ='Jogadores (1)'!D486 -> 79 | C27: ='Jogadores (1)'!C1939 -> Daizen Maeda | D27: ='Jogadores (1)'!D1939 -> 74 | E27: ='Jogadores (1)'!C4067 -> Roony Bardghji | F27: ='Jogadores (1)'!D4067 -> 70 | G27: Omar Ben Ali | H27: 70
C28: ='Jogadores (2)'!B15221 -> Keisuke Goto | D28: ='Jogadores (2)'!C15221 -> 56 | G28: ='Jogadores (2)'!B3208 -> Anisse Saidi | H28: ='Jogadores (2)'!C3208 -> 48
C29: ='Jogadores (2)'!B8588 -> Kento Shiogai | D29: ='Jogadores (2)'!C8588 -> 66 | G29: Khalil Ayari | H29: 70
G30: Rayan Elloumi | H30: 57
G31: Mohamed Neffati | H31: 70
A33: Média | B33: =AVERAGE(B3:B27) -> 79.96 | C33: Média | D33: =AVERAGE(D3:D29) -> 71.481481 | E33: Média | F33: =AVERAGE(F3:F27) -> 72.12 | G33: Média | H33: =AVERAGE(H3:H31) -> 67.413793

Sheet Grupo G
A2: =Seleções!B26 -> Belgium | C2: =Seleções!B27 -> Egypt | E2: =Seleções!B28 -> IR Iran | G2: =Seleções!B29 -> New Zealand
A3: ='Jogadores (1)'!C1004 -> Matz Sels | B3: ='Jogadores (1)'!D1004 -> 77 | C3: Mohamed El Shenawy | D3: 73 | E3: Hossein Hosseini | F3: 67 | G3: ='Jogadores (2)'!B1803 -> Joe Bell | H3: ='Jogadores (2)'!C1803 -> 74
A4: ='Jogadores (1)'!C1660 -> Maarten Vandevoordt | B4: ='Jogadores (1)'!D1660 -> 75 | C4: Mahdy Soliman | D4: 75 | E4: Alireza Beiranvand | F4: 70 | G4: ='Jogadores (2)'!B3500 -> Marko Stamenić | H4: ='Jogadores (2)'!C3500 -> 71
A5: ='Jogadores (1)'!C7142 -> Senne Lammens | B5: ='Jogadores (1)'!D7142 -> 67 | C5: Mostafa Shobeir | D5: 72 | E5: Payam Niazmand | F5: 68 | G5: ='Jogadores (2)'!B3538 -> Alex Paulsen | H5: ='Jogadores (2)'!C3538 -> 71
A6: ='Jogadores (1)'!C7 -> Kevin De Bruyne | B6: ='Jogadores (1)'!D7 -> 90 | C6: Mohamed Alaa | D6: 76 | E6: Mohammad Khalifeh | F6: 66 | G6: ='Jogadores (2)'!B5085 -> Francis de Vries | H6: ='Jogadores (2)'!C5085 -> 69
A7: ='Jogadores (1)'!C82 -> Loïs Openda | B7: ='Jogadores (1)'!D82 -> 85 | C7: Mohamed Hany | D7: 70 | E7: Shoja Khalilzadeh | F7: 72 | G7: ='Jogadores (2)'!B5495 -> Tyler Bindon | H7: ='Jogadores (2)'!C5495 -> 69
A8: ='Jogadores (1)'!C250 -> Romelu Lukaku | B8: ='Jogadores (1)'!D250 -> 82 | C8: ='Jogadores (2)'!B7484 -> Ramy Rabia | D8: ='Jogadores (2)'!C7484 -> 67 | E8: Ehsan Hajsafi | F8: 71 | G8: ='Jogadores (2)'!B5898 -> Ben Old | H8: ='Jogadores (2)'!C5898 -> 68
A9: ='Jogadores (1)'!C343 -> Youri Tielemans | B9: ='Jogadores (1)'!D343 -> 81 | C9: ='Jogadores (2)'!B2165 -> Mohamed Abdelmonem | D9: ='Jogadores (2)'!C2165 -> 74 | E9: Ramin Rezaeian | F9: 70 | G9: ='Jogadores (2)'!B5944 -> Kosta Barbarouses | H9: ='Jogadores (2)'!C5944 -> 68
A10: ='Jogadores (1)'!C385 -> Jérémy Doku | B10: ='Jogadores (1)'!D385 -> 80 | C10: Ahmed Fatouh | D10: 77 | E10: Milad Mohammadi | F10: 72 | G10: ='Jogadores (2)'!B6658 -> Finn Surman | H10: ='Jogadores (2)'!C6658 -> 68
A11: ='Jogadores (1)'!C457 -> Axel Witsel | B11: ='Jogadores (1)'!D457 -> 80 | C11: Yasser Ibrahim | D11: 64 | E11: Daniel Esmaeilifar | F11: 71 | G11: ='Jogadores (2)'!B6877 -> Alex Rufer | H11: ='Jogadores (2)'!C6877 -> 67
A12: ='Jogadores (1)'!C496 -> Charles De Ketelaere | B12: ='Jogadores (1)'!D496 -> 79 | C12: Hossam Abdelmaguid | D12: 78 | E12: Hossein Kanani | F12: 75 | G12: ='Jogadores (2)'!B6894 -> Callum McCowatt | H12: ='Jogadores (2)'!C6894 -> 67
A13: ='Jogadores (1)'!C555 -> Dodi Lukébakio | B13: ='Jogadores (1)'!D555 -> 79 | C13: Khaled Sobhy | D13: 66 | E13: Ali Nemati | F13: 72 | G13: ='Jogadores (2)'!B8098 -> Ryan Thomas | H13: ='Jogadores (2)'!C8098 -> 66
A14: ='Jogadores (1)'!C751 -> Amadou Onana | B14: ='Jogadores (1)'!D751 -> 78 | C14: Tarek Alaa | D14: 64 | E14: Abolfazl Jalali | F14: 68 | G14: ='Jogadores (2)'!B8316 -> Elijah Just | H14: ='Jogadores (2)'!C8316 -> 66
A15: ='Jogadores (1)'!C776 -> Alexis Saelemaekers | B15: ='Jogadores (1)'!D776 -> 78 | C15: Zizo | D15: 72 | E15: Saleh Hardani | F15: 65 | G15: ='Jogadores (2)'!B9127 -> Max Crocombe | H15: ='Jogadores (2)'!C9127 -> 65
A16: ='Jogadores (1)'!C849 -> Timothy Castagne | B16: ='Jogadores (1)'!D849 -> 77 | C16: Hamdy Fathy | D16: 62 | E16: Aria Yousefi | F16: 68 | G16: ='Jogadores (2)'!B9129 -> Bill Tuiloma | H16: ='Jogadores (2)'!C9129 -> 65
A17: ='Jogadores (1)'!C1024 -> Arthur Theate | B17: ='Jogadores (1)'!D1024 -> 77 | C17: Emam Ashour | D17: 69 | E17: Saman Fallah | F17: 62 | G17: ='Jogadores (2)'!B9856 -> James McGarry | H17: ='Jogadores (2)'!C9856 -> 64
A18: ='Jogadores (1)'!C1102 -> Maxim De Cuyper | B18: ='Jogadores (1)'!D1102 -> 76 | C18: Ibrahim Adel | D18: 69 | E18: Danial Iri | F18: 65 | G18: ='Jogadores (2)'!B9908 -> Tim Payne | H18: ='Jogadores (2)'!C9908 -> 64
A19: ='Jogadores (1)'!C1106 -> Zeno Debast | B19: ='Jogadores (1)'!D1106 -> 76 | C19: Ahmed Koka | D19: 70 | E19: Hossein Abarghouei | F19: 62 | G19: ='Jogadores (2)'!B9911 -> Logan Rogerson | H19: ='Jogadores (2)'!C9911 -> 64
A20: ='Jogadores (1)'!C1223 -> Thomas Meunier | B20: ='Jogadores (1)'!D1223 -> 76 | C20: Mahmoud Saber | D20: 65 | E20: Saeid Ezatolahi | F20: 64 | G20: ='Jogadores (2)'!B11789 -> Callan Elliot | H20: ='Jogadores (2)'!C11789 -> 62
A21: ='Jogadores (1)'!C1533 -> Brandon Mechele | B21: ='Jogadores (1)'!D1533 -> 75 | C21: Mohanad Lasheen | D21: 75 | E21: Ali Gholizadeh | F21: 71 | G21: ='Jogadores (2)'!B11796 -> Ben Waine | H21: ='Jogadores (2)'!C11796 -> 62
A22: ='Jogadores (1)'!C1587 -> Nicolas Raskin | B22: ='Jogadores (1)'!D1587 -> 75 | C22: Marwan Attia | D22: 74 | E22: Mehdi Torabi | F22: 67 | G22: ='Jogadores (2)'!B11885 -> Lachlan Bayliss | H22: ='Jogadores (2)'!C11885 -> 62
A23: ='Jogadores (1)'!C2828 -> Koni De Winter | B23: ='Jogadores (1)'!D2828 -> 72 | C23: Trézéguet | D23: 75 | E23: Omid Norafkan | F23: 60 | G23: ='Jogadores (2)'!B13324 -> Jesse Randall | H23: ='Jogadores (2)'!C13324 -> 60
A24: ='Jogadores (1)'!C5098 -> Mika Godts | B24: ='Jogadores (1)'!D5098 -> 69 | C24: Mostafa Mohamed | D24: 75 | E24: Mehdi Ghayedi | F24: 74 | G24: ='Jogadores (2)'!B13406 -> Michael Woud | H24: ='Jogadores (2)'!C13406 -> 60
A25: ='Jogadores (1)'!C6510 -> Lucas Stassin | B25: ='Jogadores (1)'!D6510 -> 68 | C25: Islam Eissa Elsayed Mohamed Attia | D25: 70 | E25: Mohammad Mohebbi | F25: 73 | G25: Andre De Jong | H25: 58
A26: ='Jogadores (1)'!C7280 -> Nathan Ngoy | B26: ='Jogadores (1)'!D7280 -> 67 | C26: Haissem Hassan | D26: 70 | E26: Hadi Habibinejad | F26: 62
A27: ='Jogadores (1)'!C12312 -> Joaquin Seys | B27: ='Jogadores (1)'!D12312 -> 62 | C27: Omar Marmoush | D27: 79 | E27: Mohammad Ghorbani | F27: 64
A28: Nathan de Cat | B28: 63 | C28: Nasser Mansi | D28: 68 | E28: Amir Razzaghinia | F28: 62
C29: Mohamed Salah | D29: 89 | E29: Alireza Jahanbakhsh | F29: 71
E30: Mehdi Taremi | F30: 78
E31: Ali Alipour | F31: 66
E32: Saman Ghoddos | F32: 67
E33: Amirhossein Hosseinzadeh | F33: 66
E34: Dennis Eckert | F34: 73
E35: Shahriar Moghanlou | F35: 57
E36: Mehdi Hashemnejad | F36: 68
E37: Amirhossein Mahmoudi | F37: 55
E38: Ehsan Mahroughi | F38: 60
A40: média | B40: =AVERAGE(B3:B28) -> 75.538462 | C40: média | D40: =AVERAGE(D3:D29) -> 71.777778 | E40: média | F40: =AVERAGE(F3:F38) -> 67.277778 | G40: média | H40: =AVERAGE(H3:H28) -> 65.652174

Sheet Grupo H
A2: =Seleções!B30 -> Spain | C2: =Seleções!B31 -> Cabo Verde | E2: =Seleções!B32 -> Saudi Arabia | G2: =Seleções!B33 -> Uruguay
A3: Rodrigo Hernández Cascante | B3: 90 | C3: Vozinha | D3: 78 | E3: Saud Abdulhamid | F3: 78 | G3: Federico Valverde | H3: 88
A4: Lamine Yamal Nasraoui Ebana | B4: 89 | C4: Márcio Rosa | D4: 77 | E4: Abdulelah Al Amri | F4: 69 | G4: Emiliano Martínez | H4: 87
A5: Pedro González López | B5: 89 | C5: Carlos Dos Santos | D5: 75 | E5: Mohammed Al Owais | F5: 69 | G5: Ronald Araujo | H5: 85
A6: David Raya Martin | B6: 87 | C6: Steven Moreira | D6: 72 | E6: Nawaf Al Aqidi | F6: 68 | G6: José María Giménez | H6: 83
A7: Unai Simón Mendibil | B7: 85 | C7: Diney | D7: 65 | E7: Ahmed Al Kassar | F7: 63 | G7: Darwin Núñez | H7: 82
A8: Daniel Olmo Carvajal | B8: 85 | C8: Roberto Lopes | D8: 66 | E8: Muteb Al Mufarrij | F8: 59 | G8: Fernando Muslera | H8: 81
A9: Marcos Llorente Moreno | B9: 84 | C9: Sidny Cabral | D9: 67 | E9: Mohammed Al Yami | F9: 56 | G9: Manuel Ugarte | H9: 81
A10: Marc Cucurella Saseta | B10: 84 | C10: Jorginho Soares | D10: 70 | E10: Mohammed Kanno | F10: 71 | G10: Santiago Bueno | H10: 77
A11: Alejandro Grimaldo García | B11: 84 | C11: Wagner Pina | D11: 71 | E11: Ali Lajami | F11: 69 | G11: Mathías Olivera | H11: 77
A12: Alejandro Baena Rodríguez | B12: 84 | C12: Kelvin Spencer Pires | D12: 72 | E12: Ali Majrashi | F12: 65 | G12: Facundo Torres | H12: 74
A13: Joan García Pons | B13: 83 | C13: Semedo | D13: 74 | E13: Nawaf Boushal | F13: 63 | G13: Emiliano Martínez | H13: 73
A14: Alejandro Remiro Gargallo | B14: 83 | C14: Laros Duarte | D14: 68 | E14: Khalifa Al Dawsari | F14: 60 | G14: Santiago Mele | H14: 73
... A28: Víctor Muñoz Villanueva | B28: 65 | C28: Fábio Domingos | D28: 62 | E28: Abdulaziz Al-Aliwa | F28: 55 | G28: Giorgian de Arrascaeta | H28: 73
A29: Fermín López | B29: 73 | E29: Feras Al- Brikan | F29: 60 | G29: Brian Barboza | H29: 70
E30: Murad Al - Hawsawi | F30: 62 | G30: Benjamín García | H30: 61
E31: Salman Al Faraj | F31: 69 | G31: Sebastián Cáceres | H31: 74
E32: Rayane Hamidou | F32: 67 | G32: Matías Viña | H32: 74
E33: Hassan Mahbub | F33: 66 | G33: Gullermo Varela | H33: 73
G34: José Luis Rodríguez | H34: 72
G35: Sergio Rochet | H35: 78
A38: média | B38: =AVERAGE(B3:B29) -> 81.888889 | C38: média | D38: =AVERAGE(D3:D29) -> 69.653846 | E38: média | F38: =AVERAGE(F3:F33) -> 64.225806 | G38: média | H38: =AVERAGE(H3:H35) -> 74.848485

Sheet Grupo I
A2: =Seleções!B34 -> France | C2: =Seleções!B35 -> Senegal | E2: Iraq | G2: =Seleções!B37 -> Norway
A3: ='Jogadores (1)'!C263 -> Brice Samba | B3: ='Jogadores (1)'!D263 -> 82 | C3: ='Jogadores (1)'!C1417 -> Mory Diaw | D3: ='Jogadores (1)'!D1417 -> 75 | E3: Fahad Talib Raheem | F3: 50 | G3: ='Jogadores (1)'!C1247 -> Ørjan Nyland | H3: ='Jogadores (1)'!D1247 -> 76
A4: ='Jogadores (1)'!C38 -> Mike Maignan | B4: ='Jogadores (1)'!D38 -> 87 | C4: ='Jogadores (1)'!C423 -> Édouard Mendy | D4: ='Jogadores (1)'!D423 -> 80 | E4: Ahmed Basil Al-Fadhli | F4: 65 | G4: ='Jogadores (2)'!B7217 -> Viljar Myhra | H4: ='Jogadores (2)'!C7217 -> 67
A5: ='Jogadores (1)'!C377 -> Lucas Chevalier | B5: ='Jogadores (1)'!D377 -> 80 | C5: ='Jogadores (2)'!B709 -> Yehvann Diouf | D5: ='Jogadores (2)'!C709 -> 78 | E5: Kumel Saadi | F5: 63 | G5: ='Jogadores (1)'!C5516 -> Egil Selvik | H5: ='Jogadores (1)'!D5516 -> 69
A6: ='Jogadores (1)'!C503 -> Lucas Digne | B6: ='Jogadores (1)'!D503 -> 79 | C6: ='Jogadores (1)'!C116 -> Kalidou Koulibaly | D6: ='Jogadores (1)'!D116 -> 84 | E6: Frans Dhia Haddad | F6: 57 | G6: ='Jogadores (2)'!B2907 -> Marcus Pedersen | H6: ='Jogadores (2)'!C2907 -> 72
A7: ='Jogadores (1)'!C151 -> Lucas Hernández | B7: ='Jogadores (1)'!D151 -> 83 | C7: ='Jogadores (1)'!C1243 -> Moussa Niakhaté | D7: ='Jogadores (1)'!D1243 -> 76 | E7: Rebin Solaka | F7: 65 | G7: ='Jogadores (1)'!C1050 -> Kristoffer Ajer | H7: ='Jogadores (1)'!D1050 -> 76
A8: ='Jogadores (1)'!C277 -> Dayot Upamecano | B8: ='Jogadores (1)'!D277 -> 82 | C8: Abdoulaye Seck | D8: 71 | E8: ='Jogadores (1)'!C11683 -> Hussein Ali | F8: ='Jogadores (1)'!D11683 -> 62 | G8: ='Jogadores (1)'!C595 -> Julian Ryerson | H8: ='Jogadores (1)'!D595 -> 79
A9: ='Jogadores (1)'!C34 -> Theo Hernández | B9: ='Jogadores (1)'!D34 -> 87 | C9: ='Jogadores (1)'!C1883 -> Ismail Jakobs | D9: ='Jogadores (1)'!D1883 -> 74 | E9: Maytham Jabbar | F9: 65 | G9: ='Jogadores (1)'!C2190 -> Fredrik Andre Bjørkan | H9: ='Jogadores (1)'!D2190 -> 73
A10: ='Jogadores (1)'!C154 -> Ibrahima Konaté | B10: ='Jogadores (1)'!D154 -> 83 | C10: ='Jogadores (2)'!B4703 -> Antoine Mendy | D10: ='Jogadores (2)'!C4703 -> 70 | E10: Munaf Younis Hashim | F10: 67 | G10: ='Jogadores (1)'!C5742 -> Odin Luraas Bjørtuft | H10: ='Jogadores (1)'!D5742 -> 68
A11: ='Jogadores (1)'!C1190 -> Maxence Lacroix | B11: ='Jogadores (1)'!D1190 -> 76 | C11: ='Jogadores (1)'!C9559 -> Mamadou Sarr | D11: ='Jogadores (1)'!D9559 -> 65 | E11: Merchas Doski | F11: 69 | G11: ='Jogadores (1)'!C9105 -> Torbjørn L. Heggem | H11: ='Jogadores (1)'!D9105 -> 65
A12: ='Jogadores (1)'!C716 -> Pierre Kalulu | B12: ='Jogadores (1)'!D716 -> 78 | C12: ='Jogadores (1)'!C13491 -> Nobel Mendy | D12: ='Jogadores (1)'!D13491 -> 60 | E12: Ahmed Hasan | F12: 70 | G12: ='Jogadores (1)'!C3103 -> Leo Østigård | H12: ='Jogadores (1)'!D3103 -> 72
A13: ='Jogadores (1)'!C404 -> Malo Gusto | B13: ='Jogadores (1)'!D404 -> 80 | C13: ='Jogadores (1)'!C3483 -> El Hadji Malick Diouf | D13: ='Jogadores (1)'!D3483 -> 71 | E13: Akam Hashim Rahman | F13: 71 | G13: ='Jogadores (2)'!B9370 -> Henrik Falchener | H13: ='Jogadores (2)'!C9370 -> 65
A14: ='Jogadores (1)'!C73 -> N'Golo Kanté | B14: ='Jogadores (1)'!D73 -> 85 | C14: ='Jogadores (1)'!C2211 -> Lamine Camara | D14: ='Jogadores (1)'!D2211 -> 73 | E14: Zaid Tahseen | F14: 72 | G14: ='Jogadores (1)'!C4742 -> David Møller Wolfe | H14: ='Jogadores (1)'!D4742 -> 70
A15: ='Jogadores (2)'!B142 -> Adrien Rabiot | B15: ='Jogadores (2)'!C142 -> 83 | C15: ='Jogadores (1)'!C1152 -> Idrissa Gueye | D15: ='Jogadores (1)'!D1152 -> 76 | E15: Ibrahim Bayesh | F15: 65 | G15: ='Jogadores (1)'!C3249 -> Morten Thorsby | H15: ='Jogadores (1)'!D3249 -> 72
A16: ='Jogadores (1)'!C89 -> Aurélien Tchouaméni | B16: ='Jogadores (1)'!D89 -> 85 | C16: ='Jogadores (1)'!C1416 -> Krépin Diatta | D16: ='Jogadores (1)'!D1416 -> 75 | E16: Kevin Yakob | F16: 69 | G16: ='Jogadores (1)'!C1077 -> Patrick Berg | H16: ='Jogadores (1)'!D1077 -> 76
A17: ='Jogadores (1)'!C137 -> Eduardo Camavinga | B17: ='Jogadores (1)'!D137 -> 83 | C17: ='Jogadores (1)'!C1460 -> Pape Gueye | D17: ='Jogadores (1)'!D1460 -> 75 | E17: Peter Gwargis | F17: 65 | G17: ='Jogadores (1)'!C1078 -> Sander Berge | H17: ='Jogadores (1)'!D1078 -> 76
A18: ='Jogadores (1)'!C1185 -> Kouadio Manu Koné | B18: ='Jogadores (1)'!D1185 -> 76 | C18: ='Jogadores (1)'!C1761 -> Pathé Ciss | D18: ='Jogadores (1)'!D1761 -> 74 | E18: Aimar Sher | F18: 70 | G18: ='Jogadores (2)'!B2033 -> Jens Petter Hauge | H18: ='Jogadores (2)'!C2033 -> 74
A19: ='Jogadores (1)'!C258 -> Michael Olise | B19: ='Jogadores (1)'!D258 -> 82 | C19: ='Jogadores (1)'!C596 -> Pape Matar Sarr | D19: ='Jogadores (1)'!D596 -> 79 | E19: ='Jogadores (1)'!C8727 -> Amir Al-Ammari | F19: ='Jogadores (1)'!D8727 -> 65 | G19: ='Jogadores (1)'!C8326 -> Felix Horn Myhre | H19: ='Jogadores (1)'!D8326 -> 66
A20: ='Jogadores (1)'!C1392 -> Rayan Cherki | B20: ='Jogadores (1)'!D1392 -> 75 | C20: ='Jogadores (1)'!C2269 -> Habib Diarra | D20: ='Jogadores (1)'!D2269 -> 73 | E20: ='Jogadores (1)'!C11145 -> Zidane Iqbal | F20: ='Jogadores (1)'!D11145 -> 63 | G20: ='Jogadores (1)'!C2615 -> Kristian Thorstvedt | H20: ='Jogadores (1)'!D2615 -> 73
A21: ='Jogadores (1)'!C1051 -> Maghnes Akliouche | B21: ='Jogadores (1)'!D1051 -> 76 | C21: ='Jogadores (1)'!C1793 -> Habib Diallo | D21: ='Jogadores (1)'!D1793 -> 74 | E21: Marko Lawk Farji | F21: 67 | G21: ='Jogadores (1)'!C2748 -> Oscar Bobb | H21: ='Jogadores (1)'!D2748 -> 72
A22: ='Jogadores (1)'!C187 -> Marcus Thuram | B22: ='Jogadores (1)'!D187 -> 83 | C22: ='Jogadores (1)'!C1288 -> Ismaïla Sarr | D22: ='Jogadores (1)'!D1288 -> 76 | E22: Hasan Abdulkareem | F22: 69 | G22: ='Jogadores (1)'!C3086 -> Antonio Nusa | H22: ='Jogadores (1)'!D3086 -> 72
A23: ='Jogadores (1)'!C57 -> Ousmane Dembélé | B23: ='Jogadores (1)'!D57 -> 86 | C23: Cherif Ndiaye | D23: 69 | E23: Zaid Ismael Khaleel Al Dulaimi | F23: 65 | G23: ='Jogadores (1)'!C271 -> Alexander Sørloth | H23: ='Jogadores (1)'!D271 -> 82
A24: ='Jogadores (1)'!C2 -> Kylian Mbappé | B24: ='Jogadores (1)'!D2 -> 91 | C24: ='Jogadores (1)'!C1549 -> Iliman Ndiaye | D24: ='Jogadores (1)'!D1549 -> 75 | E24: Aymen Hussein | F24: 67 | G24: ='Jogadores (1)'!C1499 -> Jørgen Strand Larsen | H24: ='Jogadores (1)'!D1499 -> 75
A25: ='Jogadores (1)'!C241 -> Randal Kolo Muani | B25: ='Jogadores (1)'!D241 -> 82 | C25: ='Jogadores (1)'!C501 -> Boulaye Dia | D25: ='Jogadores (1)'!D501 -> 79 | E25: Mohannad Ali Kadhim | F25: 69 | G25: ='Jogadores (1)'!C4 -> Erling Haaland | H25: ='Jogadores (1)'!D4 -> 91
A26: ='Jogadores (1)'!C1120 -> Hugo Ekitike | B26: ='Jogadores (1)'!D1120 -> 76 | C26: ='Jogadores (1)'!C533 -> Nicolas Jackson | D26: ='Jogadores (1)'!D533 -> 79 | E26: Ali Yousif Hashim | F26: 58 | G26: ='Jogadores (1)'!C3197 -> Andreas Schjelderup | H26: ='Jogadores (1)'!D3197 -> 72
A27: ='Jogadores (2)'!B76 -> Désiré Doué | B27: ='Jogadores (2)'!C76 -> 85 | C27: ='Jogadores (1)'!C2840 -> Bamba Dieng | D27: ='Jogadores (1)'!D2840 -> 72 | E27: Ali Jasim | F27: 62
C28: ='Jogadores (2)'!B8405 -> Mamadou Diakhon | D28: ='Jogadores (2)'!C8405 -> 66 | E28: Youssef Amyn | F28: 69
C29: ='Jogadores (2)'!B1293 -> Assane Diao | D29: ='Jogadores (2)'!C1293 -> 76 | E29: Ali Ibrahim Al-Hamadi | F29: 65
C30: ='Jogadores (2)'!B8724 -> Ibrahim Mbaye | D30: ='Jogadores (2)'!C8724 -> 66 | E30: Karrar Nabeel | F30: 58
A32: Média | B32: =AVERAGE(B3:B27) -> 81.8 | C32: Média | D32: =AVERAGE(D3:D30) -> 73.607143 | E32: Média | F32: =AVERAGE(F3:F30) -> 65.071429 | G32: Média | H32: =AVERAGE(H3:H26) -> 73.041667

Sheet Grupo J
A2: =Seleções!B38 -> Argentina | C2: =Seleções!B39 -> Algeria | E2: =Seleções!B40 -> Austria | G2: =Seleções!B41 -> Jordan
A3: ='Jogadores (1)'!C44 -> Emiliano Martínez | B3: ='Jogadores (1)'!D44 -> 87 | C3: Melvin Mastil | D3: 51 | E3: ='Jogadores (2)'!B2401 -> Alexander Schlager | F3: ='Jogadores (2)'!C2401 -> 73 | G3: Yazeed Abu Laila | H3: 60
A4: ='Jogadores (1)'!C577 -> Juan Musso | B4: ='Jogadores (1)'!D577 -> 79 | C4: Killian Belazzoug | D4: 70 | E4: ='Jogadores (2)'!B2890 -> Patrick Pentz | F4: ='Jogadores (2)'!C2890 -> 72 | G4: Abdallah Al-Fakhouri | H4: 68
A5: ='Jogadores (1)'!C594 -> Gerónimo Rulli | B5: ='Jogadores (1)'!D594 -> 79 | C5: ='Jogadores (1)'!C4419 -> Anthony Mandréa | D5: ='Jogadores (1)'!D4419 -> 70 | E5: ='Jogadores (2)'!B3137 -> Tobias Lawal | F5: ='Jogadores (2)'!C3137 -> 72 | G5: Abdel Rahman Mohammad Awwad Suleiman | H5: 62
A6: ='Jogadores (1)'!C126 -> Cristian Romero | B6: ='Jogadores (1)'!D126 -> 84 | C6: Luca Zidane | D6: 68 | E6: ='Jogadores (2)'!B7587 -> Florian Wiegele | F6: ='Jogadores (2)'!C7587 -> 67 | G6: ='Jogadores (1)'!C11680 -> Yazan Al-Arab | H6: 71
A7: ='Jogadores (1)'!C329 -> Nicolás Otamendi | B7: ='Jogadores (1)'!D329 -> 81 | C7: ='Jogadores (2)'!B6734 -> Sohaïb Nair | D7: ='Jogadores (2)'!C6734 -> 68 | E7: ='Jogadores (1)'!C67 -> David Alaba | F7: ='Jogadores (1)'!D67 -> 85 | G7: Mohammad Abualnadi | H7: 65
A8: ='Jogadores (1)'!C786 -> Nicolás Tagliafico | B8: ='Jogadores (1)'!D786 -> 78 | C8: ='Jogadores (1)'!C1207 -> Aïssa Mandi | D8: ='Jogadores (1)'!D1207 -> 76 | E8: ='Jogadores (1)'!C548 -> Philipp Lienhart | F8: ='Jogadores (1)'!D548 -> 79 | G8: Saleem Obaid | H8: 68
A9: ='Jogadores (1)'!C133 -> Marcos Acuña | B9: ='Jogadores (1)'!D133 -> 83 | C9: ='Jogadores (2)'!B3665 -> Mehdi Dorval | D9: ='Jogadores (2)'!C3665 -> 71 | E9: ='Jogadores (1)'!C1040 -> Maximilian Wöber | F9: ='Jogadores (1)'!D1040 -> 77 | G9: Yousef Abualjazar | H9: 67
A10: ='Jogadores (1)'!C254 -> Nahuel Molina | B10: ='Jogadores (1)'!D254 -> 82 | C10: ='Jogadores (1)'!C6734 -> Zineddine Belaïd | D10: ='Jogadores (1)'!D6734 -> 67 | E10: ='Jogadores (1)'!C1441 -> Marco Friedl | F10: ='Jogadores (1)'!D1441 -> 75 | G10: Abdallah Nasib | H10: 68
A11: ='Jogadores (1)'!C945 -> Lucas Martínez Quarta | B11: ='Jogadores (1)'!D945 -> 77 | C11: ='Jogadores (2)'!B314 -> Rayan Aït-Nouri | D11: ='Jogadores (2)'!C314 -> 81 | E11: ='Jogadores (1)'!C759 -> Stefan Posch | F11: ='Jogadores (1)'!D759 -> 78 | G11: Mohannad Abu Taha | H11: 64
A12: ='Jogadores (1)'!C779 -> Marcos Senesi | B12: ='Jogadores (1)'!D779 -> 78 | C12: Achref Abada | D12: 79 | E12: ='Jogadores (1)'!C1976 -> Phillipp Mwene | F12: ='Jogadores (1)'!D1976 -> 74 | G12: Mohammad Abu Hasheesh | H12: 70
A13: ='Jogadores (1)'!C2547 -> Gabriel Rojas | B13: ='Jogadores (1)'!D2547 -> 73 | C13: ='Jogadores (1)'!C645 -> Ramy Bensebaini | D13: ='Jogadores (1)'!D645 -> 78 | E13: ='Jogadores (1)'!C380 -> Kevin Danso | F13: ='Jogadores (1)'!D380 -> 80 | G13: Husam Ali Mohammad Abudahab | H13: 62
A14: Agustín Giay | B14: 71 | C14: ='Jogadores (1)'!C8798 -> Rafik Belghali | D14: ='Jogadores (1)'!D8798 -> 65 | E14: ='Jogadores (1)'!C5551 -> Michael Svoboda | F14: ='Jogadores (1)'!D5551 -> 69 | G14: Amer Rasem Adel Jamous | H14: 69
A15: ='Jogadores (1)'!C10460 -> Tomás Palacios | B15: ='Jogadores (1)'!D10460 -> 64 | C15: ='Jogadores (1)'!C1349 -> Houssem Aouar | D15: ='Jogadores (1)'!D1349 -> 75 | E15: ='Jogadores (2)'!B1642 -> David Affengruber | F15: ='Jogadores (2)'!C1642 -> 75 | G15: Ahmad Assaf | H15: 62
A16: ='Jogadores (1)'!C755 -> Leandro Paredes | B16: ='Jogadores (1)'!D755 -> 78 | C16: Adil Aouchiche | D16: 68 | E16: ='Jogadores (2)'!B1786 -> Alexander Prass | F16: ='Jogadores (2)'!C1786 -> 74 | G16: Mohammad Ahmed Mohammad Taha | H16: 65
A17: ='Jogadores (1)'!C104 -> Rodrigo De Paul | B17: ='Jogadores (1)'!D104 -> 84 | C17: ='Jogadores (1)'!C1682 -> Ramiz Zerrouki | D17: ='Jogadores (1)'!D1682 -> 75 | E17: ='Jogadores (1)'!C157 -> Konrad Laimer | F17: ='Jogadores (1)'!D157 -> 83 | G17: Noor Al-Rawabdeh | H17: 68
A18: ='Jogadores (1)'!C123 -> Exequiel Palacios | B18: ='Jogadores (1)'!D123 -> 84 | C18: ='Jogadores (1)'!C9659 -> Yacine Titraoui | D18: ='Jogadores (1)'!D9659 -> 65 | E18: ='Jogadores (1)'!C127 -> Marcel Sabitzer | F18: ='Jogadores (1)'!D127 -> 84 | G18: Ibrahim Sadeh | H18: 70
A19: ='Jogadores (1)'!C55 -> Alexis Mac Allister | B19: ='Jogadores (1)'!D55 -> 86 | C19: ='Jogadores (1)'!C1081 -> Hicham Boudaoui | D19: ='Jogadores (1)'!D1081 -> 76 | E19: ='Jogadores (2)'!B5894 -> Alessandro Schöpf | F19: ='Jogadores (2)'!C5894 -> 68 | G19: Mohammad Ratib Mohammad Al-Daoud | H19: 62
A20: Thiago Almada | B20: 79 | C20: ='Jogadores (1)'!C854 -> Farès Chaïbi | D20: ='Jogadores (1)'!D854 -> 77 | E20: ='Jogadores (1)'!C1850 -> Florian Grillitsch | F20: ='Jogadores (1)'!D1850 -> 74 | G20: Nizar Al-Rashdan | H20: 70
A21: ='Jogadores (1)'!C221 -> Enzo Fernández | B21: ='Jogadores (1)'!D221 -> 82 | C21: Adil Boulbina | D21: 75 | E21: ='Jogadores (1)'!C1619 -> Romano Schmid | F21: ='Jogadores (1)'!D1619 -> 75 | G21: Yousef Hussein Abed Qashi | H21: 60
A22: ='Jogadores (1)'!C3790 -> Máximo Perrone | B22: ='Jogadores (1)'!D3790 -> 71 | C22: ='Jogadores (1)'!C692 -> Amine Gouiri | D22: ='Jogadores (1)'!D692 -> 78 | E22: ='Jogadores (1)'!C335 -> Xaver Schlager | F22: ='Jogadores (1)'!D335 -> 81 | G22: Mahmoud Al-Mardi | H22: 65
A23: ='Jogadores (1)'!C2175 -> Valentín Barco | B23: ='Jogadores (1)'!D2175 -> 73 | C23: ='Jogadores (1)'!C9837 -> Nadhir Benbouali | D23: ='Jogadores (1)'!D9837 -> 64 | E23: ='Jogadores (1)'!C368 -> Christoph Baumgartner | F23: ='Jogadores (1)'!D368 -> 80 | G23: Baha' Faisal | H23: 66
A24: ='Jogadores (1)'!C5398 -> Nico Paz | B24: ='Jogadores (1)'!D5398 -> 69 | C24: Farès Ghedjemis | D24: 70 | E24: Carney Chukwuemeka | F24: 78 | G24: ='Jogadores (1)'!C1340 -> Musa Al Tamari | H24: ='Jogadores (1)'!D1340 -> 75
A25: ='Jogadores (1)'!C18 -> Lionel Messi | B25: ='Jogadores (1)'!D18 -> 88 | C25: ='Jogadores (2)'!B9407 -> Amin Chiakha | D25: ='Jogadores (2)'!C9407 -> 65 | E25: ='Jogadores (1)'!C1039 -> Patrick Wimmer | F25: ='Jogadores (1)'!D1039 -> 77 | G25: Mohammed Abu Zraiq | H25: 67
A26: ='Jogadores (1)'!C398 -> Nicolás González | B26: ='Jogadores (1)'!D398 -> 80 | C26: ='Jogadores (1)'!C78 -> Riyad Mahrez | D26: ='Jogadores (1)'!D78 -> 85 | E26: ='Jogadores (1)'!C1003 -> Nicolas Seiwald | F26: ='Jogadores (1)'!D1003 -> 77 | G26: Abdallah Khaled Khaleel Al-Shuaybat | H26: 62
A27: ='Jogadores (1)'!C97 -> Julián Álvarez | B27: ='Jogadores (1)'!D97 -> 84 | C27: ='Jogadores (1)'!C7010 -> Anis Hadj-Moussa | D27: ='Jogadores (1)'!D7010 -> 67 | E27: Paul Wanner | F27: 74 | G27: Ibrahim Mohammad Abdallah Sabra | H27: 60
A28: Flaco López | B28: 78 | C28: ='Jogadores (1)'!C1345 -> Mohamed Amoura | D28: ='Jogadores (1)'!D1345 -> 75 | E28: ='Jogadores (1)'!C361 -> Marko Arnautović | F28: ='Jogadores (1)'!D361 -> 80 | G28: Odeh Burhan Shehade Fakhoury | H28: 60
A29: ='Jogadores (1)'!C3213 -> Giuliano Simeone | B29: ='Jogadores (1)'!D3213 -> 72 | C29: ='Jogadores (2)'!B3713 -> Ibrahim Maza | D29: ='Jogadores (2)'!C3713 -> 71 | E29: ='Jogadores (1)'!C695 -> Michael Gregoritsch | F29: ='Jogadores (1)'!D695 -> 78 | G29: Ali Ahmad Ali Azaizeh | H29: 60
A30: ='Jogadores (1)'!C6362 -> Gianluca Prestianni | B30: ='Jogadores (1)'!D6362 -> 68 | E30: ='Jogadores (1)'!C918 -> Saša Kalajdžić | F30: ='Jogadores (1)'!D918 -> 77
A31: ='Jogadores (1)'!C5295 -> Franco Mastantuono | B31: ='Jogadores (1)'!D5295 -> 69
A33: Média | B33: =AVERAGE(B3:B31) -> 77.965517 | C33: Média | D33: =AVERAGE(D3:D29) -> 71.481481 | E33: Média | F33: =AVERAGE(F3:F30) -> 76.285714 | G33: Média | H33: =AVERAGE(H3:H29) -> 65.407407

Sheet Grupo K
A2: =Seleções!B42 -> Portugal | C2: Congo | E2: =Seleções!B44 -> Uzbekistan | G2: =Seleções!B45 -> Colombia
A3: ='Jogadores (1)'!C119 -> Diogo Costa | B3: ='Jogadores (1)'!D119 -> 84 | C3: ='Jogadores (1)'!C6244 -> Lionel Mpasi | D3: ='Jogadores (1)'!D6244 -> 68 | E3: Botirali Ergashev | F3: 69 | G3: ='Jogadores (1)'!C975 -> David Ospina | H3: ='Jogadores (1)'!D975 -> 77
A4: ='Jogadores (1)'!C293 -> Rui Silva | B4: ='Jogadores (1)'!D293 -> 81 | C4: ='Jogadores (1)'!C6934 -> Timothy Fayulu | D4: ='Jogadores (1)'!D6934 -> 67 | E4: Utkir Yusupov | F4: 70 | G4: ='Jogadores (1)'!C1227 -> Álvaro Montero | H4: ='Jogadores (1)'!D1227 -> 76
A5: ='Jogadores (1)'!C559 -> José Sá | B5: ='Jogadores (1)'!D559 -> 79 | C5: Matthieu Epolo | D5: 75 | E5: Abduvohid Nematov | F5: 71 | G5: Camilo Vargas | H5: 79
A6: ='Jogadores (1)'!C51 -> João Cancelo | B6: ='Jogadores (1)'!D51 -> 86 | C6: ='Jogadores (1)'!C1214 -> Arthur Masuaku | D6: ='Jogadores (1)'!D1214 -> 76 | E6: Rustamjon Ashurmatov | F6: 67 | G6: ='Jogadores (1)'!C1735 -> Juan David Cabal | H6: ='Jogadores (1)'!D1735 -> 74
A7: ='Jogadores (1)'!C214 -> Diogo Dalot | B7: ='Jogadores (1)'!D214 -> 82 | C7: ='Jogadores (1)'!C565 -> Chancel Mbemba | D7: ='Jogadores (1)'!D565 -> 79 | E7: Farrukh Sayfiev | F7: 66 | G7: ='Jogadores (1)'!C425 -> Daniel Muñoz | H7: ='Jogadores (1)'!D425 -> 80
A8: ='Jogadores (1)'!C186 -> Nuno Mendes | B8: ='Jogadores (1)'!D186 -> 83 | C8: ='Jogadores (1)'!C2367 -> Joris Kayembe | D8: ='Jogadores (1)'!D2367 -> 73 | E8: Umarbek Eshmurodov | F8: 67 | G8: Santiago Arias | H8: 74
A9: ='Jogadores (1)'!C370 -> Gonçalo Inácio | B9: ='Jogadores (1)'!D370 -> 80 | C9: ='Jogadores (2)'!B2546 -> Axel Tuanzebe | D9: ='Jogadores (2)'!C2546 -> 73 | E9: Khojiakbar Alijonov | F9: 68 | G9: ='Jogadores (1)'!C955 -> Johan Mojica | H9: ='Jogadores (1)'!D955 -> 77
A10: ='Jogadores (2)'!B810 -> Tomás Lemos Araújo | B10: ='Jogadores (2)'!C810 -> 78 | C10: ='Jogadores (2)'!B5535 -> Jeremy Ngakia | D10: ='Jogadores (2)'!C5535 -> 69 | E10: Sherzod Nasrullaev | F10: 70 | G10: ='Jogadores (1)'!C438 -> Davinson Sánchez | H10: ='Jogadores (1)'!D438 -> 80
A11: ='Jogadores (1)'!C3112 -> Renato Veiga | B11: ='Jogadores (1)'!D3112 -> 72 | C11: ='Jogadores (2)'!B434 -> Aaron Wan-Bissaka | D11: ='Jogadores (2)'!C434 -> 80 | E11: ='Jogadores (1)'!C2972 -> Abdukodir Khusanov | F11: 80 | G11: ='Jogadores (1)'!C1201 -> Deiver Machado | H11: ='Jogadores (1)'!D1201 -> 76
A12: ='Jogadores (1)'!C605 -> António Silva | B12: ='Jogadores (1)'!D605 -> 79 | C12: ='Jogadores (1)'!C7796 -> Rocky Bushiri | D12: ='Jogadores (1)'!D7796 -> 66 | E12: Jakhongir O'Rozov | F12: 65 | G12: ='Jogadores (1)'!C935 -> Jhon Lucumí | H12: ='Jogadores (1)'!D935 -> 77
A13: ='Jogadores (1)'!C39 -> Bruno Fernandes | B13: ='Jogadores (1)'!D39 -> 87 | C13: ='Jogadores (1)'!C3611 -> Edo Kayembe | D13: ='Jogadores (1)'!D3611 -> 71 | E13: Muhammadkodir Hamraliev | F13: 68 | G13: ='Jogadores (1)'!C4477 -> Yerson Mosquera | H13: ='Jogadores (1)'!D4477 -> 70
A14: ='Jogadores (1)'!C1344 -> Samu | B14: ='Jogadores (1)'!D1344 -> 75 | C14: ='Jogadores (2)'!B4003 -> Steve Kapuadi | D14: ='Jogadores (2)'!C4003 -> 71 | E14: Mukhammadrasul Abdumajidov | F14: 70 | G14: James Rodríguez | H14: 80
A15: ='Jogadores (1)'!C102 -> Rúben Neves | B15: ='Jogadores (1)'!D102 -> 84 | C15: Theo Bongonda | D15: 74 | E15: Behruzjon Karimov | F15: 66 | G15: ='Jogadores (1)'!C984 -> Juan Fernando Quintero | H15: ='Jogadores (1)'!D984 -> 77
A16: ='Jogadores (1)'!C172 -> Pedro Gonçalves | B16: ='Jogadores (1)'!D172 -> 83 | C16: ='Jogadores (1)'!C4548 -> Charles Pickel | D16: ='Jogadores (1)'!D4548 -> 70 | E16: Jamshid Iskanderov | F16: 62 | G16: ='Jogadores (1)'!C547 -> Jefferson Lerma | H16: ='Jogadores (1)'!D547 -> 79
A17: ='Jogadores (1)'!C76 -> Vitinha | B17: ='Jogadores (1)'!D76 -> 85 | C17: ='Jogadores (1)'!C617 -> Yoane Wissa | D17: ='Jogadores (1)'!D617 -> 79 | E17: Odiljon Xamrobekov | F17: 60 | G17: Jorge Carrascal | H17: 74
A18: ='Jogadores (1)'!C726 -> Matheus Nunes | B18: ='Jogadores (1)'!D726 -> 78 | C18: ='Jogadores (1)'!C364 -> Simon Banza | D18: ='Jogadores (1)'!D364 -> 80 | E18: Dostonbek Khamdamov | F18: 71 | G18: ='Jogadores (2)'!B755 -> Jhon Arias | H18: ='Jogadores (2)'!C755 -> 78
A19: ='Jogadores (1)'!C525 -> João Neves | B19: ='Jogadores (1)'!D525 -> 79 | C19: ='Jogadores (1)'!C1812 -> Meschack Elia | D19: ='Jogadores (1)'!D1812 -> 74 | E19: ='Jogadores (1)'!C5526 -> Otabek Shukurov | F19: ='Jogadores (1)'!D5526 -> 69 | G19: ='Jogadores (1)'!C1090 -> Jaminton Campaz | H19: ='Jogadores (1)'!D1090 -> 76
A20: ='Jogadores (1)'!C292 -> Ricardo Horta | B20: ='Jogadores (1)'!D292 -> 81 | C20: ='Jogadores (1)'!C2838 -> Grady Diangana | D20: ='Jogadores (1)'!D2838 -> 72 | E20: Azizjon G'aniyev | F20: 68 | G20: ='Jogadores (2)'!B489 -> Richard Ríos | H20: ='Jogadores (2)'!C489 -> 79
A21: Paulinho | B21: 78 | C21: ='Jogadores (2)'!B4700 -> Nathanaël Mbuku | D21: ='Jogadores (2)'!C4700 -> 70 | E21: Akmal Mozgovoy | F21: 68 | G21: ='Jogadores (2)'!B879 -> Kevin Castaño | H21: ='Jogadores (2)'!C879 -> 77
A22: ='Jogadores (1)'!C895 -> Gonçalo Guedes | B22: ='Jogadores (1)'!D895 -> 77 | C22: Fiston Mayele | D22: 70 | E22: Oston Urunov | F22: 72 | G22: ='Jogadores (2)'!B5979 -> Gustavo Puerta | H22: ='Jogadores (2)'!C5979 -> 68
A23: ='Jogadores (1)'!C551 -> Pedro Neto | B23: ='Jogadores (1)'!D551 -> 79 | C23: ='Jogadores (1)'!C7858 -> Brian Cipenga | D23: ='Jogadores (1)'!D7858 -> 66 | E23: Sherzod Temirov | F23: 62 | G23: Jhon Córdoba | H23: 77
A24: ='Jogadores (1)'!C794 -> Trincão | B24: ='Jogadores (1)'!D794 -> 78 | E24: Umarali Rakhmonaliev | F24: 71 | G24: Rafael Borré | H24: 76
A25: ='Jogadores (1)'!C390 -> João Félix | B25: ='Jogadores (1)'!D390 -> 80 | E25: Ibrokhim Ibragimov | F25: 68 | G25: ='Jogadores (1)'!C106 -> Luis Díaz | H25: ='Jogadores (1)'!D106 -> 84
A26: ='Jogadores (1)'!C588 -> Gonçalo Ramos | B26: ='Jogadores (1)'!D588 -> 79 | E26: Igor Sergeev | F26: 71 | G26: ='Jogadores (1)'!C2777 -> Johan Carbonero | H26: ='Jogadores (1)'!D2777 -> 72
A27: ='Jogadores (1)'!C680 -> Francisco Conceição | B27: ='Jogadores (1)'!D680 -> 78 | E27: ='Jogadores (1)'!C3207 -> Eldor Shomurodov | F27: ='Jogadores (1)'!D3207 -> 72 | G27: ='Jogadores (1)'!C1638 -> Luis Javier Suárez | H27: ='Jogadores (1)'!D1638 -> 75
E28: Alisher Odilov | F28: 72 | G28: ='Jogadores (1)'!C4281 -> Andrés Gómez | H28: ='Jogadores (1)'!D4281 -> 70
A31: Média | B31: =AVERAGE(B3:B27) -> 80.2 | C31: Média | D31: =AVERAGE(D3:D23) -> 72.52381 | E31: Média | F31: =AVERAGE(F3:F28) -> 68.576923 | G31: Média | H31: =AVERAGE(H3:H28) -> 76.230769

Sheet Grupo L
A2: =Seleções!B46 -> England | C2: =Seleções!B47 -> Croatia | E2: =Seleções!B48 -> Ghana | G2: =Seleções!B49 -> Panama
A3: ='Jogadores (1)'!C1634 -> Jason Steele | B3: ='Jogadores (1)'!D1634 -> 75 | C3: ='Jogadores (1)'!C414 -> Dominik Livaković | D3: ='Jogadores (1)'!D414 -> 80 | E3: ='Jogadores (1)'!C2670 -> Lawrence Ati Zigi | F3: ='Jogadores (1)'!D2670 -> 73 | G3: ='Jogadores (1)'!C4448 -> Luis Mejía | H3: ='Jogadores (1)'!D4448 -> 70
A4: ='Jogadores (1)'!C173 -> Jordan Pickford | B4: ='Jogadores (1)'!D173 -> 83 | C4: ='Jogadores (1)'!C5246 -> Karlo Letica | D4: ='Jogadores (1)'!D5246 -> 69 | E4: ='Jogadores (2)'!B7362 -> Joseph Anang | F4: ='Jogadores (2)'!C7362 -> 67 | G4: Orlando Mosquera | H4: 70
A5: ='Jogadores (1)'!C530 -> Dean Henderson | B5: ='Jogadores (1)'!D530 -> 79 | C5: ='Jogadores (1)'!C4529 -> Ivor Pandur | D5: ='Jogadores (1)'!D4529 -> 70 | E5: Benjamin Asare | F5: 75 | G5: César Samudio | H5: 70
A6: ='Jogadores (1)'!C331 -> Aaron Ramsdale | B6: ='Jogadores (1)'!D331 -> 81 | C6: ='Jogadores (1)'!C1380 -> Duje Ćaleta-Car | D6: ='Jogadores (1)'!D1380 -> 75 | E6: ='Jogadores (1)'!C506 -> Alexander Djiku | F6: ='Jogadores (1)'!D506 -> 79 | G6: Roderick Miller | H6: 64
A7: ='Jogadores (1)'!C2619 -> James Trafford | B7: ='Jogadores (1)'!D2619 -> 73 | C7: ='Jogadores (1)'!C2859 -> Martin Erlić | D7: ='Jogadores (1)'!D2859 -> 72 | E7: Derrick Luckassen | F7: 71 | G7: Éric Davis | H7: 67
A8: ='Jogadores (1)'!C2332 -> Lewis Hall | B8: ='Jogadores (1)'!D2332 -> 73 | C8: ='Jogadores (1)'!C1578 -> Marin Pongračić | D8: ='Jogadores (1)'!D1578 -> 75 | E8: ='Jogadores (1)'!C3767 -> Jerome Opoku | F8: ='Jogadores (1)'!D3767 -> 71 | G8: ='Jogadores (2)'!B5042 -> Andrés Andrade | H8: ='Jogadores (2)'!C5042 -> 69
A9: ='Jogadores (1)'!C417 -> Harry Maguire | B9: ='Jogadores (1)'!D417 -> 80 | C9: ='Jogadores (1)'!C1016 -> Josip Stanišić | D9: ='Jogadores (1)'!D1016 -> 77 | E9: Derrick Kohn | F9: 75 | G9: Michael Murillo | H9: 76
A10: ='Jogadores (1)'!C88 -> John Stones | B10: ='Jogadores (1)'!D88 -> 85 | C10: ='Jogadores (1)'!C1021 -> Josip Šutalo | D10: ='Jogadores (1)'!D1021 -> 77 | E10: ='Jogadores (1)'!C4452 -> Gideon Mensah | F10: ='Jogadores (1)'!D4452 -> 70 | G10: César Blackman | H10: 72
A11: ='Jogadores (1)'!C655 -> Dan Burn | B11: ='Jogadores (1)'!D655 -> 78 | C11: ='Jogadores (2)'!B3025 -> Ivan Smolčić | D11: ='Jogadores (2)'!C3025 -> 72 | E11: Patric Pfeiffer | F11: 70 | G11: Jorge Gutiérrez | H11: 69
A12: ='Jogadores (1)'!C314 -> Ezri Konsa | B12: ='Jogadores (1)'!D314 -> 81 | C12: ='Jogadores (1)'!C10720 -> Luka Vušković | D12: ='Jogadores (1)'!D10720 -> 64 | E12: Marvin Senaya | F12: 70 | G12: ='Jogadores (1)'!C7867 -> José Córdoba | H12: ='Jogadores (1)'!D7867 -> 66
A13: ='Jogadores (1)'!C188 -> Fikayo Tomori | B13: ='Jogadores (1)'!D188 -> 83 | C13: ='Jogadores (1)'!C54 -> Luka Modrić | D13: ='Jogadores (1)'!D54 -> 86 | E13: ='Jogadores (1)'!C9771 -> Jonas Adjetey | F13: ='Jogadores (1)'!D9771 -> 64 | G13: ='Jogadores (1)'!C6378 -> Jiovany Ramos | H13: ='Jogadores (1)'!D6378 -> 68
A14: ='Jogadores (1)'!C132 -> Benjamin White | B14: ='Jogadores (1)'!D132 -> 84 | C14: ='Jogadores (1)'!C431 -> Mario Pašalić | D14: ='Jogadores (1)'!D431 -> 80 | E14: ='Jogadores (2)'!B9693 -> Kojo Peprah Oppong | F14: ='Jogadores (2)'!C9693 -> 65 | G14: Martín Krug | H14: 70
A15: ='Jogadores (1)'!C306 -> Marc Guéhi | B15: ='Jogadores (1)'!D306 -> 81 | C15: ='Jogadores (1)'!C613 -> Nikola Vlašić | D15: ='Jogadores (1)'!D613 -> 79 | E15: ='Jogadores (1)'!C260 -> Thomas Partey | F15: ='Jogadores (1)'!D260 -> 82 | G15: ='Jogadores (1)'!C4279 -> Aníbal Godoy | H15: ='Jogadores (1)'!D4279 -> 70
A16: ='Jogadores (1)'!C3228 -> Djed Spence | B16: ='Jogadores (1)'!D3228 -> 72 | C16: ='Jogadores (1)'!C1541 -> Nikola Moro | D16: ='Jogadores (1)'!D1541 -> 75 | E16: ='Jogadores (1)'!C3771 -> Elisha Owusu | F16: ='Jogadores (1)'!D3771 -> 71 | G16: Christian Martínez | H16: 61
A17: ='Jogadores (1)'!C724 -> Tino Livramento | B17: ='Jogadores (1)'!D724 -> 78 | C17: ='Jogadores (1)'!C729 -> Lovro Majer | D17: ='Jogadores (1)'!D729 -> 78 | E17: ='Jogadores (1)'!C7507 -> Kwasi Sibo | F17: ='Jogadores (1)'!D7507 -> 67 | G17: Édgar Bárcenas | H17: 65
A18: ='Jogadores (1)'!C408 -> Jordan Henderson | B18: ='Jogadores (1)'!D408 -> 80 | C18: ='Jogadores (1)'!C1473 -> Kristijan Jakić | D18: ='Jogadores (1)'!D1473 -> 75 | E18: ='Jogadores (1)'!C3897 -> Ibrahim Sulemana | F18: ='Jogadores (1)'!D3897 -> 71 | G18: ='Jogadores (1)'!C3412 -> Adalberto Carrasquilla | H18: ='Jogadores (1)'!D3412 -> 71
A19: ='Jogadores (1)'!C36 -> Declan Rice | B19: ='Jogadores (1)'!D36 -> 87 | C19: ='Jogadores (1)'!C2082 -> Luka Sučić | D19: ='Jogadores (1)'!D2082 -> 74 | E19: ='Jogadores (2)'!B7007 -> Caleb Yirenkyi | F19: ='Jogadores (2)'!C7007 -> 67 | G19: José Luis Rodríguez | H19: 68
A20: ='Jogadores (2)'!B385 -> Elliot Anderson | B20: ='Jogadores (2)'!C385 -> 80 | C20: ='Jogadores (1)'!C1071 -> Martin Baturina | D20: ='Jogadores (1)'!D1071 -> 76 | E20: ='Jogadores (1)'!C1355 -> Jordan Ayew | F20: ='Jogadores (1)'!D1355 -> 75 | G20: ='Jogadores (1)'!C15000 -> Carlos Harvey | H20: ='Jogadores (1)'!D15000 -> 56
A21: ='Jogadores (1)'!C367 -> Harvey Barnes | B21: ='Jogadores (1)'!D367 -> 80 | C21: Toni Fruk | D21: 77 | E21: Daniel Agyei | F21: 75 | G21: Cecilio Waterman | H21: 71
A22: ='Jogadores (1)'!C17 -> Phil Foden | B22: ='Jogadores (1)'!D17 -> 88 | C22: ='Jogadores (1)'!C4669 -> Petar Sučić | D22: ='Jogadores (1)'!D4669 -> 70 | E22: ='Jogadores (1)'!C1289 -> Antoine Semenyo | F22: ='Jogadores (1)'!D1289 -> 76 | G22: ='Jogadores (1)'!C1795 -> Ismael Díaz | H22: ='Jogadores (1)'!D1795 -> 74
A23: ='Jogadores (1)'!C1444 -> James Garner | B23: ='Jogadores (1)'!D1444 -> 75 | C23: ='Jogadores (2)'!B298 -> Ivan Perišić | D23: ='Jogadores (2)'!C298 -> 81 | E23: ='Jogadores (1)'!C6115 -> Ransford-Yeboah Königsdörffer | F23: ='Jogadores (1)'!D6115 -> 68 | G23: ='Jogadores (1)'!C4235 -> José Fajardo | H23: ='Jogadores (1)'!D4235 -> 70
A24: ='Jogadores (1)'!C5 -> Jude Bellingham | B24: ='Jogadores (1)'!D5 -> 90 | C24: ='Jogadores (1)'!C316 -> Andrej Kramarić | D24: ='Jogadores (1)'!D316 -> 81 | E24: ='Jogadores (1)'!C3896 -> Kamaldeen Sulemana | F24: ='Jogadores (1)'!D3896 -> 71 | G24: César Yanis | H24: 66
A25: ='Jogadores (1)'!C84 -> Cole Palmer | B25: ='Jogadores (1)'!D84 -> 85 | C25: ='Jogadores (1)'!C652 -> Ante Budimir | D25: ='Jogadores (1)'!D652 -> 78 | E25: Fatawu Issahaku | F25: 76 | G25: José Kadir | H25: 68
A26: ='Jogadores (2)'!B2263 -> Nico O'Reilly | B26: ='Jogadores (2)'!C2263 -> 73 | C26: ='Jogadores (1)'!C1237 -> Petar Musa | D26: ='Jogadores (1)'!D1237 -> 76 | E26: ='Jogadores (1)'!C4866 -> Christopher Bonsu Baah | F26: ='Jogadores (1)'!D4866 -> 69
A27: ='Jogadores (1)'!C940 -> Kobbie Mainoo | B27: ='Jogadores (1)'!D940 -> 77 | C27: ='Jogadores (2)'!B3921 -> Igor Matanović | D27: ='Jogadores (2)'!C3921 -> 71 | E27: ='Jogadores (2)'!B4746 -> Prince Kwabena Adu | F27: ='Jogadores (2)'!C4746 -> 70
A28: ='Jogadores (1)'!C801 -> Adam Wharton | B28: ='Jogadores (1)'!D801 -> 78 | C28: ='Jogadores (2)'!B3800 -> Marco Pašalić | D28: ='Jogadores (2)'!C3800 -> 71
A29: ='Jogadores (1)'!C8 -> Harry Kane | B29: ='Jogadores (1)'!D8 -> 90
A30: ='Jogadores (1)'!C339 -> Dominic Solanke | B30: ='Jogadores (1)'!D339 -> 81
A31: ='Jogadores (1)'!C841 -> Dominic Calvert-Lewin | B31: ='Jogadores (1)'!D841 -> 77
A32: ='Jogadores (1)'!C203 -> Jarrod Bowen | B32: ='Jogadores (1)'!D203 -> 82
A33: ='Jogadores (1)'!C332 -> Marcus Rashford | B33: ='Jogadores (1)'!D332 -> 81
A34: ='Jogadores (1)'!C1601 -> Morgan Rogers | B34: ='Jogadores (1)'!D1601 -> 75
A35: ='Jogadores (1)'!C231 -> Anthony Gordon | B35: ='Jogadores (1)'!D231 -> 82
A36: ='Jogadores (1)'!C32 -> Bukayo Saka | B36: ='Jogadores (1)'!D32 -> 87
A37: ='Jogadores (1)'!C727 -> Noni Madueke | B37: ='Jogadores (1)'!D727 -> 78
A39: Média | B39: =AVERAGE(B3:B37) -> 80.342857 | C39: Média | D39: =AVERAGE(D3:D28) -> 75.346154 | E39: Média | F39: =AVERAGE(F3:F27) -> 71.52 | G39: Média | H39: =AVERAGE(H3:H25) -> 68.304348
